Workbook
Name criado: 'BASE CONE'!$J:$J
Name dtc: 'BASE CONE'!$K:$K
Name Item: 'BASE CONE'!$A:$A
Name jornada: 'BASE CONE'!$T:$T
Name release: 'BASE CONE'!$U:$U
Name resolvido: 'BASE CONE'!$M:$M
Name status: 'BASE CONE'!$E:$E
Name time: 'BASE CONE'!$F:$F

Sheet Visão Geral
J2: Times Locavia | K2: Melhor caso | M2: Pior caso | O2: QA
J3: ID.4 | K3: =INDEX(#REF!,MATCH(0,#REF!,0)) -> #REF! | L3: 7 | M3: =INDEX(#REF!,MATCH(0,#REF!,0)) -> #REF! | N3: =L3 -> 7 | O3: 46066 | P3: -3
J4: Scania | K4: =INDEX(#REF!,MATCH(0,#REF!,0)) -> #REF! | L4: 2 | M4: =INDEX(#REF!,MATCH(0,#REF!,0)) -> #REF! | N4: =L4 -> 2 | O4: Produção
J5: Fusca | K5: =INDEX(#REF!,MATCH(0,#REF!,0)) -> #REF! | L5: 5 | M5: =INDEX(#REF!,MATCH(0,#REF!,0)) -> #REF! | N5: =L5 -> 5 | O5: 46092 | P5: -3
J6: Optimus | K6: =INDEX(#REF!,MATCH(0,#REF!,0)) -> #REF! | L6: 8 | M6: =INDEX(#REF!,MATCH(0,#REF!,0)) -> #REF! | N6: =L6 -> 8
J7: Jetta | K7: =INDEX(#REF!,MATCH(0,#REF!,0)) -> #REF! | L7: 3 | M7: =INDEX(#REF!,MATCH(0,#REF!,0)) -> #REF! | N7: =L7 -> 3
J8: Brasília | K8: =INDEX(#REF!,MATCH(0,#REF!,0)) -> #REF! | L8: 1 | M8: =INDEX(#REF!,MATCH(0,#REF!,0)) -> #REF! | N8: =L8 -> 1
J9: Amarok | K9: =INDEX(#REF!,MATCH(0,#REF!,0)) -> #REF! | L9: 4 | M9: =INDEX(#REF!,MATCH(0,#REF!,0)) -> #REF! | N9: =L9 -> 4
J10: Tiguan | K10: =INDEX(#REF!,MATCH(0,#REF!,0)) -> #REF! | L10: 6 | M10: =INDEX(#REF!,MATCH(0,#REF!,0)) -> #REF! | N10: =L10 -> 6
J11: Up | K11: =INDEX(#REF!,MATCH(0,#REF!,0)) -> #REF! | L11: 9 | M11: =INDEX(#REF!,MATCH(0,#REF!,0)) -> #REF! | N11: =L11 -> 9
J12: Gol | K12: =INDEX(#REF!,MATCH(0,#REF!,0)) -> #REF! | L12: 10 | M12: =INDEX(#REF!,MATCH(0,#REF!,0)) -> #REF! | N12: 10
J13: Taos | K13: =INDEX(#REF!,MATCH(0,#REF!,0)) -> #REF! | L13: 11 | M13: =INDEX(#REF!,MATCH(0,#REF!,0)) -> #REF! | N13: 11
J14: Santana | K14: =INDEX(#REF!,MATCH(0,#REF!,0)) -> #REF! | L14: 12 | M14: =INDEX(#REF!,MATCH(0,#REF!,0)) -> #REF! | N14: 12
J15: Arquitetura | K15: =INDEX(#REF!,MATCH(0,#REF!,0)) -> #REF! | L15: 13 | M15: =INDEX(#REF!,MATCH(0,#REF!,0)) -> #REF! | N15: 13

Sheet Visão O4R1
J2: Times Locavia | K2: Melhor caso | M2: Pior caso | O2: QA
J3: ID.4 | K3: =INDEX(#REF!,MATCH(0,#REF!,0)) -> #REF! | L3: 7 | M3: =INDEX(#REF!,MATCH(0,#REF!,0)) -> #REF! | N3: =L3 -> 7 | O3: 46020 | P3: -3
J4: Scania | K4: =INDEX(#REF!,MATCH(0,#REF!,0)) -> #REF! | L4: 2 | M4: =INDEX(#REF!,MATCH(0,#REF!,0)) -> #REF! | N4: =L4 -> 2 | O4: Produção
J5: Fusca | K5: =INDEX(#REF!,MATCH(0,#REF!,0)) -> #REF! | L5: 5 | M5: =INDEX(#REF!,MATCH(0,#REF!,0)) -> #REF! | N5: =L5 -> 5 | O5: 46034 | P5: -3
J6: Optimus | K6: =INDEX(#REF!,MATCH(0,#REF!,0)) -> #REF! | L6: 8 | M6: =INDEX(#REF!,MATCH(0,#REF!,0)) -> #REF! | N6: =L6 -> 8
J7: Jetta | K7: =INDEX(#REF!,MATCH(0,#REF!,0)) -> #REF! | L7: 3 | M7: =INDEX(#REF!,MATCH(0,#REF!,0)) -> #REF! | N7: =L7 -> 3
J8: Brasília | K8: =INDEX(#REF!,MATCH(0,#REF!,0)) -> #REF! | L8: 1 | M8: =INDEX(#REF!,MATCH(0,#REF!,0)) -> #REF! | N8: =L8 -> 1
J9: Amarok (Plano B) | K9: =INDEX(#REF!,MATCH(0,#REF!,0)) -> #REF! | L9: 4 | M9: =INDEX(#REF!,MATCH(0,#REF!,0)) -> #REF! | N9: =L9 -> 4
J10: Tiguan | K10: =INDEX(#REF!,MATCH(0,#REF!,0)) -> #REF! | L10: 6 | M10: =INDEX(#REF!,MATCH(0,#REF!,0)) -> #REF! | N10: =L10 -> 6
J11: Up | K11: =INDEX(#REF!,MATCH(0,#REF!,0)) -> #REF! | L11: 9 | M11: =INDEX(#REF!,MATCH(0,#REF!,0)) -> #REF! | N11: =L11 -> 9
J12: Gol | K12: =INDEX(#REF!,MATCH(0,#REF!,0)) -> #REF! | L12: 10 | M12: =INDEX(#REF!,MATCH(0,#REF!,0)) -> #REF! | N12: 10
J13: Taos | K13: =INDEX(#REF!,MATCH(0,#REF!,0)) -> #REF! | L13: 11 | M13: =INDEX(#REF!,MATCH(0,#REF!,0)) -> #REF! | N13: 11
J14: Santana | K14: =INDEX(#REF!,MATCH(0,#REF!,0)) -> #REF! | L14: 12 | M14: =INDEX(#REF!,MATCH(0,#REF!,0)) -> #REF! | N14: 12
J15: Arquitetura | K15: =INDEX(#REF!,MATCH(0,#REF!,0)) -> #REF! | L15: 13 | M15: =INDEX(#REF!,MATCH(0,#REF!,0)) -> #REF! | N15: 13
J16: Tera | K16: =INDEX(#REF!,MATCH(0,#REF!,0)) -> #REF! | L16: 14 | M16: =INDEX(#REF!,MATCH(0,#REF!,0)) -> #REF! | N16: 14

Sheet Modelo Estrutura
A1: Cone: baseado na nossa vazão, chegaremos na data alvo? O que cabe até data alvo?
B2: Quantidade de Épicos | C2: 1 | D2: Épicos | E2: considerar apenas os épicos que estão no mapa de release
B3: Qtd de Story / Task / Bug / Spike | C3: 13 | D3: Story / Tarefa / Bug / Spike | E3: considerar o trabalho de todos os integrantes do time, inclsuive tasks de dívidas técnicas e automação
B4: Data início | C4: 45936 | D4: Primeria sprint da release
B5: Data fim esperada | C5: 46014 | D5: Data entregada release
B6: Melhor cenário | C6: 4 | D6: itens por semana | E6: considerar sempre as ultimas 4 sprints para atualizar os números
B7: Pior cenário | C7: 1 | D7: itens por semana | E7: considerar sempre as ultimas 4 sprints para atualizar os números
B8: Velocidade necessária | C8: 3 | D8: itens por semana
B9: Acompanhar a cada | C9: 7 | D9: dias
B11: Data do Início da Semana | C11: Se seguirmos nossa melhor vazão, quando entregamos? | D11: Se seguirmos nossa pior vazão, quando entregamos? | E11: Vazão ideal para atender à data | F11: Itens da sprint anterior que não foram concluídos | G11: Itens que entram em sprint pela primeira vez | H11: Itens que entraram na Sprint depois do planejamento, mas não são "Fura fila" | I11: Itens Fura-Fila que apareceram ao longo da Sprint | J11: Itens entregues na Sprint | K11: Itens que chegaram no backlog do time ao longo da semana, mas não na sprint | L11: Observações adicionais
B12: Não editar esses campos | G12: Preencher com os dados de cada semana
A13: Sprint | B13: Semana | C13: A fazer (melhor cenário) | D13: A fazer (pior cenário) | E13: A fazer (valocidade necessária) | F13: Itens Transbordo | G13: Itens Planejados (Planning) | H13: Itens não planejados na sprint | I13: (+) Expedite | J13: Realizado | K13: (+)(-) Escopo pro time | L13: OBSERVAÇÕES
B14: =C4 -> 45936 | C14: =C3 -> 13 | D14: =C3 -> 13 | E14: =C3 -> 13 | F14: 0 | G14: 3 | H14: 1 | I14: 1 | J14: 0 | K14: 5
B15: =B14+$C$9 -> 45943 | C15: =IF(OR(C14="",C14=0),"",IF(ISBLANK($J14),IF(C14+$K14+$I14-$C$6<=0,IF(AND(C14>0,C14<>""),0,""),C14+$K14+$I14-$C$6),IF((C14-$J14)+$K14+$I14<=0,IF(AND(C14>0,C14<>""),0,""),(C14-$J14)+$K14+$I14))) -> 19 | D15: =IF(OR(D14="",D14=0),"",IF(ISBLANK($J14),IF(D14+$K14+$I14-$C$7<=0,IF(AND(D14>0,D14<>""),0,""),D14+$K14+$I14-$C$7),IF((D14-$J14)+$K14+$I14<=0,IF(AND(D14>0,D14<>""),0,""),(D14-$J14)+$K14+$I14))) -> 19 | E15: =IF(OR(E14="",E14=0),"",IF(ISBLANK($J14),IF(E14+$K14+$I14-$C$8<=0,IF(AND(E14>0,E14<>""),0,""),E14+$K14+$I14-$C$8),IF((E14-$J14)+$K14+$I14<=0,IF(AND(E14>0,E14<>""),0,""),(E14-$J14)+$K14+$I14))) -> 19 | F15: =IF(J14="","",IF(G14+F14+H14+I14-J14<0,0,G14+F14+H14+I14-J14)) -> 5 | G15: 0 | H15: -1 | I15: 1 | J15: 1 | L15: Começamos entrega X
B16: =B15+$C$9 -> 45950 | C16: =IF(OR(C15="",C15=0),"",IF(ISBLANK(J15),IF(C15+K15+I15-$C$6<=0,IF(AND(C15>0,C15<>""),0,""),C15+K15+I15-$C$6),IF((C15-J15)+K15+I15<=0,IF(AND(C15>0,C15<>""),0,""),(C15-J15)+K15+I15))) -> 19 | D16: =IF(OR(D15="",D15=0),"",IF(ISBLANK($J15),IF(D15+$K15+$I15-$C$7<=0,IF(AND(D15>0,D15<>""),0,""),D15+$K15+$I15-$C$7),IF((D15-$J15)+$K15+$I15<=0,IF(AND(D15>0,D15<>""),0,""),(D15-$J15)+$K15+$I15))) -> 19 | E16: =IF(OR(E15="",E15=0),"",IF(ISBLANK($J15),IF(E15+$K15+$I15-$C$8<=0,IF(AND(E15>0,E15<>""),0,""),E15+$K15+$I15-$C$8),IF((E15-$J15)+$K15+$I15<=0,IF(AND(E15>0,E15<>""),0,""),(E15-$J15)+$K15+$I15))) -> 19 | F16: =IF(J15="","",IF(G15+F15+H15+I15-J15<0,0,G15+F15+H15+I15-J15)) -> 4 | G16: 3 | J16: 0
B17: =B16+$C$9 -> 45957 | C17: =IF(OR(C16="",C16=0),"",IF(ISBLANK(J16),IF(C16+K16+I16-$C$6<=0,IF(AND(C16>0,C16<>""),0,""),C16+K16+I16-$C$6),IF((C16-J16)+K16+I16<=0,IF(AND(C16>0,C16<>""),0,""),(C16-J16)+K16+I16))) -> 19 | D17: =IF(OR(D16="",D16=0),"",IF(ISBLANK($J16),IF(D16+$K16+$I16-$C$7<=0,IF(AND(D16>0,D16<>""),0,""),D16+$K16+$I16-$C$7),IF((D16-$J16)+$K16+$I16<=0,IF(AND(D16>0,D16<>""),0,""),(D16-$J16)+$K16+$I16))) -> 19 | E17: =IF(OR(E16="",E16=0),"",IF(ISBLANK($J16),IF(E16+$K16+$I16-$C$8<=0,IF(AND(E16>0,E16<>""),0,""),E16+$K16+$I16-$C$8),IF((E16-$J16)+$K16+$I16<=0,IF(AND(E16>0,E16<>""),0,""),(E16-$J16)+$K16+$I16))) -> 19 | F17: =IF(J16="","",IF(G16+F16+H16+I16-J16<0,0,G16+F16+H16+I16-J16)) -> 7 | J17: 2 | K17: 7
B18: =B17+$C$9 -> 45964 | C18: =IF(OR(C17="",C17=0),"",IF(ISBLANK(J17),IF(C17+K17+I17-$C$6<=0,IF(AND(C17>0,C17<>""),0,""),C17+K17+I17-$C$6),IF((C17-J17)+K17+I17<=0,IF(AND(C17>0,C17<>""),0,""),(C17-J17)+K17+I17))) -> 24 | D18: =IF(OR(D17="",D17=0),"",IF(ISBLANK($J17),IF(D17+$K17+$I17-$C$7<=0,IF(AND(D17>0,D17<>""),0,""),D17+$K17+$I17-$C$7),IF((D17-$J17)+$K17+$I17<=0,IF(AND(D17>0,D17<>""),0,""),(D17-$J17)+$K17+$I17))) -> 24 | E18: =IF(OR(E17="",E17=0),"",IF(ISBLANK($J17),IF(E17+$K17+$I17-$C$8<=0,IF(AND(E17>0,E17<>""),0,""),E17+$K17+$I17-$C$8),IF((E17-$J17)+$K17+$I17<=0,IF(AND(E17>0,E17<>""),0,""),(E17-$J17)+$K17+$I17))) -> 24 | F18: =IF(J17="","",IF(G17+F17+H17+I17-J17<0,0,G17+F17+H17+I17-J17)) -> 5 | J18: 1
B19: =B18+$C$9 -> 45971 | C19: =IF(OR(C18="",C18=0),"",IF(ISBLANK(J18),IF(C18+K18+I18-$C$6<=0,IF(AND(C18>0,C18<>""),0,""),C18+K18+I18-$C$6),IF((C18-J18)+K18+I18<=0,IF(AND(C18>0,C18<>""),0,""),(C18-J18)+K18+I18))) -> 23 | D19: =IF(OR(D18="",D18=0),"",IF(ISBLANK($J18),IF(D18+$K18+$I18-$C$7<=0,IF(AND(D18>0,D18<>""),0,""),D18+$K18+$I18-$C$7),IF((D18-$J18)+$K18+$I18<=0,IF(AND(D18>0,D18<>""),0,""),(D18-$J18)+$K18+$I18))) -> 23 | E19: =IF(OR(E18="",E18=0),"",IF(ISBLANK($J18),IF(E18+$K18+$I18-$C$8<=0,IF(AND(E18>0,E18<>""),0,""),E18+$K18+$I18-$C$8),IF((E18-$J18)+$K18+$I18<=0,IF(AND(E18>0,E18<>""),0,""),(E18-$J18)+$K18+$I18))) -> 23 | F19: =IF(J18="","",IF(G18+F18+H18+I18-J18<0,0,G18+F18+H18+I18-J18)) -> 4
B20: =B19+$C$9 -> 45978 | C20: =IF(OR(C19="",C19=0),"",IF(ISBLANK(J19),IF(C19+K19+I19-$C$6<=0,IF(AND(C19>0,C19<>""),0,""),C19+K19+I19-$C$6),IF((C19-J19)+K19+I19<=0,IF(AND(C19>0,C19<>""),0,""),(C19-J19)+K19+I19))) -> 19 | D20: =IF(OR(D19="",D19=0),"",IF(ISBLANK($J19),IF(D19+$K19+$I19-$C$7<=0,IF(AND(D19>0,D19<>""),0,""),D19+$K19+$I19-$C$7),IF((D19-$J19)+$K19+$I19<=0,IF(AND(D19>0,D19<>""),0,""),(D19-$J19)+$K19+$I19))) -> 22 | E20: =IF(OR(E19="",E19=0),"",IF(ISBLANK($J19),IF(E19+$K19+$I19-$C$8<=0,IF(AND(E19>0,E19<>""),0,""),E19+$K19+$I19-$C$8),IF((E19-$J19)+$K19+$I19<=0,IF(AND(E19>0,E19<>""),0,""),(E19-$J19)+$K19+$I19))) -> 20 | F20: =IF(J19="","",IF(G19+F19+H19+I19-J19<0,0,G19+F19+H19+I19-J19))
B21: =B20+$C$9 -> 45985 | C21: =IF(OR(C20="",C20=0),"",IF(ISBLANK(J20),IF(C20+K20+I20-$C$6<=0,IF(AND(C20>0,C20<>""),0,""),C20+K20+I20-$C$6),IF((C20-J20)+K20+I20<=0,IF(AND(C20>0,C20<>""),0,""),(C20-J20)+K20+I20))) -> 15 | D21: =IF(OR(D20="",D20=0),"",IF(ISBLANK($J20),IF(D20+$K20+$I20-$C$7<=0,IF(AND(D20>0,D20<>""),0,""),D20+$K20+$I20-$C$7),IF((D20-$J20)+$K20+$I20<=0,IF(AND(D20>0,D20<>""),0,""),(D20-$J20)+$K20+$I20))) -> 21 | E21: =IF(OR(E20="",E20=0),"",IF(ISBLANK($J20),IF(E20+$K20+$I20-$C$8<=0,IF(AND(E20>0,E20<>""),0,""),E20+$K20+$I20-$C$8),IF((E20-$J20)+$K20+$I20<=0,IF(AND(E20>0,E20<>""),0,""),(E20-$J20)+$K20+$I20))) -> 17 | F21: =IF(J20="","",IF(G20+F20+H20+I20-J20<0,0,G20+F20+H20+I20-J20))
B22: =B21+$C$9 -> 45992 | C22: =IF(OR(C21="",C21=0),"",IF(ISBLANK(J21),IF(C21+K21+I21-$C$6<=0,IF(AND(C21>0,C21<>""),0,""),C21+K21+I21-$C$6),IF((C21-J21)+K21+I21<=0,IF(AND(C21>0,C21<>""),0,""),(C21-J21)+K21+I21))) -> 11 | D22: =IF(OR(D21="",D21=0),"",IF(ISBLANK($J21),IF(D21+$K21+$I21-$C$7<=0,IF(AND(D21>0,D21<>""),0,""),D21+$K21+$I21-$C$7),IF((D21-$J21)+$K21+$I21<=0,IF(AND(D21>0,D21<>""),0,""),(D21-$J21)+$K21+$I21))) -> 20 | E22: =IF(OR(E21="",E21=0),"",IF(ISBLANK($J21),IF(E21+$K21+$I21-$C$8<=0,IF(AND(E21>0,E21<>""),0,""),E21+$K21+$I21-$C$8),IF((E21-$J21)+$K21+$I21<=0,IF(AND(E21>0,E21<>""),0,""),(E21-$J21)+$K21+$I21))) -> 14 | F22: =IF(J21="","",IF(G21+F21+H21+I21-J21<0,0,G21+F21+H21+I21-J21))
B23: =B22+$C$9 -> 45999 | C23: =IF(OR(C22="",C22=0),"",IF(ISBLANK(J22),IF(C22+K22+I22-$C$6<=0,IF(AND(C22>0,C22<>""),0,""),C22+K22+I22-$C$6),IF((C22-J22)+K22+I22<=0,IF(AND(C22>0,C22<>""),0,""),(C22-J22)+K22+I22))) -> 7 | D23: =IF(OR(D22="",D22=0),"",IF(ISBLANK($J22),IF(D22+$K22+$I22-$C$7<=0,IF(AND(D22>0,D22<>""),0,""),D22+$K22+$I22-$C$7),IF((D22-$J22)+$K22+$I22<=0,IF(AND(D22>0,D22<>""),0,""),(D22-$J22)+$K22+$I22))) -> 19 | E23: =IF(OR(E22="",E22=0),"",IF(ISBLANK($J22),IF(E22+$K22+$I22-$C$8<=0,IF(AND(E22>0,E22<>""),0,""),E22+$K22+$I22-$C$8),IF((E22-$J22)+$K22+$I22<=0,IF(AND(E22>0,E22<>""),0,""),(E22-$J22)+$K22+$I22))) -> 11 | F23: =IF(J22="","",IF(G22+F22+H22+I22-J22<0,0,G22+F22+H22+I22-J22))
B24: =B23+$C$9 -> 46006 | C24: =IF(OR(C23="",C23=0),"",IF(ISBLANK(J23),IF(C23+K23+I23-$C$6<=0,IF(AND(C23>0,C23<>""),0,""),C23+K23+I23-$C$6),IF((C23-J23)+K23+I23<=0,IF(AND(C23>0,C23<>""),0,""),(C23-J23)+K23+I23))) -> 3 | D24: =IF(OR(D23="",D23=0),"",IF(ISBLANK($J23),IF(D23+$K23+$I23-$C$7<=0,IF(AND(D23>0,D23<>""),0,""),D23+$K23+$I23-$C$7),IF((D23-$J23)+$K23+$I23<=0,IF(AND(D23>0,D23<>""),0,""),(D23-$J23)+$K23+$I23))) -> 18 | E24: =IF(OR(E23="",E23=0),"",IF(ISBLANK($J23),IF(E23+$K23+$I23-$C$8<=0,IF(AND(E23>0,E23<>""),0,""),E23+$K23+$I23-$C$8),IF((E23-$J23)+$K23+$I23<=0,IF(AND(E23>0,E23<>""),0,""),(E23-$J23)+$K23+$I23))) -> 8 | F24: =IF(J23="","",IF(G23+F23+H23+I23-J23<0,0,G23+F23+H23+I23-J23))
B25: =B24+$C$9 -> 46013 | C25: =IF(OR(C24="",C24=0),"",IF(ISBLANK(J24),IF(C24+K24+I24-$C$6<=0,IF(AND(C24>0,C24<>""),0,""),C24+K24+I24-$C$6),IF((C24-J24)+K24+I24<=0,IF(AND(C24>0,C24<>""),0,""),(C24-J24)+K24+I24))) -> 0 | D25: =IF(OR(D24="",D24=0),"",IF(ISBLANK($J24),IF(D24+$K24+$I24-$C$7<=0,IF(AND(D24>0,D24<>""),0,""),D24+$K24+$I24-$C$7),IF((D24-$J24)+$K24+$I24<=0,IF(AND(D24>0,D24<>""),0,""),(D24-$J24)+$K24+$I24))) -> 17 | E25: =IF(OR(E24="",E24=0),"",IF(ISBLANK($J24),IF(E24+$K24+$I24-$C$8<=0,IF(AND(E24>0,E24<>""),0,""),E24+$K24+$I24-$C$8),IF((E24-$J24)+$K24+$I24<=0,IF(AND(E24>0,E24<>""),0,""),(E24-$J24)+$K24+$I24))) -> 5 | F25: =IF(J24="","",IF(G24+F24+H24+I24-J24<0,0,G24+F24+H24+I24-J24))
B26: =B25+$C$9 -> 46020 | C26: =IF(OR(C25="",C25=0),"",IF(ISBLANK(J25),IF(C25+K25+I25-$C$6<=0,IF(AND(C25>0,C25<>""),0,""),C25+K25+I25-$C$6),IF((C25-J25)+K25+I25<=0,IF(AND(C25>0,C25<>""),0,""),(C25-J25)+K25+I25))) | D26: =IF(OR(D25="",D25=0),"",IF(ISBLANK($J25),IF(D25+$K25+$I25-$C$7<=0,IF(AND(D25>0,D25<>""),0,""),D25+$K25+$I25-$C$7),IF((D25-$J25)+$K25+$I25<=0,IF(AND(D25>0,D25<>""),0,""),(D25-$J25)+$K25+$I25))) -> 16 | E26: =IF(OR(E25="",E25=0),"",IF(ISBLANK($J25),IF(E25+$K25+$I25-$C$8<=0,IF(AND(E25>0,E25<>""),0,""),E25+$K25+$I25-$C$8),IF((E25-$J25)+$K25+$I25<=0,IF(AND(E25>0,E25<>""),0,""),(E25-$J25)+$K25+$I25))) -> 2 | F26: =IF(J25="","",IF(G25+F25+H25+I25-J25<0,0,G25+F25+H25+I25-J25))
B27: =B26+$C$9 -> 46027 | C27: =IF(OR(C26="",C26=0),"",IF(ISBLANK(J26),IF(C26+K26+I26-$C$6<=0,IF(AND(C26>0,C26<>""),0,""),C26+K26+I26-$C$6),IF((C26-J26)+K26+I26<=0,IF(AND(C26>0,C26<>""),0,""),(C26-J26)+K26+I26))) | D27: =IF(OR(D26="",D26=0),"",IF(ISBLANK($J26),IF(D26+$K26+$I26-$C$7<=0,IF(AND(D26>0,D26<>""),0,""),D26+$K26+$I26-$C$7),IF((D26-$J26)+$K26+$I26<=0,IF(AND(D26>0,D26<>""),0,""),(D26-$J26)+$K26+$I26))) -> 15 | E27: =IF(OR(E26="",E26=0),"",IF(ISBLANK($J26),IF(E26+$K26+$I26-$C$8<=0,IF(AND(E26>0,E26<>""),0,""),E26+$K26+$I26-$C$8),IF((E26-$J26)+$K26+$I26<=0,IF(AND(E26>0,E26<>""),0,""),(E26-$J26)+$K26+$I26))) -> 0 | F27: =IF(J26="","",IF(G26+F26+H26+I26-J26<0,0,G26+F26+H26+I26-J26))
B28: =B27+$C$9 -> 46034 | C28: =IF(OR(C27="",C27=0),"",IF(ISBLANK(J27),IF(C27+K27+I27-$C$6<=0,IF(AND(C27>0,C27<>""),0,""),C27+K27+I27-$C$6),IF((C27-J27)+K27+I27<=0,IF(AND(C27>0,C27<>""),0,""),(C27-J27)+K27+I27))) | D28: =IF(OR(D27="",D27=0),"",IF(ISBLANK($J27),IF(D27+$K27+$I27-$C$7<=0,IF(AND(D27>0,D27<>""),0,""),D27+$K27+$I27-$C$7),IF((D27-$J27)+$K27+$I27<=0,IF(AND(D27>0,D27<>""),0,""),(D27-$J27)+$K27+$I27))) -> 14 | E28: =IF(OR(E27="",E27=0),"",IF(ISBLANK($J27),IF(E27+$K27+$I27-$C$8<=0,IF(AND(E27>0,E27<>""),0,""),E27+$K27+$I27-$C$8),IF((E27-$J27)+$K27+$I27<=0,IF(AND(E27>0,E27<>""),0,""),(E27-$J27)+$K27+$I27))) | F28: =IF(J27="","",IF(G27+F27+H27+I27-J27<0,0,G27+F27+H27+I27-J27))
B29: =B28+$C$9 -> 46041 | C29: =IF(OR(C28="",C28=0),"",IF(ISBLANK(J28),IF(C28+K28+I28-$C$6<=0,IF(AND(C28>0,C28<>""),0,""),C28+K28+I28-$C$6),IF((C28-J28)+K28+I28<=0,IF(AND(C28>0,C28<>""),0,""),(C28-J28)+K28+I28))) | D29: =IF(OR(D28="",D28=0),"",IF(ISBLANK($J28),IF(D28+$K28+$I28-$C$7<=0,IF(AND(D28>0,D28<>""),0,""),D28+$K28+$I28-$C$7),IF((D28-$J28)+$K28+$I28<=0,IF(AND(D28>0,D28<>""),0,""),(D28-$J28)+$K28+$I28))) -> 13 | E29: =IF(OR(E28="",E28=0),"",IF(ISBLANK($J28),IF(E28+$K28+$I28-$C$8<=0,IF(AND(E28>0,E28<>""),0,""),E28+$K28+$I28-$C$8),IF((E28-$J28)+$K28+$I28<=0,IF(AND(E28>0,E28<>""),0,""),(E28-$J28)+$K28+$I28))) | F29: =IF(J28="","",IF(G28+F28+H28+I28-J28<0,0,G28+F28+H28+I28-J28))
B30: =B29+$C$9 -> 46048 | C30: =IF(OR(C29="",C29=0),"",IF(ISBLANK(J29),IF(C29+K29+I29-$C$6<=0,IF(AND(C29>0,C29<>""),0,""),C29+K29+I29-$C$6),IF((C29-J29)+K29+I29<=0,IF(AND(C29>0,C29<>""),0,""),(C29-J29)+K29+I29))) | D30: =IF(OR(D29="",D29=0),"",IF(ISBLANK($J29),IF(D29+$K29+$I29-$C$7<=0,IF(AND(D29>0,D29<>""),0,""),D29+$K29+$I29-$C$7),IF((D29-$J29)+$K29+$I29<=0,IF(AND(D29>0,D29<>""),0,""),(D29-$J29)+$K29+$I29))) -> 12 | E30: =IF(OR(E29="",E29=0),"",IF(ISBLANK($J29),IF(E29+$K29+$I29-$C$8<=0,IF(AND(E29>0,E29<>""),0,""),E29+$K29+$I29-$C$8),IF((E29-$J29)+$K29+$I29<=0,IF(AND(E29>0,E29<>""),0,""),(E29-$J29)+$K29+$I29))) | F30: =IF(J29="","",IF(G29+F29+H29+I29-J29<0,0,G29+F29+H29+I29-J29))
... B54: =B53+$C$9 -> 46216 | C54: =IF(OR(C53="",C53=0),"",IF(ISBLANK(J53),IF(C53+K53+I53-$C$6<=0,IF(AND(C53>0,C53<>""),0,""),C53+K53+I53-$C$6),IF((C53-J53)+K53+I53<=0,IF(AND(C53>0,C53<>""),0,""),(C53-J53)+K53+I53))) | D54: =IF(OR(D53="",D53=0),"",IF(ISBLANK($J53),IF(D53+$K53+$I53-$C$7<=0,IF(AND(D53>0,D53<>""),0,""),D53+$K53+$I53-$C$7),IF((D53-$J53)+$K53+$I53<=0,IF(AND(D53>0,D53<>""),0,""),(D53-$J53)+$K53+$I53))) | E54: =IF(OR(E53="",E53=0),"",IF(ISBLANK($J53),IF(E53+$K53+$I53-$C$8<=0,IF(AND(E53>0,E53<>""),0,""),E53+$K53+$I53-$C$8),IF((E53-$J53)+$K53+$I53<=0,IF(AND(E53>0,E53<>""),0,""),(E53-$J53)+$K53+$I53))) | F54: =IF(J53="","",IF(G53+F53+H53+I53-J53<0,0,G53+F53+H53+I53-J53))
B111: =IF(B110="","",IF(B110+$C$9<=$C$5,B110+$C$9,"")) | C111: =IF(B111<>"",C110-$C$2/COUNT($B$17:$B$510),"")
B112: =IF(B111="","",IF(B111+$C$9<=$C$5,B111+$C$9,"")) | C112: =IF(B112<>"",C111-$C$2/COUNT($B$17:$B$510),"")
B113: =IF(B112="","",IF(B112+$C$9<=$C$5,B112+$C$9,"")) | C113: =IF(B113<>"",C112-$C$2/COUNT($B$17:$B$510),"")
B114: =IF(B113="","",IF(B113+$C$9<=$C$5,B113+$C$9,"")) | C114: =IF(B114<>"",C113-$C$2/COUNT($B$17:$B$510),"")
B115: =IF(B114="","",IF(B114+$C$9<=$C$5,B114+$C$9,"")) | C115: =IF(B115<>"",C114-$C$2/COUNT($B$17:$B$510),"")
B116: =IF(B115="","",IF(B115+$C$9<=$C$5,B115+$C$9,"")) | C116: =IF(B116<>"",C115-$C$2/COUNT($B$17:$B$510),"")
B117: =IF(B116="","",IF(B116+$C$9<=$C$5,B116+$C$9,"")) | C117: =IF(B117<>"",C116-$C$2/COUNT($B$17:$B$510),"")
B118: =IF(B117="","",IF(B117+$C$9<=$C$5,B117+$C$9,"")) | C118: =IF(B118<>"",C117-$C$2/COUNT($B$17:$B$510),"")
B119: =IF(B118="","",IF(B118+$C$9<=$C$5,B118+$C$9,"")) | C119: =IF(B119<>"",C118-$C$2/COUNT($B$17:$B$510),"")
B120: =IF(B119="","",IF(B119+$C$9<=$C$5,B119+$C$9,"")) | C120: =IF(B120<>"",C119-$C$2/COUNT($B$17:$B$510),"")
B121: =IF(B120="","",IF(B120+$C$9<=$C$5,B120+$C$9,"")) | C121: =IF(B121<>"",C120-$C$2/COUNT($B$17:$B$510),"")
B122: =IF(B121="","",IF(B121+$C$9<=$C$5,B121+$C$9,"")) | C122: =IF(B122<>"",C121-$C$2/COUNT($B$17:$B$510),"")
... B511: =IF(B510="","",IF(B510+$C$9<=$C$5,B510+$C$9,"")) | C511: =IF(B511<>"",C510-$C$2/COUNT($B$17:$B$510),"")

Sheet LEIA-ME
A1: Times | B1: ESCOPO | C1: Release
A2: UP | B2: WHATSAPP | C2: O4R
A3: NIVUS | B3: COMERCIAL | C3: O4R1
A4: TERA | B4: FATURAMENTO | C4: O4R2
A5: GOL | B5: VENDAS_ASSISTIDAS | C5: BAF
A6: OPTIMUS | B6: CONTRATOS | C6: BAF-QW
A7: AMAROK | B7: VENDAS_AUTO-ATENDIMENTO
A8: SANTANA | B8: RESSARCIMENTO
A9: TAOS | B9: CREDITO
A10: FUSCA | B10: SALESFORCE_PÓSVEND
A11: PARATI | B11: MIGRAÇÃO
A12: D.LAKE DOMINIO | B12: LAKE-ESTRUTURANTE
B13: RISCO
B14: COBRANÇA
B15: PROPOSTA

Sheet BASE CONE
A1: Tipo de item | B1: Chave da item | C1: ID da item | D1: Resumo | E1: Status | F1: Campo personalizado (Time) | G1: Campo personalizado (Jornada) | H1: Campo personalizado (Jornada)_1 | I1: Campo personalizado (Jornada)_2 | J1: Criado | K1: Campo personalizado (Data de Compromentimento) | L1: Campo personalizado (Start date) | M1: Resolvido | N1: Campo personalizado (Release) | O1: Campo personalizado (Release)_3 | P1: Campo personalizado (Release)_4 | Q1: Pai | R1: Chave pai | S1: Parent summary | T1: time | U1: release
A2: História | B2: WA-747 | C2: 156507 | D2: [Blip][AssinsCar.][Pós venda][Abertura de ocorrência] Meu Contrato, Documento - Solicitação de segunda via de contrato | E2: 1. Backlog | G2: WHATSAPP | J2: 46084.455 | K2: 45992.64 | L2: 45993 | N2: O4R1 | Q2: 156472 | R2: JAC-1528 | S2: [Blip][AssinsCar.] Pós venda - Abertura de ocorrência por área | T2: WHATSAPP;; | U2: O4R1;;
A3: Tarefa | B3: WA-696 | C3: 153376 | D3: [Blip][S&D Colab.][Comercial][Tabela de valor] Ajuste na tabela de preço - Lead e Renovação | E3: DESENV CONCLUIDO | F3: UP | G3: WHATSAPP | J3: 46066.617 | K3: 46066 | L3: 46066 | M3: 46076.447 | N3: O4R1 | Q3: 75650 | R3: WA-334 | S3: [Blip][S&D Colab.][R1] Comercial - Qualificação de Lead | T3: WHATSAPP;; | U3: O4R1;;
A4: História | B4: WA-676 | C4: 150279 | D4: [Blip][S&D Colab.][Pós vendas][Melhoria] Fluxo da FAQ perguntas e resposta | E4: 1. Backlog | G4: WHATSAPP | J4: 46056.426 | N4: O4R2 | Q4: 148376 | R4: WA-642 | S4: [Blip][S&D Colab.][R3] Pós venda - Abertura de ocorrência por área | T4: WHATSAPP;; | U4: O4R2;;
A5: História | B5: WA-669 | C5: 150097 | D5: [Blip][S&D Colab.][Click-tracker] Implementar studar a documentação da aplicação da Blip - Click Tracker | E5: DESENV CONCLUIDO | F5: UP | G5: WHATSAPP | J5: 46055.591 | K5: 46063.729 | L5: 46063 | M5: 46076.599 | N5: O4R2 | Q5: 148350 | R5: WA-624 | S5: [Blip][S&D Colab.][R3] [Cross] Estrutura do bot | T5: WHATSAPP;; | U5: O4R2;;
A6: Spike | B6: WA-660 | C6: 148789 | D6: [Blip][S&D Colaboradores][Comercial][Criação] UX -Desenho da jornada do no fluxo comercial - Qualificação de lead | E6: DESENV CONCLUIDO | F6: UP | G6: Comercial | J6: 46049.481 | K6: 46055 | L6: 46062 | M6: 46094.387 | N6: O4R2 | Q6: 148792 | R6: WA-661 | S6: [Blip][S&D Colab.][R3] Comercial - Qualificação de Lead | T6: Comercial;; | U6: O4R2;;
A7: Spike | B7: WA-659 | C7: 148788 | D7: [Blip][S&D Colaboradores][Comercial][Discovey] Melhoria no fluxo comercial - Qualificação de lead | E7: DESENV CONCLUIDO | F7: UP | G7: Comercial | J7: 46049.479 | K7: 46049 | L7: 46050 | M7: 46062.446 | N7: O4R2 | Q7: 148792 | R7: WA-661 | S7: [Blip][S&D Colab.][R3] Comercial - Qualificação de Lead | T7: Comercial;; | U7: O4R2;;
A8: História | B8: WA-656 | C8: 148784 | D8: [Blip][S&D Colab.][Comercial][Carrossel] Desenvolver o flow do componente do carrossel dentro da meta | E8: DESENV CONCLUIDO | F8: UP | G8: WHATSAPP | J8: 46049.471 | K8: 46073.52 | L8: 46073 | M8: 46076.592 | N8: O4R2 | Q8: 148350 | R8: WA-624 | S8: [Blip][S&D Colab.][R3] [Cross] Estrutura do bot | T8: WHATSAPP;; | U8: O4R2;;
A9: História | B9: WA-654 | C9: 148778 | D9: [Blip][S&D Colab.][Comercial][Carrossel][Flows] Converter a imagem para consumo do carrossel | E9: DESENV CONCLUIDO | F9: UP | G9: WHATSAPP | J9: 46049.458 | K9: 46076.8 | L9: 46076 | M9: 46083.43 | N9: O4R2 | Q9: 148350 | R9: WA-624 | S9: [Blip][S&D Colab.][R3] [Cross] Estrutura do bot | T9: WHATSAPP;; | U9: O4R2;;
A10: História | B10: WA-620 | C10: 148208 | D10: [Blip][S&D Colab.][Click-tracker][Estudo] Estudar a documentação da aplicação da Blip - Click Tracker | E10: DESENV CONCLUIDO | F10: UP | G10: WHATSAPP | J10: 46044.615 | K10: 46049.509 | L10: 46049 | M10: 46055.591 | N10: O4R2 | Q10: 148350 | R10: WA-624 | S10: [Blip][S&D Colab.][R3] [Cross] Estrutura do bot | T10: WHATSAPP;; | U10: O4R2;;
A11: História | B11: WA-618 | C11: 148197 | D11: [Blip][S&D Colab.][Pós vendas][Tag] Tagamento do fluxo de pos vendas | E11: DESENV CONCLUIDO | F11: UP | G11: Comercial | J11: 46044.592 | K11: 46044.885 | L11: 46044 | M11: 46073.39 | N11: O4R2 | Q11: 148376 | R11: WA-642 | S11: [Blip][S&D Colab.][R3] Pós venda - Abertura de ocorrência por área | T11: Comercial;; | U11: O4R2;;
A12: Tarefa | B12: WA-611 | C12: 145760 | D12: [Blip][S&D Colab.][Comercial][Tabela de valor] Ajuste na tabela de preço - Lead e Renovação | E12: DESENV CONCLUIDO | F12: UP | G12: WHATSAPP | J12: 46030.41 | K12: 46030.539 | L12: 46030.539 | M12: 46030.456 | N12: O4R1 | Q12: 75650 | R12: WA-334 | S12: [Blip][S&D Colab.][R1] Comercial - Qualificação de Lead | T12: WHATSAPP;; | U12: O4R1;;
A13: Tarefa | B13: WA-608 | C13: 141520 | D13: [Blip][S&D Colab.][Pós venda][Abertura de ocorrência] Fim de contrato - Devolução veículo - Ajuste | E13: DESENV CONCLUIDO | G13: WHATSAPP | J13: 46022.424 | K13: 46022 | L13: 46022 | M13: 46027.575 | N13: O4R1 | Q13: 75650 | R13: WA-334 | S13: [Blip][S&D Colab.][R1] Comercial - Qualificação de Lead | T13: WHATSAPP;; | U13: O4R1;;
A14: Tarefa | B14: WA-594 | C14: 140573 | D14: [Blip][S&D Colab.][Comercial][Renovação] Ajuste no fluxo - Incluir FAQ | E14: DESENV CONCLUIDO | F14: UP | G14: WHATSAPP | J14: 46020.469 | K14: 46020.758 | L14: 46020.758 | M14: 46030.631 | N14: O4R1 | Q14: 75650 | R14: WA-334 | S14: [Blip][S&D Colab.][R1] Comercial - Qualificação de Lead | T14: WHATSAPP;; | U14: O4R1;;
A15: Tarefa | B15: WA-593 | C15: 140572 | D15: [Blip][S&D Colab.][Comercial][Renovação] Ajuste no fluxo - Renovação de contrato | E15: DESENV CONCLUIDO | F15: UP | G15: WHATSAPP | J15: 46020.469 | K15: 46020.625 | L15: 46020.625 | M15: 46021.662 | N15: O4R1 | Q15: 75650 | R15: WA-334 | S15: [Blip][S&D Colab.][R1] Comercial - Qualificação de Lead | T15: WHATSAPP;; | U15: O4R1;;
A16: História | B16: WA-550 | C16: 129142 | D16: [Blip][S&D Colab.][Autosserviço] 2º via do boleto Investigação e correção de fluxos causando lentidão no fluxo de boleto (BLiP) | E16: DESENV CONCLUIDO | F16: UP | G16: WHATSAPP | J16: 46006.39 | K16: 46006.517 | L16: 46009 | M16: 46027.381 | N16: O4R1 | Q16: 75664 | R16: WA-348 | S16: [Blip][S&D Colab.][R1] Autosserviço - Financeiro - Solicitação boleto | T16: WHATSAPP;; | U16: O4R1;;
A17: Tarefa | B17: WA-543 | C17: 121717 | D17: [Blip][S&D Colab.] [Pós venda] Saudação inicial cliente sem placa | E17: DESENV CONCLUIDO | F17: UP | G17: WHATSAPP | J17: 45996.598 | K17: 46000.556 | L17: 46000 | M17: 46003.608 | N17: O4R1 | Q17: 71048 | R17: WA-274 | S17: [Blip][S&D Colab.][R1] Inicio bot | T17: WHATSAPP;; | U17: O4R1;;
A18: História | B18: WA-537 | C18: 119794 | D18: [Blip][S&D Colab.][Pós venda][Abertura de ocorrência] Desenvolvimento jornada Assistência 24h | E18: DESENV CONCLUIDO | F18: UP | G18: WHATSAPP | J18: 45994.514 | K18: 46014.503 | L18: 46015 | M18: 46031.485 | N18: O4R1 | Q18: 71032 | R18: WA-259 | S18: [Blip][S&D Colab.][R1] Pós venda - Abertura de ocorrência por área | T18: WHATSAPP;; | U18: O4R1;;
A19: História | B19: WA-534 | C19: 119790 | D19: [Blip][S&D Colab.][Pós venda][Abertura de ocorrência] Desenvolvimento jornada de manutenção | E19: DESENV CONCLUIDO | F19: UP | G19: WHATSAPP | J19: 45994.512 | K19: 46006.523 | L19: 46006 | M19: 46030.441 | N19: O4R1 | Q19: 71032 | R19: WA-259 | S19: [Blip][S&D Colab.][R1] Pós venda - Abertura de ocorrência por área | T19: WHATSAPP;; | U19: O4R1;;
A20: Spike | B20: WA-528 | C20: 118422 | D20: [Blip][S&D Colab.][Pós venda][Abertura de ocorrência] UX desenho da jornada - Assistência 24h | E20: DESENV CONCLUIDO | F20: UP | G20: Pos_venda | J20: 45993.801 | K20: 46006.535 | L20: 46009 | M20: 46010.725 | N20: O4R1 | Q20: 71032 | R20: WA-259 | S20: [Blip][S&D Colab.][R1] Pós venda - Abertura de ocorrência por área | T20: Pos_venda;; | U20: O4R1;;
A21: Spike | B21: WA-527 | C21: 118421 | D21: [Blip][S&D Colab.][Pós venda][Abertura de ocorrência] UX desenho da jornada - Manutenção | E21: DESENV CONCLUIDO | F21: UP | G21: Pos_venda | J21: 45993.8 | K21: 46001.833 | L21: 46001 | M21: 46006.378 | N21: O4R1 | Q21: 71032 | R21: WA-259 | S21: [Blip][S&D Colab.][R1] Pós venda - Abertura de ocorrência por área | T21: Pos_venda;; | U21: O4R1;;
A22: Tarefa | B22: WA-523 | C22: 116465 | D22: [Blip][S&D Colab.][Pós venda][Abertura de ocorrência] Debito técnico - Fluxo de Devolução de veiculo | E22: DESENV CONCLUIDO | F22: UP | G22: Pos_venda | J22: 45992.415 | K22: 45992.64 | L22: 45993 | M22: 46001.701 | N22: O4R1 | Q22: 71032 | R22: WA-259 | S22: [Blip][S&D Colab.][R1] Pós venda - Abertura de ocorrência por área | T22: Pos_venda;; | U22: O4R1;;
A23: Spike | B23: WA-504 | C23: 110041 | D23: [Blip][S&D Colab.][Comercial][Renovação] UX desenho da jornada -Renovação de contrato | E23: DESENV CONCLUIDO | F23: UP | G23: Pos_venda | J23: 45986.435 | K23: 45987.781 | L23: 45987.781 | M23: 45987.656 | N23: O4R1 | Q23: 71032 | R23: WA-259 | S23: [Blip][S&D Colab.][R1] Pós venda - Abertura de ocorrência por área | T23: Pos_venda;; | U23: O4R1;;
A24: Spike | B24: WA-503 | C24: 110040 | D24: [Blip][S&D Colab.][Pós venda][Abertura de ocorrência] UX desenho da jornada -Fim de contrato - 2 via de contrato | E24: DESENV CONCLUIDO | F24: UP | G24: Pos_venda | J24: 45986.435 | K24: 45999.747 | L24: 45999 | M24: 45999.622 | N24: O4R1 | Q24: 71032 | R24: WA-259 | S24: [Blip][S&D Colab.][R1] Pós venda - Abertura de ocorrência por área | T24: Pos_venda;; | U24: O4R1;;
A25: Tarefa | B25: WA-488 | C25: 103095 | D25: [S&D Colab.][4] Desenvolvimento arvore de saudação - Não recebeu o veiculo | E25: DESENV CONCLUIDO | F25: UP | G25: WHATSAPP | J25: 45979.441 | K25: 45985.499 | L25: 45985.499 | M25: 45989.385 | N25: O4R1 | Q25: 71032 | R25: WA-259 | S25: [Blip][S&D Colab.][R1] Pós venda - Abertura de ocorrência por área | T25: WHATSAPP;; | U25: O4R1;;
A26: Spike | B26: WA-473 | C26: 99291 | D26: [Blip][S&D Colab.][Pós venda][Abertura de ocorrência] UX desenho da jornada -Manutenção - Direcionamento para a ticket | E26: DESENV CONCLUIDO | F26: UP | G26: Pos_venda | J26: 45975.713 | K26: 45978.652 | L26: 45978.652 | M26: 45985.384 | N26: O4R1 | O26: Release_01 | Q26: 71032 | R26: WA-259 | S26: [Blip][S&D Colab.][R1] Pós venda - Abertura de ocorrência por área | T26: Pos_venda;; | U26: O4R1;Release_01;
A27: Spike | B27: WA-469 | C27: 99275 | D27: [Blip][S&D Colab.][HSM][Multas] Disparo endpoint de disparo | E27: DESENV CONCLUIDO | F27: UP | G27: Pos_venda | J27: 45975.687 | K27: 45978.753 | L27: 45979.715 | M27: 45982.668 | N27: O4R1 | Q27: 76935 | R27: WA-401 | S27: [Blip][S&D Colab.][R3] Multas - Disparos de mensagens ativas | T27: Pos_venda;; | U27: O4R1;;
A28: Spike | B28: WA-463 | C28: 94185 | D28: [Blip][S&D Colab.][Autosserviço] UX desenho da arvore de Solicitação segunda via da CRLV | E28: DESENV CONCLUIDO | F28: UP | G28: Migra_Blip | H28: Pos_venda | I28: WHATSAPP | J28: 45972.467 | K28: 45979.917 | L28: 45982.183 | M28: 45985.385 | N28: O4R1 | O28: Release_01 | Q28: 75678 | R28: WA-362 | S28: [Blip][S&D Colab.][R1] Autosserviço - Doc. do veículo - CRLV | T28: Migra_Blip;Pos_venda;WHATSAPP | U28: O4R1;Release_01;
A29: História | B29: WA-462 | C29: 90829 | D29: [Blip][S&D Colab.][Comercial][Renovação] Renovação de contrato | E29: DESENV CONCLUIDO | F29: UP | G29: WHATSAPP | J29: 45968.528 | K29: 45980.494 | L29: 45982.517 | M29: 45989.385 | N29: O4R1 | Q29: 75650 | R29: WA-334 | S29: [Blip][S&D Colab.][R1] Comercial - Qualificação de Lead | T29: WHATSAPP;; | U29: O4R1;;
A30: Spike | B30: WA-444 | C30: 89302 | D30: [Blip][S&D Colab.][Pós venda][Abertura de ocorrência] UX desenho da jornada - Fim de contrato - Devolução veículo | E30: DESENV CONCLUIDO | F30: UP | G30: Migra_Blip | H30: Pos_venda | I30: WHATSAPP | J30: 45967.864 | K30: 45978.651 | L30: 45978.651 | M30: 45985.384 | N30: O4R1 | Q30: 71032 | R30: WA-259 | S30: [Blip][S&D Colab.][R1] Pós venda - Abertura de ocorrência por área | T30: Migra_Blip;Pos_venda;WHATSAPP | U30: O4R1;;
A31: História | B31: WA-435 | C31: 89234 | D31: [Blip][S&D Colab.][Pós venda][Abertura de ocorrência] Perguntas frequentes | E31: DESENV CONCLUIDO | F31: UP | G31: Pos_venda | H31: WHATSAPP | J31: 45967.526 | K31: 45999.744 | L31: 46001 | M31: 46014.553 | N31: O4R1 | O31: Release_01 | Q31: 71032 | R31: WA-259 | S31: [Blip][S&D Colab.][R1] Pós venda - Abertura de ocorrência por área | T31: Pos_venda;WHATSAPP; | U31: O4R1;Release_01;
A32: Spike | B32: WA-418 | C32: 76971 | D32: [Blip][S&D Colab.][Autosserviço][Árvore de decisão] UX desenho da jornada solicitação do boleto | E32: DESENV CONCLUIDO | F32: UP | G32: Pos_venda | H32: WHATSAPP | J32: 45954.783 | K32: 45978.651 | L32: 45978.651 | M32: 45985.384 | N32: O4R1 | O32: Release_01 | Q32: 75664 | R32: WA-348 | S32: [Blip][S&D Colab.][R1] Autosserviço - Financeiro - Solicitação boleto | T32: Pos_venda;WHATSAPP; | U32: O4R1;Release_01;
A33: Spike | B33: WA-416 | C33: 76967 | D33: [Blip][S&D Colab.][Árvore de decisão] UX desenho da jornada - Pós venda menu inicial | E33: DESENV CONCLUIDO | F33: UP | G33: Migra_Blip | H33: Pos_venda | I33: WHATSAPP | J33: 45954.783 | K33: 45978.562 | L33: 45978.562 | M33: 45978.438 | N33: O4R1 | O33: Release_01 | Q33: 71032 | R33: WA-259 | S33: [Blip][S&D Colab.][R1] Pós venda - Abertura de ocorrência por área | T33: Migra_Blip;Pos_venda;WHATSAPP | U33: O4R1;Release_01;
A34: História | B34: WA-409 | C34: 76951 | D34: [Blip][S&D Colab.][HSM][Multas] Disparo de NIC - Responsabilidade Cliente | E34: 1. Backlog | G34: WHATSAPP | J34: 45954.767 | N34: O4R1 | Q34: 76935 | R34: WA-401 | S34: [Blip][S&D Colab.][R3] Multas - Disparos de mensagens ativas | T34: WHATSAPP;; | U34: O4R1;;
A35: História | B35: WA-407 | C35: 76947 | D35: [Blip][S&D Colab.][HSM][Multas] Disparo de NIP - Responsabilidade Locadora | E35: DESCARTADO | G35: WHATSAPP | J35: 45954.765 | M35: 46044.628 | N35: O4R1 | Q35: 76935 | R35: WA-401 | S35: [Blip][S&D Colab.][R3] Multas - Disparos de mensagens ativas | T35: WHATSAPP;; | U35: O4R1;;
A36: História | B36: WA-402 | C36: 76937 | D36: [Blip][S&D Colab.][HSM][Multas] Disparo de NAI/NIP BRF | E36: 1. Backlog | G36: WHATSAPP | J36: 45954.764 | N36: O4R1 | Q36: 76935 | R36: WA-401 | S36: [Blip][S&D Colab.][R3] Multas - Disparos de mensagens ativas | T36: WHATSAPP;; | U36: O4R1;;
A37: História | B37: WA-383 | C37: 75758 | D37: [Blip][S&D Colab.] Pós venda - Cadastro dos agentes de atendimento | E37: DESENV CONCLUIDO | F37: UP | G37: WHATSAPP | J37: 45953.518 | K37: 45972.637 | L37: 45972.637 | M37: 45972.512 | N37: O4R1 | O37: Release_01 | Q37: 74927 | R37: WA-333 | S37: [Blip][S&D Colab.][R1][Cross] Estrutura do bot | T37: WHATSAPP;; | U37: O4R1;Release_01;
A38: Spike | B38: WA-381 | C38: 75754 | D38: [Blip][S&D Colab.] Ativação dos números de homologação | E38: DESENV CONCLUIDO | F38: UP | G38: Migra_Blip | H38: WHATSAPP | J38: 45953.515 | K38: 45964.9 | L38: 45964 | M38: 45964.776 | N38: O4R1 | O38: Release_01 | Q38: 74927 | R38: WA-333 | S38: [Blip][S&D Colab.][R1][Cross] Estrutura do bot | T38: Migra_Blip;WHATSAPP; | U38: O4R1;Release_01;
A39: História | B39: WA-365 | C39: 75681 | D39: [Blip][S&D Colab.][Autosserviço] 2º via do boleto - Escritório de cobrança | E39: DESENV CONCLUIDO | F39: UP | G39: WHATSAPP | J39: 45952.783 | K39: 45994.514 | L39: 45994 | M39: 46009.65 | N39: O4R1 | O39: Release_01 | Q39: 75664 | R39: WA-348 | S39: [Blip][S&D Colab.][R1] Autosserviço - Financeiro - Solicitação boleto | T39: WHATSAPP;; | U39: O4R1;Release_01;
A40: História | B40: WA-364 | C40: 75680 | D40: [Blip][S&D Colab.][Autosserviço] Solicitação segunda via da CRLV | E40: DESENV CONCLUIDO | F40: UP | G40: WHATSAPP | J40: 45952.783 | K40: 45985.73 | L40: 45985 | M40: 46003.446 | N40: O4R1 | O40: Release_01 | Q40: 75678 | R40: WA-362 | S40: [Blip][S&D Colab.][R1] Autosserviço - Doc. do veículo - CRLV | T40: WHATSAPP;; | U40: O4R1;Release_01;
A41: História | B41: WA-335 | C41: 75651 | D41: [Blip][S&D Colab.][Comercial] Novo lead - Qualificação | E41: DESENV CONCLUIDO | F41: UP | G41: WHATSAPP | J41: 45952.782 | K41: 45971.635 | L41: 45971.635 | M41: 45985.392 | N41: O4R1 | O41: Release_01 | Q41: 75650 | R41: WA-334 | S41: [Blip][S&D Colab.][R1] Comercial - Qualificação de Lead | T41: WHATSAPP;; | U41: O4R1;Release_01;
A42: História | B42: WA-326 | C42: 71099 | D42: [Blip][S&D Colab.][Pós venda][Abertura de ocorrência] Manutenção - Direcionamento para a ticket | E42: DESENV CONCLUIDO | F42: UP | G42: WHATSAPP | J42: 45940.516 | K42: 45978.735 | L42: 45978.828 | M42: 45989.38 | N42: O4R1 | Q42: 71032 | R42: WA-259 | S42: [Blip][S&D Colab.][R1] Pós venda - Abertura de ocorrência por área | T42: WHATSAPP;; | U42: O4R1;;
A43: História | B43: WA-276 | C43: 71049 | D43: [Blip][S&D Colab.] Pós venda - Saudação inicial e Identificação do Cliente | E43: DESENV CONCLUIDO | F43: UP | G43: WHATSAPP | J43: 45940.515 | K43: 45966.724 | L43: 45966 | M43: 45985.392 | N43: O4R1 | Q43: 71048 | R43: WA-274 | S43: [Blip][S&D Colab.][R1] Inicio bot | T43: WHATSAPP;; | U43: O4R1;;
A44: História | B44: WA-273 | C44: 71046 | D44: [Blip][S&D Colab.][Pós venda][Abertura de ocorrência] Fim de contrato - Devolução veículo | E44: DESENV CONCLUIDO | F44: UP | G44: WHATSAPP | J44: 45940.515 | K44: 45985.731 | L44: 45986.502 | M44: 46021.592 | N44: O4R1 | O44: Release_01 | Q44: 71032 | R44: WA-259 | S44: [Blip][S&D Colab.][R1] Pós venda - Abertura de ocorrência por área | T44: WHATSAPP;; | U44: O4R1;Release_01;
A45: História | B45: WA-265 | C45: 71038 | D45: [Blip][S&D Colab.][Pós venda][Abertura de ocorrência] Meu Contrato, Documento - Solicitação de segunda via de contrato | E45: DESENV CONCLUIDO | F45: UP | G45: WHATSAPP | J45: 45940.515 | K45: 45992.64 | L45: 45993 | M45: 45999.505 | N45: O4R1 | Q45: 71032 | R45: WA-259 | S45: [Blip][S&D Colab.][R1] Pós venda - Abertura de ocorrência por área | T45: WHATSAPP;; | U45: O4R1;;
A46: História | B46: VAA-420 | C46: 160833 | D46: Exibição de ofertas agrupadas na home com “a partir de "Preço” 13 Pontos | E46: SPRINT BACKLOG | F46: NIVUS | G46: VENDAS_AUTO-ATENDIMENTO | J46: 46104.488 | K46: 46104.623 | L46: 46083 | N46: O4R2 | Q46: 108214 | R46: VAA-138 | S46: Épico 1 — Visualizar Ofertas e Regras de Pricing (Pricing + Locavia (proposta) + Maestro)) - HOME | T46: VENDAS_AUTO-ATENDIMENTO;; | U46: O4R2;;
A47: Bug | B47: VAA-412 | C47: 160805 | D47: CLONE - Logotipo Sign and Drive no mobile está distorcido | E47: 1. Backlog | F47: NIVUS | G47: VENDAS_AUTO-ATENDIMENTO | J47: 46104.441 | L47: 46093 | N47: O4R2 | T47: VENDAS_AUTO-ATENDIMENTO;; | U47: O4R2;;
A48: História | B48: VAA-403 | C48: 160795 | D48: CLONE - Carregar Catálogo e Preço Real (Locavia + Maestro) | E48: 1. Backlog | F48: NIVUS | G48: VENDAS_AUTO-ATENDIMENTO | J48: 46104.44 | K48: 45985.56 | L48: 45985.56 | N48: O4R2 | Q48: 108214 | R48: VAA-138 | S48: Épico 1 — Visualizar Ofertas e Regras de Pricing (Pricing + Locavia (proposta) + Maestro)) - HOME | T48: VENDAS_AUTO-ATENDIMENTO;; | U48: O4R2;;
A49: História | B49: VAA-402 | C49: 160794 | D49: CLONE - Validação de Vínculo de Parente via Autorização do Colaborador | E49: 1. Backlog | F49: NIVUS | G49: VENDAS_AUTO-ATENDIMENTO | J49: 46104.438 | K49: 46058.824 | L49: 46058 | N49: O4R2 | Q49: 75256 | R49: VAA-1 | S49: Épico 3 — Autenticação e Validação de Vínculo (Keycloak + Octopus) | T49: VENDAS_AUTO-ATENDIMENTO;; | U49: O4R2;;
A50: História | B50: VAA-401 | C50: 160785 | D50: CLONE - Login e Identificação de Perfil | E50: 1. Backlog | F50: NIVUS | G50: VENDAS_AUTO-ATENDIMENTO | J50: 46104.436 | K50: 46007.608 | L50: 46010 | N50: O4R2 | Q50: 75256 | R50: VAA-1 | S50: Épico 3 — Autenticação e Validação de Vínculo (Keycloak + Octopus) | T50: VENDAS_AUTO-ATENDIMENTO;; | U50: O4R2;;
A51: Spike | B51: VAA-388 | C51: 159281 | D51: Validar o Maestro com oferta do princing | E51: EM DESENVOLVIMENTO | F51: NIVUS | G51: VENDAS_AUTO-ATENDIMENTO | J51: 46097.477 | K51: 46097 | L51: 46100 | N51: O4R2 | Q51: 75256 | R51: VAA-1 | S51: Épico 3 — Autenticação e Validação de Vínculo (Keycloak + Octopus) | T51: VENDAS_AUTO-ATENDIMENTO;; | U51: O4R2;;
A52: História | B52: VAA-381 | C52: 158965 | D52: Botão Flutuante de Atendimento via WhatsApp ( 2 pontos) | E52: DESENV CONCLUIDO | F52: NIVUS | G52: VENDAS_AUTO-ATENDIMENTO | J52: 46093.739 | K52: 46097.59 | L52: 46098 | M52: 46100.635 | N52: O4R2 | Q52: 101276 | R52: VAA-123 | S52: Épico 2 — Configuração do carro (modelo, cor, km, prazo) | T52: VENDAS_AUTO-ATENDIMENTO;; | U52: O4R2;;
A53: História | B53: VAA-370 | C53: 157724 | D53: Pagina Checkout | E53: DESCARTADO | F53: NIVUS | G53: VENDAS_AUTO-ATENDIMENTO | J53: 46087.716 | K53: 46090.59 | M53: 46093.537 | N53: O4R2 | Q53: 108214 | R53: VAA-138 | S53: Épico 1 — Visualizar Ofertas e Regras de Pricing (Pricing + Locavia (proposta) + Maestro)) - HOME | T53: VENDAS_AUTO-ATENDIMENTO;; | U53: O4R2;;
A54: História | B54: VAA-367 | C54: 157719 | D54: Equalização Banner/Carrossel topo da Home 3pts | E54: EM DESENVOLVIMENTO | F54: NIVUS | G54: VENDAS_AUTO-ATENDIMENTO | J54: 46087.713 | K54: 46090.59 | L54: 46105 | N54: O4R2 | Q54: 108214 | R54: VAA-138 | S54: Épico 1 — Visualizar Ofertas e Regras de Pricing (Pricing + Locavia (proposta) + Maestro)) - HOME | T54: VENDAS_AUTO-ATENDIMENTO;; | U54: O4R2;;
A55: História | B55: VAA-358 | C55: 157365 | D55: Endpoint das ofertas por perfil de usuário 8 Pontos | E55: DESENV CONCLUIDO | F55: NIVUS | G55: VENDAS_AUTO-ATENDIMENTO | J55: 46086.622 | K55: 46086.747 | L55: 46086 | M55: 46094.738 | N55: O4R2 | T55: VENDAS_AUTO-ATENDIMENTO;; | U55: O4R2;;
A56: Spike | B56: VAA-348 | C56: 156543 | D56: Gestão de descontos | E56: DESENV CONCLUIDO | F56: NIVUS | G56: VENDAS_AUTO-ATENDIMENTO | J56: 46084.478 | K56: 46084 | L56: 46086 | M56: 46086.397 | N56: O4R2 | Q56: 108214 | R56: VAA-138 | S56: Épico 1 — Visualizar Ofertas e Regras de Pricing (Pricing + Locavia (proposta) + Maestro)) - HOME | T56: VENDAS_AUTO-ATENDIMENTO;; | U56: O4R2;;
A57: História | B57: VAA-346 | C57: 156540 | D57: Equalização Catálogo/Carrossel seção da home 5 pts | E57: DESENV CONCLUIDO | F57: NIVUS | G57: VENDAS_AUTO-ATENDIMENTO | J57: 46084.476 | K57: 46090.59 | L57: 46090.606 | M57: 46094.721 | N57: O4R2 | Q57: 108214 | R57: VAA-138 | S57: Épico 1 — Visualizar Ofertas e Regras de Pricing (Pricing + Locavia (proposta) + Maestro)) - HOME | T57: VENDAS_AUTO-ATENDIMENTO;; | U57: O4R2;;
A58: História | B58: VAA-344 | C58: 156537 | D58: Equalização Layout Menu Hamburguer/Menu mobile 3 pts | E58: DESENV CONCLUIDO | F58: NIVUS | G58: VENDAS_AUTO-ATENDIMENTO | J58: 46084.471 | K58: 46090.59 | L58: 46091 | M58: 46100.637 | N58: O4R2 | Q58: 108214 | R58: VAA-138 | S58: Épico 1 — Visualizar Ofertas e Regras de Pricing (Pricing + Locavia (proposta) + Maestro)) - HOME | T58: VENDAS_AUTO-ATENDIMENTO;; | U58: O4R2;;
A59: Tarefa | B59: VAA-335 | C59: 156215 | D59: Validação do Fluxo em DEV | E59: DESENV CONCLUIDO | F59: NIVUS | G59: VENDAS_AUTO-ATENDIMENTO | J59: 46083.502 | K59: 46083 | L59: 46084 | M59: 46087.718 | N59: O4R2 | Q59: 108214 | R59: VAA-138 | S59: Épico 1 — Visualizar Ofertas e Regras de Pricing (Pricing + Locavia (proposta) + Maestro)) - HOME | T59: VENDAS_AUTO-ATENDIMENTO;; | U59: O4R2;;
A60: História | B60: VAA-331 | C60: 156192 | D60: Equalização layout Mega Menus Desktop (Veículos/Por que Assinar) 8pts | E60: DESENV CONCLUIDO | F60: NIVUS | G60: VENDAS_AUTO-ATENDIMENTO | J60: 46083.479 | K60: 46083.631 | L60: 46083 | M60: 46094.721 | N60: O4R2 | Q60: 108214 | R60: VAA-138 | S60: Épico 1 — Visualizar Ofertas e Regras de Pricing (Pricing + Locavia (proposta) + Maestro)) - HOME | T60: VENDAS_AUTO-ATENDIMENTO;; | U60: O4R2;;
A61: História | B61: VAA-329 | C61: 156175 | D61: UX Checkout: Finalização do pedido | E61: DESCARTADO | G61: VENDAS_AUTO-ATENDIMENTO | J61: 46083.468 | M61: 46093.538 | N61: O4R2 | Q61: 108214 | R61: VAA-138 | S61: Épico 1 — Visualizar Ofertas e Regras de Pricing (Pricing + Locavia (proposta) + Maestro)) - HOME | T61: VENDAS_AUTO-ATENDIMENTO;; | U61: O4R2;;
A62: Tarefa | B62: VAA-327 | C62: 155251 | D62: Teste integrados Release 1 | E62: DESENV CONCLUIDO | F62: NIVUS | G62: VENDAS_AUTO-ATENDIMENTO | J62: 46078.397 | K62: 46080.519 | L62: 46080.519 | M62: 46093.468 | N62: O4R2 | Q62: 108214 | R62: VAA-138 | S62: Épico 1 — Visualizar Ofertas e Regras de Pricing (Pricing + Locavia (proposta) + Maestro)) - HOME | T62: VENDAS_AUTO-ATENDIMENTO;; | U62: O4R2;;
A63: História | B63: VAA-324 | C63: 154754 | D63: Implementação da interações na Home | E63: DESCARTADO | F63: NIVUS | G63: VENDAS_AUTO-ATENDIMENTO | J63: 46076.469 | K63: 46083.598 | L63: 46083 | M63: 46084.399 | N63: O4R2 | Q63: 108214 | R63: VAA-138 | S63: Épico 1 — Visualizar Ofertas e Regras de Pricing (Pricing + Locavia (proposta) + Maestro)) - HOME | T63: VENDAS_AUTO-ATENDIMENTO;; | U63: O4R2;;
A64: História | B64: VAA-320 | C64: 154173 | D64: Máquina de Estados + Idempotência do Pedido | E64: 1. Backlog | G64: VENDAS_AUTO-ATENDIMENTO | J64: 46072.747 | N64: O4R2 | Q64: 138830 | R64: VAA-182 | S64: Épico 4 — Integrações de Crédito (Neurotech) e Check Out | T64: VENDAS_AUTO-ATENDIMENTO;; | U64: O4R2;;
A65: História | B65: VAA-319 | C65: 154170 | D65: Tratamento de falha de autenticação (Keycloak) (5 Pontos ) | E65: DESENV CONCLUIDO | F65: NIVUS | G65: VENDAS_AUTO-ATENDIMENTO | J65: 46072.74 | K65: 46097.602 | L65: 46098 | M65: 46101.705 | N65: O4R2 | Q65: 75256 | R65: VAA-1 | S65: Épico 3 — Autenticação e Validação de Vínculo (Keycloak + Octopus) | T65: VENDAS_AUTO-ATENDIMENTO;; | U65: O4R2;;
A66: História | B66: VAA-318 | C66: 154169 | D66: Estados formais de vínculo (Octopus) | E66: 1. Backlog | G66: VENDAS_AUTO-ATENDIMENTO | J66: 46072.738 | K66: 46049.823 | L66: 46050 | N66: O4R2 | Q66: 75256 | R66: VAA-1 | S66: Épico 3 — Autenticação e Validação de Vínculo (Keycloak + Octopus) | T66: VENDAS_AUTO-ATENDIMENTO;; | U66: O4R2;;
A67: História | B67: VAA-317 | C67: 154166 | D67: Tratamento de CPF/e-mail já existente | E67: 1. Backlog | G67: VENDAS_AUTO-ATENDIMENTO | J67: 46072.733 | K67: 46049.823 | L67: 46050 | N67: O4R2 | Q67: 75256 | R67: VAA-1 | S67: Épico 3 — Autenticação e Validação de Vínculo (Keycloak + Octopus) | T67: VENDAS_AUTO-ATENDIMENTO;; | U67: O4R2;;
A68: História | B68: VAA-316 | C68: 154165 | D68: Persistência de contexto e retorno pós-SSO | E68: 1. Backlog | G68: VENDAS_AUTO-ATENDIMENTO | J68: 46072.731 | K68: 46049.823 | L68: 46050 | N68: O4R2 | Q68: 75256 | R68: VAA-1 | S68: Épico 3 — Autenticação e Validação de Vínculo (Keycloak + Octopus) | T68: VENDAS_AUTO-ATENDIMENTO;; | U68: O4R2;;
A69: História | B69: VAA-311 | C69: 154125 | D69: Consolidação do Snapshot Final de Configuração | E69: 1. Backlog | G69: VENDAS_AUTO-ATENDIMENTO | J69: 46072.694 | N69: O4R2 | Q69: 101276 | R69: VAA-123 | S69: Épico 2 — Configuração do carro (modelo, cor, km, prazo) | T69: VENDAS_AUTO-ATENDIMENTO;; | U69: O4R2;;
A70: História | B70: VAA-310 | C70: 154122 | D70: Tratamento de combinações inválidas | E70: 1. Backlog | G70: VENDAS_AUTO-ATENDIMENTO | J70: 46072.681 | N70: O4R2 | Q70: 101276 | R70: VAA-123 | S70: Épico 2 — Configuração do carro (modelo, cor, km, prazo) | T70: VENDAS_AUTO-ATENDIMENTO;; | U70: O4R2;;
A71: História | B71: VAA-309 | C71: 154109 | D71: Padronizar comportamento do CTA “Assine já” | E71: DESCARTADO | G71: VENDAS_AUTO-ATENDIMENTO | J71: 46072.672 | K71: 45985.56 | L71: 45985.56 | M71: 46093.538 | N71: O4R2 | Q71: 108214 | R71: VAA-138 | S71: Épico 1 — Visualizar Ofertas e Regras de Pricing (Pricing + Locavia (proposta) + Maestro)) - HOME | T71: VENDAS_AUTO-ATENDIMENTO;; | U71: O4R2;;
A72: História | B72: VAA-308 | C72: 154071 | D72: Implementar fallback e tratamento de exceções na Home dinâmica | E72: 1. Backlog | F72: NIVUS | G72: VENDAS_AUTO-ATENDIMENTO | J72: 46072.581 | K72: 45985.56 | L72: 45985.56 | N72: O4R2 | Q72: 108214 | R72: VAA-138 | S72: Épico 1 — Visualizar Ofertas e Regras de Pricing (Pricing + Locavia (proposta) + Maestro)) - HOME | T72: VENDAS_AUTO-ATENDIMENTO;; | U72: O4R2;;
A73: História | B73: VAA-306 | C73: 153283 | D73: Forçar fluxo obrigatório de confirmação de dados após login 8ptos | E73: DESENV CONCLUIDO | F73: NIVUS | G73: VENDAS_AUTO-ATENDIMENTO | J73: 46066.418 | K73: 46066.544 | L73: 46071 | M73: 46080.388 | N73: O4R2 | Q73: 108214 | R73: VAA-138 | S73: Épico 1 — Visualizar Ofertas e Regras de Pricing (Pricing + Locavia (proposta) + Maestro)) - HOME | T73: VENDAS_AUTO-ATENDIMENTO;; | U73: O4R2;;
A74: Tarefa | B74: VAA-304 | C74: 151820 | D74: Merge e subida em deploy das entregas até o momento | E74: DESENV CONCLUIDO | F74: NIVUS | G74: VENDAS_AUTO-ATENDIMENTO | J74: 46063.396 | K74: 46073.513 | L74: 46073.513 | M74: 46073.388 | N74: O4R2 | T74: VENDAS_AUTO-ATENDIMENTO;; | U74: O4R2;;
A75: Tarefa | B75: VAA-302 | C75: 151741 | D75: Subir o pacote de alteração da Venice | E75: 1. Backlog | F75: NIVUS | G75: VENDAS_AUTO-ATENDIMENTO | J75: 46062.716 | N75: O4R2 | T75: VENDAS_AUTO-ATENDIMENTO;; | U75: O4R2;;
A76: Spike | B76: VAA-300 | C76: 151622 | D76: Estudar implementação do Banner | E76: 1. Backlog | F76: NIVUS | G76: VENDAS_AUTO-ATENDIMENTO | J76: 46062.49 | N76: O4R2 | T76: VENDAS_AUTO-ATENDIMENTO;; | U76: O4R2;;
A77: Spike | B77: VAA-298 | C77: 151609 | D77: Levantamento de informações extras de cadastro das ofertas no portal | E77: DESENV CONCLUIDO | F77: NIVUS | G77: VENDAS_AUTO-ATENDIMENTO | J77: 46062.487 | K77: 46062 | L77: 46064 | M77: 46073.718 | N77: O4R2 | Q77: 108214 | R77: VAA-138 | S77: Épico 1 — Visualizar Ofertas e Regras de Pricing (Pricing + Locavia (proposta) + Maestro)) - HOME | T77: VENDAS_AUTO-ATENDIMENTO;; | U77: O4R2;;
A78: História | B78: VAA-296 | C78: 151607 | D78: Tela para gerenciar imagens das ofertas do veiculos | E78: DESENV CONCLUIDO | F78: NIVUS | G78: VENDAS_AUTO-ATENDIMENTO | J78: 46062.485 | K78: 46062.612 | L78: 46064 | M78: 46094.755 | N78: O4R2 | Q78: 108214 | R78: VAA-138 | S78: Épico 1 — Visualizar Ofertas e Regras de Pricing (Pricing + Locavia (proposta) + Maestro)) - HOME | T78: VENDAS_AUTO-ATENDIMENTO;; | U78: O4R2;;
A79: História | B79: VAA-294 | C79: 151201 | D79: Integração da equalização do checkout | E79: 1. Backlog | G79: VENDAS_AUTO-ATENDIMENTO | J79: 46058.704 | N79: O4R2 | Q79: 138830 | R79: VAA-182 | S79: Épico 4 — Integrações de Crédito (Neurotech) e Check Out | T79: VENDAS_AUTO-ATENDIMENTO;; | U79: O4R2;;
A80: História | B80: VAA-292 | C80: 151199 | D80: Equalização do layout do checkout | E80: 1. Backlog | G80: VENDAS_AUTO-ATENDIMENTO | J80: 46058.703 | N80: O4R2 | Q80: 138830 | R80: VAA-182 | S80: Épico 4 — Integrações de Crédito (Neurotech) e Check Out | T80: VENDAS_AUTO-ATENDIMENTO;; | U80: O4R2;;
A81: História | B81: VAA-290 | C81: 151092 | D81: Revisar alteração de textos e informativos | E81: DESENV CONCLUIDO | F81: NIVUS | G81: VENDAS_AUTO-ATENDIMENTO | J81: 46058.447 | K81: 46058.6 | L81: 46058 | M81: 46073.387 | N81: O4R2 | Q81: 148923 | R81: VAA-267 | S81: Épico 5 — UX, Conteúdo e Mensagens Transacionais | T81: VENDAS_AUTO-ATENDIMENTO;; | U81: O4R2;;
A82: História | B82: VAA-280 | C82: 150203 | D82: Interações da Home | E82: DESENV CONCLUIDO | F82: NIVUS | G82: VENDAS_AUTO-ATENDIMENTO | J82: 46055.745 | K82: 46064.519 | L82: 46064 | M82: 46084.392 | N82: O4R2 | Q82: 108214 | R82: VAA-138 | S82: Épico 1 — Visualizar Ofertas e Regras de Pricing (Pricing + Locavia (proposta) + Maestro)) - HOME | T82: VENDAS_AUTO-ATENDIMENTO;; | U82: O4R2;;
A83: História | B83: VAA-279 | C83: 150200 | D83: Integração da equalização do ex funcionário 5pts | E83: DESENV CONCLUIDO | F83: NIVUS | G83: VENDAS_AUTO-ATENDIMENTO | J83: 46055.742 | K83: 46062.599 | L83: 46062 | M83: 46064.351 | N83: O4R2 | Q83: 108214 | R83: VAA-138 | S83: Épico 1 — Visualizar Ofertas e Regras de Pricing (Pricing + Locavia (proposta) + Maestro)) - HOME | T83: VENDAS_AUTO-ATENDIMENTO;; | U83: O4R2;;
A84: História | B84: VAA-278 | C84: 150199 | D84: Integração da equalização do parente 5ptos | E84: DESENV CONCLUIDO | F84: NIVUS | G84: VENDAS_AUTO-ATENDIMENTO | J84: 46055.741 | K84: 46062.599 | L84: 46062 | M84: 46063.378 | N84: O4R2 | Q84: 108214 | R84: VAA-138 | S84: Épico 1 — Visualizar Ofertas e Regras de Pricing (Pricing + Locavia (proposta) + Maestro)) - HOME | T84: VENDAS_AUTO-ATENDIMENTO;; | U84: O4R2;;
A85: História | B85: VAA-277 | C85: 150198 | D85: Equalização do layout página de veículo 13 pts | E85: 1. Backlog | G85: VENDAS_AUTO-ATENDIMENTO | J85: 46055.739 | N85: O4R2 | Q85: 101276 | R85: VAA-123 | S85: Épico 2 — Configuração do carro (modelo, cor, km, prazo) | T85: VENDAS_AUTO-ATENDIMENTO;; | U85: O4R2;;
A86: História | B86: VAA-276 | C86: 150197 | D86: Integração do layout equalizado | E86: 1. Backlog | G86: VENDAS_AUTO-ATENDIMENTO | J86: 46055.738 | N86: O4R2 | Q86: 101276 | R86: VAA-123 | S86: Épico 2 — Configuração do carro (modelo, cor, km, prazo) | T86: VENDAS_AUTO-ATENDIMENTO;; | U86: O4R2;;
A87: História | B87: VAA-275 | C87: 150196 | D87: Template de email transacional - Parente | E87: DESENV CONCLUIDO | F87: NIVUS | G87: VENDAS_AUTO-ATENDIMENTO | J87: 46055.735 | K87: 46057.854 | L87: 46057 | M87: 46062.472 | N87: O4R2 | Q87: 148923 | R87: VAA-267 | S87: Épico 5 — UX, Conteúdo e Mensagens Transacionais | T87: VENDAS_AUTO-ATENDIMENTO;; | U87: O4R2;;
A88: História | B88: VAA-274 | C88: 150195 | D88: Template de email transacional - Ex - Funcionário | E88: DESENV CONCLUIDO | F88: NIVUS | G88: VENDAS_AUTO-ATENDIMENTO | J88: 46055.735 | K88: 46057.522 | L88: 46057 | M88: 46062.471 | N88: O4R2 | Q88: 148923 | R88: VAA-267 | S88: Épico 5 — UX, Conteúdo e Mensagens Transacionais | T88: VENDAS_AUTO-ATENDIMENTO;; | U88: O4R2;;
A89: História | B89: VAA-273 | C89: 149464 | D89: Equalização do layout da home 13ptos | E89: DESENV CONCLUIDO | F89: NIVUS | G89: VENDAS_AUTO-ATENDIMENTO | J89: 46051.707 | K89: 46062.605 | L89: 46064 | M89: 46087.467 | N89: O4R2 | Q89: 108214 | R89: VAA-138 | S89: Épico 1 — Visualizar Ofertas e Regras de Pricing (Pricing + Locavia (proposta) + Maestro)) - HOME | T89: VENDAS_AUTO-ATENDIMENTO;; | U89: O4R2;;
A90: História | B90: VAA-272 | C90: 149462 | D90: Integração da equalização da home - 8 pontos | E90: DESENV CONCLUIDO | F90: NIVUS | G90: VENDAS_AUTO-ATENDIMENTO | J90: 46051.705 | K90: 46097.59 | L90: 46098 | M90: 46100.705 | N90: O4R2 | Q90: 108214 | R90: VAA-138 | S90: Épico 1 — Visualizar Ofertas e Regras de Pricing (Pricing + Locavia (proposta) + Maestro)) - HOME | T90: VENDAS_AUTO-ATENDIMENTO;; | U90: O4R2;;
A91: História | B91: VAA-269 | C91: 148927 | D91: Template de email transacional - Funcionário - 5pts | E91: DESENV CONCLUIDO | F91: NIVUS | G91: VENDAS_AUTO-ATENDIMENTO | J91: 46049.694 | K91: 46049.823 | L91: 46055 | M91: 46062.471 | N91: O4R2 | Q91: 148923 | R91: VAA-267 | S91: Épico 5 — UX, Conteúdo e Mensagens Transacionais | T91: VENDAS_AUTO-ATENDIMENTO;; | U91: O4R2;;
A92: História | B92: VAA-259 | C92: 148909 | D92: Equalização de layout - 13 Confirme seus dados (Parente) - 3pts | E92: DESENV CONCLUIDO | F92: NIVUS | G92: VENDAS_AUTO-ATENDIMENTO | J92: 46049.689 | K92: 46049.823 | L92: 46050 | M92: 46062.467 | N92: O4R2 | Q92: 75256 | R92: VAA-1 | S92: Épico 3 — Autenticação e Validação de Vínculo (Keycloak + Octopus) | T92: VENDAS_AUTO-ATENDIMENTO;; | U92: O4R2;;
A93: História | B93: VAA-257 | C93: 148906 | D93: Integração 12.1 Confirme seus dados (Funcionário) - 13pts | E93: DESENV CONCLUIDO | F93: NIVUS | G93: VENDAS_AUTO-ATENDIMENTO | J93: 46049.688 | K93: 46049.823 | L93: 46050 | M93: 46057.396 | N93: O4R2 | Q93: 75256 | R93: VAA-1 | S93: Épico 3 — Autenticação e Validação de Vínculo (Keycloak + Octopus) | T93: VENDAS_AUTO-ATENDIMENTO;; | U93: O4R2;;
A94: Spike | B94: VAA-255 | C94: 148735 | D94: Mapeamento tecnico de envio de email e pedidos/proposta | E94: DESENV CONCLUIDO | F94: NIVUS | G94: VENDAS_AUTO-ATENDIMENTO | J94: 46049.408 | K94: 46049.822 | L94: 46052 | M94: 46062.47 | N94: O4R2 | T94: VENDAS_AUTO-ATENDIMENTO;; | U94: O4R2;;
A95: História | B95: VAA-252 | C95: 147409 | D95: Configuração para disparo de email (Full) | E95: DESENV CONCLUIDO | F95: NIVUS | G95: VENDAS_AUTO-ATENDIMENTO | J95: 46041.495 | K95: 46041.622 | L95: 46041 | M95: 46049.678 | N95: O4R2 | T95: VENDAS_AUTO-ATENDIMENTO;; | U95: O4R2;;
A96: História | B96: VAA-250 | C96: 147405 | D96: [UX] Aquisição: 2. Página do Veículo | E96: DESENV CONCLUIDO | F96: NIVUS | G96: VENDAS_AUTO-ATENDIMENTO | J96: 46041.49 | K96: 46041.622 | L96: 46042 | M96: 46087.397 | N96: O4R2 | T96: VENDAS_AUTO-ATENDIMENTO;; | U96: O4R2;;
A97: História | B97: VAA-248 | C97: 147403 | D97: Equalização de layout - 12.2 Confirme seus dados (Ex-funcionário Aposentado) | E97: DESENV CONCLUIDO | F97: NIVUS | G97: VENDAS_AUTO-ATENDIMENTO | J97: 46041.487 | K97: 46044.85 | L97: 46044 | M97: 46049.674 | N97: O4R2 | T97: VENDAS_AUTO-ATENDIMENTO;; | U97: O4R2;;
A98: História | B98: VAA-243 | C98: 146968 | D98: Equalização de layout - 12.1 Confirme seus dados (Funcionários) - 3 pontos | E98: DESENV CONCLUIDO | F98: NIVUS | G98: VENDAS_AUTO-ATENDIMENTO | J98: 46038.353 | K98: 46041.617 | L98: 46041 | M98: 46049.673 | N98: O4R2 | T98: VENDAS_AUTO-ATENDIMENTO;; | U98: O4R2;;
A99: Spike | B99: VAA-240 | C99: 146442 | D99: [Pricing] Definião de autenticação pricing | E99: DESENV CONCLUIDO | F99: NIVUS | G99: VENDAS_AUTO-ATENDIMENTO | J99: 46035.397 | K99: 46037.518 | L99: 46037.518 | M99: 46086.622 | N99: O4R2 | T99: VENDAS_AUTO-ATENDIMENTO;; | U99: O4R2;;
A100: Tarefa | B100: VAA-238 | C100: 146440 | D100: VENICE TELA DE LOGIN E CADASTRO | E100: 1. Backlog | F100: NIVUS | G100: VENDAS_AUTO-ATENDIMENTO | J100: 46035.395 | N100: O4R2 | T100: VENDAS_AUTO-ATENDIMENTO;; | U100: O4R2;;
...

Sheet CONE
E1: O4R2 | F1: GOL | H1: TERA | J1: OPTIMUS | L1: NIVUS | N1: TAOS | P1: FUSCA | R1: UP
E2: ESCOPO | F2: =VLOOKUP(F1,'LEIA-ME'!$A:$B,2,0) -> VENDAS_ASSISTIDAS | H2: =VLOOKUP(H1,'LEIA-ME'!$A:$B,2,0) -> FATURAMENTO | J2: =VLOOKUP(J1,'LEIA-ME'!$A:$B,2,0) -> CONTRATOS | L2: =VLOOKUP(L1,'LEIA-ME'!$A:$B,2,0) -> COMERCIAL | N2: =VLOOKUP(N1,'LEIA-ME'!$A:$B,2,0) -> CREDITO | P2: =VLOOKUP(P1,'LEIA-ME'!$A:$B,2,0) -> SALESFORCE_PÓSVEND | R2: =VLOOKUP(R1,'LEIA-ME'!$A:$B,2,0) -> WHATSAPP
E3: Semana | F3: M | G3: P | H3: M | I3: P | J3: M | K3: P | L3: M | M3: P | N3: M | O3: P | P3: M | Q3: P | R3: M | S3: P
E4: 45936 | F4: ='GOL O4R2'!C15 -> 64 | G4: ='GOL O4R2'!D15 -> 64 | H4: ='TERA O4R2'!C15 -> 31 | I4: ='TERA O4R2'!D15 -> 31 | J4: ='OPTIMUS O4R2'!C15 -> 72 | K4: ='OPTIMUS O4R2'!D15 -> 72 | L4: ='NIVUS O4R2'!C15 -> 53 | M4: ='NIVUS O4R2'!D15 -> 53 | N4: ='TAOS O4R2'!C15 -> 16 | O4: ='TAOS O4R2'!D15 -> 16 | P4: ='FUSCA O4R2'!C15 -> 21 | Q4: ='FUSCA O4R2'!D15 -> 21 | R4: ='UP O4R2'!C15 -> 39 | S4: ='UP O4R2'!D15 -> 39
E5: =E4+7 -> 45943 | F5: ='GOL O4R2'!C16 -> 64 | G5: ='GOL O4R2'!D16 -> 64 | H5: ='TERA O4R2'!C16 -> 31 | I5: ='TERA O4R2'!D16 -> 31 | J5: ='OPTIMUS O4R2'!C16 -> 72 | K5: ='OPTIMUS O4R2'!D16 -> 72 | L5: ='NIVUS O4R2'!C16 -> 53 | M5: ='NIVUS O4R2'!D16 -> 53 | N5: ='TAOS O4R2'!C16 -> 16 | O5: ='TAOS O4R2'!D16 -> 16 | P5: ='FUSCA O4R2'!C16 -> 21 | Q5: ='FUSCA O4R2'!D16 -> 21 | R5: ='UP O4R2'!C16 -> 39 | S5: ='UP O4R2'!D16 -> 39
E6: =E5+7 -> 45950 | F6: ='GOL O4R2'!C17 -> 64 | G6: ='GOL O4R2'!D17 -> 64 | H6: ='TERA O4R2'!C17 -> 31 | I6: ='TERA O4R2'!D17 -> 31 | J6: ='OPTIMUS O4R2'!C17 -> 72 | K6: ='OPTIMUS O4R2'!D17 -> 72 | L6: ='NIVUS O4R2'!C17 -> 53 | M6: ='NIVUS O4R2'!D17 -> 53 | N6: ='TAOS O4R2'!C17 -> 16 | O6: ='TAOS O4R2'!D17 -> 16 | P6: ='FUSCA O4R2'!C17 -> 21 | Q6: ='FUSCA O4R2'!D17 -> 21 | R6: ='UP O4R2'!C17 -> 39 | S6: ='UP O4R2'!D17 -> 39
E7: =E6+7 -> 45957 | F7: ='GOL O4R2'!C18 -> 63 | G7: ='GOL O4R2'!D18 -> 63 | H7: ='TERA O4R2'!C18 -> 31 | I7: ='TERA O4R2'!D18 -> 31 | J7: ='OPTIMUS O4R2'!C18 -> 70 | K7: ='OPTIMUS O4R2'!D18 -> 70 | L7: ='NIVUS O4R2'!C18 -> 53 | M7: ='NIVUS O4R2'!D18 -> 53 | N7: ='TAOS O4R2'!C18 -> 16 | O7: ='TAOS O4R2'!D18 -> 16 | P7: ='FUSCA O4R2'!C18 -> 21 | Q7: ='FUSCA O4R2'!D18 -> 21 | R7: ='UP O4R2'!C18 -> 39 | S7: ='UP O4R2'!D18 -> 39
E8: =E7+7 -> 45964 | F8: ='GOL O4R2'!C19 -> 63 | G8: ='GOL O4R2'!D19 -> 63 | H8: ='TERA O4R2'!C19 -> 31 | I8: ='TERA O4R2'!D19 -> 31 | J8: ='OPTIMUS O4R2'!C19 -> 69 | K8: ='OPTIMUS O4R2'!D19 -> 69 | L8: ='NIVUS O4R2'!C19 -> 53 | M8: ='NIVUS O4R2'!D19 -> 53 | N8: ='TAOS O4R2'!C19 -> 16 | O8: ='TAOS O4R2'!D19 -> 16 | P8: ='FUSCA O4R2'!C19 -> 21 | Q8: ='FUSCA O4R2'!D19 -> 21 | R8: ='UP O4R2'!C19 -> 39 | S8: ='UP O4R2'!D19 -> 39
E9: =E8+7 -> 45971 | F9: ='GOL O4R2'!C20 -> 62 | G9: ='GOL O4R2'!D20 -> 62 | H9: ='TERA O4R2'!C20 -> 31 | I9: ='TERA O4R2'!D20 -> 31 | J9: ='OPTIMUS O4R2'!C20 -> 68 | K9: ='OPTIMUS O4R2'!D20 -> 68 | L9: ='NIVUS O4R2'!C20 -> 53 | M9: ='NIVUS O4R2'!D20 -> 53 | N9: ='TAOS O4R2'!C20 -> 16 | O9: ='TAOS O4R2'!D20 -> 16 | P9: ='FUSCA O4R2'!C20 -> 21 | Q9: ='FUSCA O4R2'!D20 -> 21 | R9: ='UP O4R2'!C20 -> 38 | S9: ='UP O4R2'!D20 -> 38
E10: =E9+7 -> 45978 | F10: ='GOL O4R2'!C21 -> 57 | G10: ='GOL O4R2'!D21 -> 57 | H10: ='TERA O4R2'!C21 -> 31 | I10: ='TERA O4R2'!D21 -> 31 | J10: ='OPTIMUS O4R2'!C21 -> 68 | K10: ='OPTIMUS O4R2'!D21 -> 68 | L10: ='NIVUS O4R2'!C21 -> 53 | M10: ='NIVUS O4R2'!D21 -> 53 | N10: ='TAOS O4R2'!C21 -> 16 | O10: ='TAOS O4R2'!D21 -> 16 | P10: ='FUSCA O4R2'!C21 -> 21 | Q10: ='FUSCA O4R2'!D21 -> 21 | R10: ='UP O4R2'!C21 -> 37 | S10: ='UP O4R2'!D21 -> 37
E11: =E10+7 -> 45985 | F11: ='GOL O4R2'!C22 -> 55 | G11: ='GOL O4R2'!D22 -> 55 | H11: ='TERA O4R2'!C22 -> 31 | I11: ='TERA O4R2'!D22 -> 31 | J11: ='OPTIMUS O4R2'!C22 -> 68 | K11: ='OPTIMUS O4R2'!D22 -> 68 | L11: ='NIVUS O4R2'!C22 -> 53 | M11: ='NIVUS O4R2'!D22 -> 53 | N11: ='TAOS O4R2'!C22 -> 16 | O11: ='TAOS O4R2'!D22 -> 16 | P11: ='FUSCA O4R2'!C22 -> 21 | Q11: ='FUSCA O4R2'!D22 -> 21 | R11: ='UP O4R2'!C22 -> 35 | S11: ='UP O4R2'!D22 -> 35
E12: =E11+7 -> 45992 | F12: ='GOL O4R2'!C23 -> 51 | G12: ='GOL O4R2'!D23 -> 51 | H12: ='TERA O4R2'!C23 -> 31 | I12: ='TERA O4R2'!D23 -> 31 | J12: ='OPTIMUS O4R2'!C23 -> 67 | K12: ='OPTIMUS O4R2'!D23 -> 67 | L12: ='NIVUS O4R2'!C23 -> 53 | M12: ='NIVUS O4R2'!D23 -> 53 | N12: ='TAOS O4R2'!C23 -> 16 | O12: ='TAOS O4R2'!D23 -> 16 | P12: ='FUSCA O4R2'!C23 -> 21 | Q12: ='FUSCA O4R2'!D23 -> 21 | R12: ='UP O4R2'!C23 -> 25 | S12: ='UP O4R2'!D23 -> 25
E13: =E12+7 -> 45999 | F13: ='GOL O4R2'!C24 -> 49 | G13: ='GOL O4R2'!D24 -> 49 | H13: ='TERA O4R2'!C24 -> 31 | I13: ='TERA O4R2'!D24 -> 31 | J13: ='OPTIMUS O4R2'!C24 -> 65 | K13: ='OPTIMUS O4R2'!D24 -> 65 | L13: ='NIVUS O4R2'!C24 -> 53 | M13: ='NIVUS O4R2'!D24 -> 53 | N13: ='TAOS O4R2'!C24 -> 16 | O13: ='TAOS O4R2'!D24 -> 16 | P13: ='FUSCA O4R2'!C24 -> 21 | Q13: ='FUSCA O4R2'!D24 -> 21 | R13: ='UP O4R2'!C24 -> 25 | S13: ='UP O4R2'!D24 -> 25
E14: =E13+7 -> 46006 | F14: ='GOL O4R2'!C25 -> 46 | G14: ='GOL O4R2'!D25 -> 46 | H14: ='TERA O4R2'!C25 -> 31 | I14: ='TERA O4R2'!D25 -> 31 | J14: ='OPTIMUS O4R2'!C25 -> 59 | K14: ='OPTIMUS O4R2'!D25 -> 59 | L14: ='NIVUS O4R2'!C25 -> 53 | M14: ='NIVUS O4R2'!D25 -> 53 | N14: ='TAOS O4R2'!C25 -> 16 | O14: ='TAOS O4R2'!D25 -> 16 | P14: ='FUSCA O4R2'!C25 -> 21 | Q14: ='FUSCA O4R2'!D25 -> 21 | R14: ='UP O4R2'!C25 -> 20 | S14: ='UP O4R2'!D25 -> 20
E15: =E14+7 -> 46013 | F15: ='GOL O4R2'!C26 -> 44 | G15: ='GOL O4R2'!D26 -> 44 | H15: ='TERA O4R2'!C26 -> 31 | I15: ='TERA O4R2'!D26 -> 31 | J15: ='OPTIMUS O4R2'!C26 -> 56 | K15: ='OPTIMUS O4R2'!D26 -> 56 | L15: ='NIVUS O4R2'!C26 -> 53 | M15: ='NIVUS O4R2'!D26 -> 53 | N15: ='TAOS O4R2'!C26 -> 15 | O15: ='TAOS O4R2'!D26 -> 15 | P15: ='FUSCA O4R2'!C26 -> 21 | Q15: ='FUSCA O4R2'!D26 -> 21 | R15: ='UP O4R2'!C26 -> 17 | S15: ='UP O4R2'!D26 -> 17
E16: =E15+7 -> 46020 | F16: ='GOL O4R2'!C27 -> 43 | G16: ='GOL O4R2'!D27 -> 43 | H16: ='TERA O4R2'!C27 -> 31 | I16: ='TERA O4R2'!D27 -> 31 | J16: ='OPTIMUS O4R2'!C27 -> 54 | K16: ='OPTIMUS O4R2'!D27 -> 54 | L16: ='NIVUS O4R2'!C27 -> 53 | M16: ='NIVUS O4R2'!D27 -> 53 | N16: ='TAOS O4R2'!C27 -> 15 | O16: ='TAOS O4R2'!D27 -> 15 | P16: ='FUSCA O4R2'!C27 -> 21 | Q16: ='FUSCA O4R2'!D27 -> 21 | R16: ='UP O4R2'!C27 -> 16 | S16: ='UP O4R2'!D27 -> 16
... E57: =E56+7 -> 46307 | F57: ='GOL O4R2'!C68 | G57: ='GOL O4R2'!D68 | H57: ='TERA O4R2'!C68 | I57: ='TERA O4R2'!D68 | J57: ='OPTIMUS O4R2'!C68 | K57: ='OPTIMUS O4R2'!D68 | L57: ='NIVUS O4R2'!C68 | M57: ='NIVUS O4R2'!D68 | N57: ='TAOS O4R2'!C68 | O57: ='TAOS O4R2'!D68 | P57: ='FUSCA O4R2'!C68 | Q57: ='FUSCA O4R2'!D68 | R57: ='UP O4R2'!C68 | S57: ='UP O4R2'!D68

Sheet GOL - TESTE
A1: Cone: baseado na nossa vazão, chegaremos na data alvo? O que cabe até data alvo?
B2: Quantidade de Épicos | D2: Épicos | E2: considerar apenas os épicos que estão no mapa de release
B3: Features | C3: 15 | D3: Story / Tarefa / Bug / Spike | E3: considerar o trabalho de todos os integrantes do time, inclsuive tasks de dívidas técnicas e automação
B4: Data início | C4: 46062 | D4: Primeria sprint da release
B5: Data fim esperada | C5: 46118 | D5: Data entregada release
B6: Melhor cenário | C6: 4 | D6: itens por semana | E6: considerar sempre as ultimas 4 sprints para atualizar os números
B7: Pior cenário | C7: 1 | D7: itens por semana | E7: considerar sempre as ultimas 4 sprints para atualizar os números
B8: Velocidade necessária | C8: 6 | D8: itens por semana
B9: Acompanhar a cada | C9: 7 | D9: dias
B11: Data do Início da Semana | C11: Se seguirmos nossa melhor vazão, quando entregamos? | D11: Se seguirmos nossa pior vazão, quando entregamos? | E11: Vazão ideal para atender à data | F11: Itens da sprint anterior que não foram concluídos | G11: Itens que entram em sprint pela primeira vez | H11: Itens que entraram na Sprint depois do planejamento, mas não são "Fura fila" | I11: Itens Fura-Fila que apareceram ao longo da Sprint | J11: Itens entregues na Sprint | K11: Itens que chegaram no backlog do time ao longo da semana, mas não na sprint | L11: Observações adicionais
B12: Não editar esses campos | G12: Preencher com os dados de cada semana
A13: Sprint | B13: Semana | C13: A fazer (melhor cenário) | D13: A fazer (pior cenário) | E13: A fazer (valocidade necessária) | F13: Itens Transbordo | G13: Itens Planejados (Planning) | H13: Itens não planejados na sprint | I13: (+) Expedite | J13: Realizado | K13: (+)(-) Escopo pro time | L13: OBSERVAÇÕES
B14: =C4 -> 46062 | C14: =$C$3 -> 15 | D14: =$C$3 -> 15 | E14: =$C$3 -> 15
A15: Sprint 11 | B15: =B14+$C$9 -> 46069 | C15: =IF(OR(C14="",C14=0),"",IF(ISBLANK($J14),IF(C14+$K14+$I14-$C$6<=0,IF(AND(C14>0,C14<>""),0,""),C14+$K14+$I14-$C$6),IF((C14-$J14)+$K14+$I14<=0,IF(AND(C14>0,C14<>""),0,""),(C14-$J14)+$K14+$I14))) -> 11 | D15: =IF(OR(D14="",D14=0),"",IF(ISBLANK($J14),IF(D14+$K14+$I14-$C$7<=0,IF(AND(D14>0,D14<>""),0,""),D14+$K14+$I14-$C$7),IF((D14-$J14)+$K14+$I14<=0,IF(AND(D14>0,D14<>""),0,""),(D14-$J14)+$K14+$I14))) -> 14 | E15: =IF(OR(E14="",E14=0),"",IF(ISBLANK($J14),IF(E14+$K14+$I14-$C$8<=0,IF(AND(E14>0,E14<>""),0,""),E14+$K14+$I14-$C$8),IF((E14-$J14)+$K14+$I14<=0,IF(AND(E14>0,E14<>""),0,""),(E14-$J14)+$K14+$I14))) -> 9 | F15: =IF(J14="","",IF(G14+F14+H14+I14-J14<0,0,G14+F14+H14+I14-J14))
A16: Sprint 12 | B16: =B15+$C$9 -> 46076 | C16: =IF(OR(C15="",C15=0),"",IF(ISBLANK(J15),IF(C15+K15+I15-$C$6<=0,IF(AND(C15>0,C15<>""),0,""),C15+K15+I15-$C$6),IF((C15-J15)+K15+I15<=0,IF(AND(C15>0,C15<>""),0,""),(C15-J15)+K15+I15))) -> 7 | D16: =IF(OR(D15="",D15=0),"",IF(ISBLANK($J15),IF(D15+$K15+$I15-$C$7<=0,IF(AND(D15>0,D15<>""),0,""),D15+$K15+$I15-$C$7),IF((D15-$J15)+$K15+$I15<=0,IF(AND(D15>0,D15<>""),0,""),(D15-$J15)+$K15+$I15))) -> 13 | E16: =IF(OR(E15="",E15=0),"",IF(ISBLANK($J15),IF(E15+$K15+$I15-$C$8<=0,IF(AND(E15>0,E15<>""),0,""),E15+$K15+$I15-$C$8),IF((E15-$J15)+$K15+$I15<=0,IF(AND(E15>0,E15<>""),0,""),(E15-$J15)+$K15+$I15))) -> 3 | F16: =IF(J15="","",IF(G15+F15+H15+I15-J15<0,0,G15+F15+H15+I15-J15))
A17: Sprint 13 | B17: =B16+$C$9 -> 46083 | C17: =IF(OR(C16="",C16=0),"",IF(ISBLANK(J16),IF(C16+K16+I16-$C$6<=0,IF(AND(C16>0,C16<>""),0,""),C16+K16+I16-$C$6),IF((C16-J16)+K16+I16<=0,IF(AND(C16>0,C16<>""),0,""),(C16-J16)+K16+I16))) -> 3 | D17: =IF(OR(D16="",D16=0),"",IF(ISBLANK($J16),IF(D16+$K16+$I16-$C$7<=0,IF(AND(D16>0,D16<>""),0,""),D16+$K16+$I16-$C$7),IF((D16-$J16)+$K16+$I16<=0,IF(AND(D16>0,D16<>""),0,""),(D16-$J16)+$K16+$I16))) -> 12 | E17: =IF(OR(E16="",E16=0),"",IF(ISBLANK($J16),IF(E16+$K16+$I16-$C$8<=0,IF(AND(E16>0,E16<>""),0,""),E16+$K16+$I16-$C$8),IF((E16-$J16)+$K16+$I16<=0,IF(AND(E16>0,E16<>""),0,""),(E16-$J16)+$K16+$I16))) -> 0 | F17: =IF(J16="","",IF(G16+F16+H16+I16-J16<0,0,G16+F16+H16+I16-J16))
A18: Sprint 14 | B18: =B17+$C$9 -> 46090 | C18: =IF(OR(C17="",C17=0),"",IF(ISBLANK(J17),IF(C17+K17+I17-$C$6<=0,IF(AND(C17>0,C17<>""),0,""),C17+K17+I17-$C$6),IF((C17-J17)+K17+I17<=0,IF(AND(C17>0,C17<>""),0,""),(C17-J17)+K17+I17))) -> 0 | D18: =IF(OR(D17="",D17=0),"",IF(ISBLANK($J17),IF(D17+$K17+$I17-$C$7<=0,IF(AND(D17>0,D17<>""),0,""),D17+$K17+$I17-$C$7),IF((D17-$J17)+$K17+$I17<=0,IF(AND(D17>0,D17<>""),0,""),(D17-$J17)+$K17+$I17))) -> 11 | E18: =IF(OR(E17="",E17=0),"",IF(ISBLANK($J17),IF(E17+$K17+$I17-$C$8<=0,IF(AND(E17>0,E17<>""),0,""),E17+$K17+$I17-$C$8),IF((E17-$J17)+$K17+$I17<=0,IF(AND(E17>0,E17<>""),0,""),(E17-$J17)+$K17+$I17))) | F18: =IF(J17="","",IF(G17+F17+H17+I17-J17<0,0,G17+F17+H17+I17-J17))
A19: Sprint 15 | B19: =B18+$C$9 -> 46097 | C19: =IF(OR(C18="",C18=0),"",IF(ISBLANK(J18),IF(C18+K18+I18-$C$6<=0,IF(AND(C18>0,C18<>""),0,""),C18+K18+I18-$C$6),IF((C18-J18)+K18+I18<=0,IF(AND(C18>0,C18<>""),0,""),(C18-J18)+K18+I18))) | D19: =IF(OR(D18="",D18=0),"",IF(ISBLANK($J18),IF(D18+$K18+$I18-$C$7<=0,IF(AND(D18>0,D18<>""),0,""),D18+$K18+$I18-$C$7),IF((D18-$J18)+$K18+$I18<=0,IF(AND(D18>0,D18<>""),0,""),(D18-$J18)+$K18+$I18))) -> 10 | E19: =IF(OR(E18="",E18=0),"",IF(ISBLANK($J18),IF(E18+$K18+$I18-$C$8<=0,IF(AND(E18>0,E18<>""),0,""),E18+$K18+$I18-$C$8),IF((E18-$J18)+$K18+$I18<=0,IF(AND(E18>0,E18<>""),0,""),(E18-$J18)+$K18+$I18))) | F19: =IF(J18="","",IF(G18+F18+H18+I18-J18<0,0,G18+F18+H18+I18-J18))
A20: Sprint 16 | B20: =B19+$C$9 -> 46104 | C20: =IF(OR(C19="",C19=0),"",IF(ISBLANK(J19),IF(C19+K19+I19-$C$6<=0,IF(AND(C19>0,C19<>""),0,""),C19+K19+I19-$C$6),IF((C19-J19)+K19+I19<=0,IF(AND(C19>0,C19<>""),0,""),(C19-J19)+K19+I19))) | D20: =IF(OR(D19="",D19=0),"",IF(ISBLANK($J19),IF(D19+$K19+$I19-$C$7<=0,IF(AND(D19>0,D19<>""),0,""),D19+$K19+$I19-$C$7),IF((D19-$J19)+$K19+$I19<=0,IF(AND(D19>0,D19<>""),0,""),(D19-$J19)+$K19+$I19))) -> 9 | E20: =IF(OR(E19="",E19=0),"",IF(ISBLANK($J19),IF(E19+$K19+$I19-$C$8<=0,IF(AND(E19>0,E19<>""),0,""),E19+$K19+$I19-$C$8),IF((E19-$J19)+$K19+$I19<=0,IF(AND(E19>0,E19<>""),0,""),(E19-$J19)+$K19+$I19))) | F20: =IF(J19="","",IF(G19+F19+H19+I19-J19<0,0,G19+F19+H19+I19-J19))
A21: Sprint 17 | B21: =B20+$C$9 -> 46111 | C21: =IF(OR(C20="",C20=0),"",IF(ISBLANK(J20),IF(C20+K20+I20-$C$6<=0,IF(AND(C20>0,C20<>""),0,""),C20+K20+I20-$C$6),IF((C20-J20)+K20+I20<=0,IF(AND(C20>0,C20<>""),0,""),(C20-J20)+K20+I20))) | D21: =IF(OR(D20="",D20=0),"",IF(ISBLANK($J20),IF(D20+$K20+$I20-$C$7<=0,IF(AND(D20>0,D20<>""),0,""),D20+$K20+$I20-$C$7),IF((D20-$J20)+$K20+$I20<=0,IF(AND(D20>0,D20<>""),0,""),(D20-$J20)+$K20+$I20))) -> 8 | E21: =IF(OR(E20="",E20=0),"",IF(ISBLANK($J20),IF(E20+$K20+$I20-$C$8<=0,IF(AND(E20>0,E20<>""),0,""),E20+$K20+$I20-$C$8),IF((E20-$J20)+$K20+$I20<=0,IF(AND(E20>0,E20<>""),0,""),(E20-$J20)+$K20+$I20))) | F21: =IF(J20="","",IF(G20+F20+H20+I20-J20<0,0,G20+F20+H20+I20-J20))
A22: Sprint 18 | B22: =B21+$C$9 -> 46118 | C22: =IF(OR(C21="",C21=0),"",IF(ISBLANK(J21),IF(C21+K21+I21-$C$6<=0,IF(AND(C21>0,C21<>""),0,""),C21+K21+I21-$C$6),IF((C21-J21)+K21+I21<=0,IF(AND(C21>0,C21<>""),0,""),(C21-J21)+K21+I21))) | D22: =IF(OR(D21="",D21=0),"",IF(ISBLANK($J21),IF(D21+$K21+$I21-$C$7<=0,IF(AND(D21>0,D21<>""),0,""),D21+$K21+$I21-$C$7),IF((D21-$J21)+$K21+$I21<=0,IF(AND(D21>0,D21<>""),0,""),(D21-$J21)+$K21+$I21))) -> 7 | E22: =IF(OR(E21="",E21=0),"",IF(ISBLANK($J21),IF(E21+$K21+$I21-$C$8<=0,IF(AND(E21>0,E21<>""),0,""),E21+$K21+$I21-$C$8),IF((E21-$J21)+$K21+$I21<=0,IF(AND(E21>0,E21<>""),0,""),(E21-$J21)+$K21+$I21))) | F22: =IF(J21="","",IF(G21+F21+H21+I21-J21<0,0,G21+F21+H21+I21-J21))
A23: Sprint 19 | B23: =B22+$C$9 -> 46125 | C23: =IF(OR(C22="",C22=0),"",IF(ISBLANK(J22),IF(C22+K22+I22-$C$6<=0,IF(AND(C22>0,C22<>""),0,""),C22+K22+I22-$C$6),IF((C22-J22)+K22+I22<=0,IF(AND(C22>0,C22<>""),0,""),(C22-J22)+K22+I22))) | D23: =IF(OR(D22="",D22=0),"",IF(ISBLANK($J22),IF(D22+$K22+$I22-$C$7<=0,IF(AND(D22>0,D22<>""),0,""),D22+$K22+$I22-$C$7),IF((D22-$J22)+$K22+$I22<=0,IF(AND(D22>0,D22<>""),0,""),(D22-$J22)+$K22+$I22))) -> 6 | E23: =IF(OR(E22="",E22=0),"",IF(ISBLANK($J22),IF(E22+$K22+$I22-$C$8<=0,IF(AND(E22>0,E22<>""),0,""),E22+$K22+$I22-$C$8),IF((E22-$J22)+$K22+$I22<=0,IF(AND(E22>0,E22<>""),0,""),(E22-$J22)+$K22+$I22))) | F23: =IF(J22="","",IF(G22+F22+H22+I22-J22<0,0,G22+F22+H22+I22-J22))
A24: Sprint 20 | B24: =B23+$C$9 -> 46132 | C24: =IF(OR(C23="",C23=0),"",IF(ISBLANK(J23),IF(C23+K23+I23-$C$6<=0,IF(AND(C23>0,C23<>""),0,""),C23+K23+I23-$C$6),IF((C23-J23)+K23+I23<=0,IF(AND(C23>0,C23<>""),0,""),(C23-J23)+K23+I23))) | D24: =IF(OR(D23="",D23=0),"",IF(ISBLANK($J23),IF(D23+$K23+$I23-$C$7<=0,IF(AND(D23>0,D23<>""),0,""),D23+$K23+$I23-$C$7),IF((D23-$J23)+$K23+$I23<=0,IF(AND(D23>0,D23<>""),0,""),(D23-$J23)+$K23+$I23))) -> 5 | E24: =IF(OR(E23="",E23=0),"",IF(ISBLANK($J23),IF(E23+$K23+$I23-$C$8<=0,IF(AND(E23>0,E23<>""),0,""),E23+$K23+$I23-$C$8),IF((E23-$J23)+$K23+$I23<=0,IF(AND(E23>0,E23<>""),0,""),(E23-$J23)+$K23+$I23))) | F24: =IF(J23="","",IF(G23+F23+H23+I23-J23<0,0,G23+F23+H23+I23-J23))
A25: Sprint 21 | B25: =B24+$C$9 -> 46139 | C25: =IF(OR(C24="",C24=0),"",IF(ISBLANK(J24),IF(C24+K24+I24-$C$6<=0,IF(AND(C24>0,C24<>""),0,""),C24+K24+I24-$C$6),IF((C24-J24)+K24+I24<=0,IF(AND(C24>0,C24<>""),0,""),(C24-J24)+K24+I24))) | D25: =IF(OR(D24="",D24=0),"",IF(ISBLANK($J24),IF(D24+$K24+$I24-$C$7<=0,IF(AND(D24>0,D24<>""),0,""),D24+$K24+$I24-$C$7),IF((D24-$J24)+$K24+$I24<=0,IF(AND(D24>0,D24<>""),0,""),(D24-$J24)+$K24+$I24))) -> 4 | E25: =IF(OR(E24="",E24=0),"",IF(ISBLANK($J24),IF(E24+$K24+$I24-$C$8<=0,IF(AND(E24>0,E24<>""),0,""),E24+$K24+$I24-$C$8),IF((E24-$J24)+$K24+$I24<=0,IF(AND(E24>0,E24<>""),0,""),(E24-$J24)+$K24+$I24))) | F25: =IF(J24="","",IF(G24+F24+H24+I24-J24<0,0,G24+F24+H24+I24-J24))
A26: Sprint 22 | B26: =B25+$C$9 -> 46146 | C26: =IF(OR(C25="",C25=0),"",IF(ISBLANK(J25),IF(C25+K25+I25-$C$6<=0,IF(AND(C25>0,C25<>""),0,""),C25+K25+I25-$C$6),IF((C25-J25)+K25+I25<=0,IF(AND(C25>0,C25<>""),0,""),(C25-J25)+K25+I25))) | D26: =IF(OR(D25="",D25=0),"",IF(ISBLANK($J25),IF(D25+$K25+$I25-$C$7<=0,IF(AND(D25>0,D25<>""),0,""),D25+$K25+$I25-$C$7),IF((D25-$J25)+$K25+$I25<=0,IF(AND(D25>0,D25<>""),0,""),(D25-$J25)+$K25+$I25))) -> 3 | E26: =IF(OR(E25="",E25=0),"",IF(ISBLANK($J25),IF(E25+$K25+$I25-$C$8<=0,IF(AND(E25>0,E25<>""),0,""),E25+$K25+$I25-$C$8),IF((E25-$J25)+$K25+$I25<=0,IF(AND(E25>0,E25<>""),0,""),(E25-$J25)+$K25+$I25))) | F26: =IF(J25="","",IF(G25+F25+H25+I25-J25<0,0,G25+F25+H25+I25-J25))
A27: Sprint 23 | B27: =B26+$C$9 -> 46153 | C27: =IF(OR(C26="",C26=0),"",IF(ISBLANK(J26),IF(C26+K26+I26-$C$6<=0,IF(AND(C26>0,C26<>""),0,""),C26+K26+I26-$C$6),IF((C26-J26)+K26+I26<=0,IF(AND(C26>0,C26<>""),0,""),(C26-J26)+K26+I26))) | D27: =IF(OR(D26="",D26=0),"",IF(ISBLANK($J26),IF(D26+$K26+$I26-$C$7<=0,IF(AND(D26>0,D26<>""),0,""),D26+$K26+$I26-$C$7),IF((D26-$J26)+$K26+$I26<=0,IF(AND(D26>0,D26<>""),0,""),(D26-$J26)+$K26+$I26))) -> 2 | E27: =IF(OR(E26="",E26=0),"",IF(ISBLANK($J26),IF(E26+$K26+$I26-$C$8<=0,IF(AND(E26>0,E26<>""),0,""),E26+$K26+$I26-$C$8),IF((E26-$J26)+$K26+$I26<=0,IF(AND(E26>0,E26<>""),0,""),(E26-$J26)+$K26+$I26))) | F27: =IF(J26="","",IF(G26+F26+H26+I26-J26<0,0,G26+F26+H26+I26-J26))
... A30: Sprint 26 | B30: =B29+$C$9 -> 46174 | C30: =IF(OR(C29="",C29=0),"",IF(ISBLANK(J29),IF(C29+K29+I29-$C$6<=0,IF(AND(C29>0,C29<>""),0,""),C29+K29+I29-$C$6),IF((C29-J29)+K29+I29<=0,IF(AND(C29>0,C29<>""),0,""),(C29-J29)+K29+I29))) | D30: =IF(OR(D29="",D29=0),"",IF(ISBLANK($J29),IF(D29+$K29+$I29-$C$7<=0,IF(AND(D29>0,D29<>""),0,""),D29+$K29+$I29-$C$7),IF((D29-$J29)+$K29+$I29<=0,IF(AND(D29>0,D29<>""),0,""),(D29-$J29)+$K29+$I29))) | E30: =IF(OR(E29="",E29=0),"",IF(ISBLANK($J29),IF(E29+$K29+$I29-$C$8<=0,IF(AND(E29>0,E29<>""),0,""),E29+$K29+$I29-$C$8),IF((E29-$J29)+$K29+$I29<=0,IF(AND(E29>0,E29<>""),0,""),(E29-$J29)+$K29+$I29))) | F30: =IF(J29="","",IF(G29+F29+H29+I29-J29<0,0,G29+F29+H29+I29-J29))
B31: =B30+$C$9 -> 46181 | C31: =IF(OR(C30="",C30=0),"",IF(ISBLANK(J30),IF(C30+K30+I30-$C$6<=0,IF(AND(C30>0,C30<>""),0,""),C30+K30+I30-$C$6),IF((C30-J30)+K30+I30<=0,IF(AND(C30>0,C30<>""),0,""),(C30-J30)+K30+I30))) | D31: =IF(OR(D30="",D30=0),"",IF(ISBLANK($J30),IF(D30+$K30+$I30-$C$7<=0,IF(AND(D30>0,D30<>""),0,""),D30+$K30+$I30-$C$7),IF((D30-$J30)+$K30+$I30<=0,IF(AND(D30>0,D30<>""),0,""),(D30-$J30)+$K30+$I30))) | E31: =IF(OR(E30="",E30=0),"",IF(ISBLANK($J30),IF(E30+$K30+$I30-$C$8<=0,IF(AND(E30>0,E30<>""),0,""),E30+$K30+$I30-$C$8),IF((E30-$J30)+$K30+$I30<=0,IF(AND(E30>0,E30<>""),0,""),(E30-$J30)+$K30+$I30))) | F31: =IF(J30="","",IF(G30+F30+H30+I30-J30<0,0,G30+F30+H30+I30-J30))
B32: =B31+$C$9 -> 46188 | C32: =IF(OR(C31="",C31=0),"",IF(ISBLANK(J31),IF(C31+K31+I31-$C$6<=0,IF(AND(C31>0,C31<>""),0,""),C31+K31+I31-$C$6),IF((C31-J31)+K31+I31<=0,IF(AND(C31>0,C31<>""),0,""),(C31-J31)+K31+I31))) | D32: =IF(OR(D31="",D31=0),"",IF(ISBLANK($J31),IF(D31+$K31+$I31-$C$7<=0,IF(AND(D31>0,D31<>""),0,""),D31+$K31+$I31-$C$7),IF((D31-$J31)+$K31+$I31<=0,IF(AND(D31>0,D31<>""),0,""),(D31-$J31)+$K31+$I31))) | E32: =IF(OR(E31="",E31=0),"",IF(ISBLANK($J31),IF(E31+$K31+$I31-$C$8<=0,IF(AND(E31>0,E31<>""),0,""),E31+$K31+$I31-$C$8),IF((E31-$J31)+$K31+$I31<=0,IF(AND(E31>0,E31<>""),0,""),(E31-$J31)+$K31+$I31))) | F32: =IF(J31="","",IF(G31+F31+H31+I31-J31<0,0,G31+F31+H31+I31-J31))
B33: =B32+$C$9 -> 46195 | C33: =IF(OR(C32="",C32=0),"",IF(ISBLANK(J32),IF(C32+K32+I32-$C$6<=0,IF(AND(C32>0,C32<>""),0,""),C32+K32+I32-$C$6),IF((C32-J32)+K32+I32<=0,IF(AND(C32>0,C32<>""),0,""),(C32-J32)+K32+I32))) | D33: =IF(OR(D32="",D32=0),"",IF(ISBLANK($J32),IF(D32+$K32+$I32-$C$7<=0,IF(AND(D32>0,D32<>""),0,""),D32+$K32+$I32-$C$7),IF((D32-$J32)+$K32+$I32<=0,IF(AND(D32>0,D32<>""),0,""),(D32-$J32)+$K32+$I32))) | E33: =IF(OR(E32="",E32=0),"",IF(ISBLANK($J32),IF(E32+$K32+$I32-$C$8<=0,IF(AND(E32>0,E32<>""),0,""),E32+$K32+$I32-$C$8),IF((E32-$J32)+$K32+$I32<=0,IF(AND(E32>0,E32<>""),0,""),(E32-$J32)+$K32+$I32))) | F33: =IF(J32="","",IF(G32+F32+H32+I32-J32<0,0,G32+F32+H32+I32-J32))
B34: =B33+$C$9 -> 46202 | C34: =IF(OR(C33="",C33=0),"",IF(ISBLANK(J33),IF(C33+K33+I33-$C$6<=0,IF(AND(C33>0,C33<>""),0,""),C33+K33+I33-$C$6),IF((C33-J33)+K33+I33<=0,IF(AND(C33>0,C33<>""),0,""),(C33-J33)+K33+I33))) | D34: =IF(OR(D33="",D33=0),"",IF(ISBLANK($J33),IF(D33+$K33+$I33-$C$7<=0,IF(AND(D33>0,D33<>""),0,""),D33+$K33+$I33-$C$7),IF((D33-$J33)+$K33+$I33<=0,IF(AND(D33>0,D33<>""),0,""),(D33-$J33)+$K33+$I33))) | E34: =IF(OR(E33="",E33=0),"",IF(ISBLANK($J33),IF(E33+$K33+$I33-$C$8<=0,IF(AND(E33>0,E33<>""),0,""),E33+$K33+$I33-$C$8),IF((E33-$J33)+$K33+$I33<=0,IF(AND(E33>0,E33<>""),0,""),(E33-$J33)+$K33+$I33))) | F34: =IF(J33="","",IF(G33+F33+H33+I33-J33<0,0,G33+F33+H33+I33-J33))
B35: =B34+$C$9 -> 46209 | C35: =IF(OR(C34="",C34=0),"",IF(ISBLANK(J34),IF(C34+K34+I34-$C$6<=0,IF(AND(C34>0,C34<>""),0,""),C34+K34+I34-$C$6),IF((C34-J34)+K34+I34<=0,IF(AND(C34>0,C34<>""),0,""),(C34-J34)+K34+I34))) | D35: =IF(OR(D34="",D34=0),"",IF(ISBLANK($J34),IF(D34+$K34+$I34-$C$7<=0,IF(AND(D34>0,D34<>""),0,""),D34+$K34+$I34-$C$7),IF((D34-$J34)+$K34+$I34<=0,IF(AND(D34>0,D34<>""),0,""),(D34-$J34)+$K34+$I34))) | E35: =IF(OR(E34="",E34=0),"",IF(ISBLANK($J34),IF(E34+$K34+$I34-$C$8<=0,IF(AND(E34>0,E34<>""),0,""),E34+$K34+$I34-$C$8),IF((E34-$J34)+$K34+$I34<=0,IF(AND(E34>0,E34<>""),0,""),(E34-$J34)+$K34+$I34))) | F35: =IF(J34="","",IF(G34+F34+H34+I34-J34<0,0,G34+F34+H34+I34-J34))
B36: =B35+$C$9 -> 46216 | C36: =IF(OR(C35="",C35=0),"",IF(ISBLANK(J35),IF(C35+K35+I35-$C$6<=0,IF(AND(C35>0,C35<>""),0,""),C35+K35+I35-$C$6),IF((C35-J35)+K35+I35<=0,IF(AND(C35>0,C35<>""),0,""),(C35-J35)+K35+I35))) | D36: =IF(OR(D35="",D35=0),"",IF(ISBLANK($J35),IF(D35+$K35+$I35-$C$7<=0,IF(AND(D35>0,D35<>""),0,""),D35+$K35+$I35-$C$7),IF((D35-$J35)+$K35+$I35<=0,IF(AND(D35>0,D35<>""),0,""),(D35-$J35)+$K35+$I35))) | E36: =IF(OR(E35="",E35=0),"",IF(ISBLANK($J35),IF(E35+$K35+$I35-$C$8<=0,IF(AND(E35>0,E35<>""),0,""),E35+$K35+$I35-$C$8),IF((E35-$J35)+$K35+$I35<=0,IF(AND(E35>0,E35<>""),0,""),(E35-$J35)+$K35+$I35))) | F36: =IF(J35="","",IF(G35+F35+H35+I35-J35<0,0,G35+F35+H35+I35-J35))
B37: =B36+$C$9 -> 46223 | C37: =IF(OR(C36="",C36=0),"",IF(ISBLANK(J36),IF(C36+K36+I36-$C$6<=0,IF(AND(C36>0,C36<>""),0,""),C36+K36+I36-$C$6),IF((C36-J36)+K36+I36<=0,IF(AND(C36>0,C36<>""),0,""),(C36-J36)+K36+I36))) | D37: =IF(OR(D36="",D36=0),"",IF(ISBLANK($J36),IF(D36+$K36+$I36-$C$7<=0,IF(AND(D36>0,D36<>""),0,""),D36+$K36+$I36-$C$7),IF((D36-$J36)+$K36+$I36<=0,IF(AND(D36>0,D36<>""),0,""),(D36-$J36)+$K36+$I36))) | E37: =IF(OR(E36="",E36=0),"",IF(ISBLANK($J36),IF(E36+$K36+$I36-$C$8<=0,IF(AND(E36>0,E36<>""),0,""),E36+$K36+$I36-$C$8),IF((E36-$J36)+$K36+$I36<=0,IF(AND(E36>0,E36<>""),0,""),(E36-$J36)+$K36+$I36))) | F37: =IF(J36="","",IF(G36+F36+H36+I36-J36<0,0,G36+F36+H36+I36-J36))
B38: =B37+$C$9 -> 46230 | C38: =IF(OR(C37="",C37=0),"",IF(ISBLANK(J37),IF(C37+K37+I37-$C$6<=0,IF(AND(C37>0,C37<>""),0,""),C37+K37+I37-$C$6),IF((C37-J37)+K37+I37<=0,IF(AND(C37>0,C37<>""),0,""),(C37-J37)+K37+I37))) | D38: =IF(OR(D37="",D37=0),"",IF(ISBLANK($J37),IF(D37+$K37+$I37-$C$7<=0,IF(AND(D37>0,D37<>""),0,""),D37+$K37+$I37-$C$7),IF((D37-$J37)+$K37+$I37<=0,IF(AND(D37>0,D37<>""),0,""),(D37-$J37)+$K37+$I37))) | E38: =IF(OR(E37="",E37=0),"",IF(ISBLANK($J37),IF(E37+$K37+$I37-$C$8<=0,IF(AND(E37>0,E37<>""),0,""),E37+$K37+$I37-$C$8),IF((E37-$J37)+$K37+$I37<=0,IF(AND(E37>0,E37<>""),0,""),(E37-$J37)+$K37+$I37))) | F38: =IF(J37="","",IF(G37+F37+H37+I37-J37<0,0,G37+F37+H37+I37-J37))
B39: =B38+$C$9 -> 46237 | C39: =IF(OR(C38="",C38=0),"",IF(ISBLANK(J38),IF(C38+K38+I38-$C$6<=0,IF(AND(C38>0,C38<>""),0,""),C38+K38+I38-$C$6),IF((C38-J38)+K38+I38<=0,IF(AND(C38>0,C38<>""),0,""),(C38-J38)+K38+I38))) | D39: =IF(OR(D38="",D38=0),"",IF(ISBLANK($J38),IF(D38+$K38+$I38-$C$7<=0,IF(AND(D38>0,D38<>""),0,""),D38+$K38+$I38-$C$7),IF((D38-$J38)+$K38+$I38<=0,IF(AND(D38>0,D38<>""),0,""),(D38-$J38)+$K38+$I38))) | E39: =IF(OR(E38="",E38=0),"",IF(ISBLANK($J38),IF(E38+$K38+$I38-$C$8<=0,IF(AND(E38>0,E38<>""),0,""),E38+$K38+$I38-$C$8),IF((E38-$J38)+$K38+$I38<=0,IF(AND(E38>0,E38<>""),0,""),(E38-$J38)+$K38+$I38))) | F39: =IF(J38="","",IF(G38+F38+H38+I38-J38<0,0,G38+F38+H38+I38-J38))
B40: =B39+$C$9 -> 46244 | C40: =IF(OR(C39="",C39=0),"",IF(ISBLANK(J39),IF(C39+K39+I39-$C$6<=0,IF(AND(C39>0,C39<>""),0,""),C39+K39+I39-$C$6),IF((C39-J39)+K39+I39<=0,IF(AND(C39>0,C39<>""),0,""),(C39-J39)+K39+I39))) | D40: =IF(OR(D39="",D39=0),"",IF(ISBLANK($J39),IF(D39+$K39+$I39-$C$7<=0,IF(AND(D39>0,D39<>""),0,""),D39+$K39+$I39-$C$7),IF((D39-$J39)+$K39+$I39<=0,IF(AND(D39>0,D39<>""),0,""),(D39-$J39)+$K39+$I39))) | E40: =IF(OR(E39="",E39=0),"",IF(ISBLANK($J39),IF(E39+$K39+$I39-$C$8<=0,IF(AND(E39>0,E39<>""),0,""),E39+$K39+$I39-$C$8),IF((E39-$J39)+$K39+$I39<=0,IF(AND(E39>0,E39<>""),0,""),(E39-$J39)+$K39+$I39))) | F40: =IF(J39="","",IF(G39+F39+H39+I39-J39<0,0,G39+F39+H39+I39-J39))
B41: =B40+$C$9 -> 46251 | C41: =IF(OR(C40="",C40=0),"",IF(ISBLANK(J40),IF(C40+K40+I40-$C$6<=0,IF(AND(C40>0,C40<>""),0,""),C40+K40+I40-$C$6),IF((C40-J40)+K40+I40<=0,IF(AND(C40>0,C40<>""),0,""),(C40-J40)+K40+I40))) | D41: =IF(OR(D40="",D40=0),"",IF(ISBLANK($J40),IF(D40+$K40+$I40-$C$7<=0,IF(AND(D40>0,D40<>""),0,""),D40+$K40+$I40-$C$7),IF((D40-$J40)+$K40+$I40<=0,IF(AND(D40>0,D40<>""),0,""),(D40-$J40)+$K40+$I40))) | E41: =IF(OR(E40="",E40=0),"",IF(ISBLANK($J40),IF(E40+$K40+$I40-$C$8<=0,IF(AND(E40>0,E40<>""),0,""),E40+$K40+$I40-$C$8),IF((E40-$J40)+$K40+$I40<=0,IF(AND(E40>0,E40<>""),0,""),(E40-$J40)+$K40+$I40))) | F41: =IF(J40="","",IF(G40+F40+H40+I40-J40<0,0,G40+F40+H40+I40-J40))
B42: =B41+$C$9 -> 46258 | C42: =IF(OR(C41="",C41=0),"",IF(ISBLANK(J41),IF(C41+K41+I41-$C$6<=0,IF(AND(C41>0,C41<>""),0,""),C41+K41+I41-$C$6),IF((C41-J41)+K41+I41<=0,IF(AND(C41>0,C41<>""),0,""),(C41-J41)+K41+I41))) | D42: =IF(OR(D41="",D41=0),"",IF(ISBLANK($J41),IF(D41+$K41+$I41-$C$7<=0,IF(AND(D41>0,D41<>""),0,""),D41+$K41+$I41-$C$7),IF((D41-$J41)+$K41+$I41<=0,IF(AND(D41>0,D41<>""),0,""),(D41-$J41)+$K41+$I41))) | E42: =IF(OR(E41="",E41=0),"",IF(ISBLANK($J41),IF(E41+$K41+$I41-$C$8<=0,IF(AND(E41>0,E41<>""),0,""),E41+$K41+$I41-$C$8),IF((E41-$J41)+$K41+$I41<=0,IF(AND(E41>0,E41<>""),0,""),(E41-$J41)+$K41+$I41))) | F42: =IF(J41="","",IF(G41+F41+H41+I41-J41<0,0,G41+F41+H41+I41-J41))
... B54: =B53+$C$9 -> 46342 | C54: =IF(OR(C53="",C53=0),"",IF(ISBLANK(J53),IF(C53+K53+I53-$C$6<=0,IF(AND(C53>0,C53<>""),0,""),C53+K53+I53-$C$6),IF((C53-J53)+K53+I53<=0,IF(AND(C53>0,C53<>""),0,""),(C53-J53)+K53+I53))) | D54: =IF(OR(D53="",D53=0),"",IF(ISBLANK($J53),IF(D53+$K53+$I53-$C$7<=0,IF(AND(D53>0,D53<>""),0,""),D53+$K53+$I53-$C$7),IF((D53-$J53)+$K53+$I53<=0,IF(AND(D53>0,D53<>""),0,""),(D53-$J53)+$K53+$I53))) | E54: =IF(OR(E53="",E53=0),"",IF(ISBLANK($J53),IF(E53+$K53+$I53-$C$8<=0,IF(AND(E53>0,E53<>""),0,""),E53+$K53+$I53-$C$8),IF((E53-$J53)+$K53+$I53<=0,IF(AND(E53>0,E53<>""),0,""),(E53-$J53)+$K53+$I53))) | F54: =IF(J53="","",IF(G53+F53+H53+I53-J53<0,0,G53+F53+H53+I53-J53))
B92: =IF(#REF!="","",IF(#REF!+$C$9<=$C$5,#REF!+$C$9,"")) -> #REF! | C92: =IF(B92<>"",#REF!-$C$2/COUNT($B$17:$B$510),"") -> #REF!
B93: =IF(B92="","",IF(B92+$C$9<=$C$5,B92+$C$9,"")) -> #REF! | C93: =IF(B93<>"",C92-$C$2/COUNT($B$17:$B$510),"") -> #REF!
B94: =IF(B93="","",IF(B93+$C$9<=$C$5,B93+$C$9,"")) -> #REF! | C94: =IF(B94<>"",C93-$C$2/COUNT($B$17:$B$510),"") -> #REF!
B95: =IF(B94="","",IF(B94+$C$9<=$C$5,B94+$C$9,"")) -> #REF! | C95: =IF(B95<>"",C94-$C$2/COUNT($B$17:$B$510),"") -> #REF!
B96: =IF(B95="","",IF(B95+$C$9<=$C$5,B95+$C$9,"")) -> #REF! | C96: =IF(B96<>"",C95-$C$2/COUNT($B$17:$B$510),"") -> #REF!
B97: =IF(B96="","",IF(B96+$C$9<=$C$5,B96+$C$9,"")) -> #REF! | C97: =IF(B97<>"",C96-$C$2/COUNT($B$17:$B$510),"") -> #REF!
B98: =IF(B97="","",IF(B97+$C$9<=$C$5,B97+$C$9,"")) -> #REF! | C98: =IF(B98<>"",C97-$C$2/COUNT($B$17:$B$510),"") -> #REF!
B99: =IF(B98="","",IF(B98+$C$9<=$C$5,B98+$C$9,"")) -> #REF! | C99: =IF(B99<>"",C98-$C$2/COUNT($B$17:$B$510),"") -> #REF!
B100: =IF(B99="","",IF(B99+$C$9<=$C$5,B99+$C$9,"")) -> #REF! | C100: =IF(B100<>"",C99-$C$2/COUNT($B$17:$B$510),"") -> #REF!
B101: =IF(B100="","",IF(B100+$C$9<=$C$5,B100+$C$9,"")) -> #REF! | C101: =IF(B101<>"",C100-$C$2/COUNT($B$17:$B$510),"") -> #REF!
B102: =IF(B101="","",IF(B101+$C$9<=$C$5,B101+$C$9,"")) -> #REF! | C102: =IF(B102<>"",C101-$C$2/COUNT($B$17:$B$510),"") -> #REF!
B103: =IF(B102="","",IF(B102+$C$9<=$C$5,B102+$C$9,"")) -> #REF! | C103: =IF(B103<>"",C102-$C$2/COUNT($B$17:$B$510),"") -> #REF!
B104: =IF(B103="","",IF(B103+$C$9<=$C$5,B103+$C$9,"")) -> #REF! | C104: =IF(B104<>"",C103-$C$2/COUNT($B$17:$B$510),"") -> #REF!
... B511: =IF(B510="","",IF(B510+$C$9<=$C$5,B510+$C$9,"")) -> #REF! | C511: =IF(B511<>"",C510-$C$2/COUNT($B$17:$B$510),"") -> #REF!

Sheet TERA - TESTE
A1: Cone: baseado na nossa vazão, chegaremos na data alvo? O que cabe até data alvo?
B2: Quantidade de Épicos | D2: Épicos | E2: considerar apenas os épicos que estão no mapa de release
B3: Features | C3: 20 | D3: Story / Tarefa / Bug / Spike | E3: considerar o trabalho de todos os integrantes do time, inclsuive tasks de dívidas técnicas e automação
B4: Data início | C4: 46062 | D4: Primeria sprint da release
B5: Data fim esperada | C5: 46118 | D5: Data entregada release
B6: Melhor cenário | C6: 4 | D6: itens por semana | E6: considerar sempre as ultimas 4 sprints para atualizar os números
B7: Pior cenário | C7: 1 | D7: itens por semana | E7: considerar sempre as ultimas 4 sprints para atualizar os números
B8: Velocidade necessária | C8: 6 | D8: itens por semana
B9: Acompanhar a cada | C9: 7 | D9: dias
B11: Data do Início da Semana | C11: Se seguirmos nossa melhor vazão, quando entregamos? | D11: Se seguirmos nossa pior vazão, quando entregamos? | E11: Vazão ideal para atender à data | F11: Itens da sprint anterior que não foram concluídos | G11: Itens que entram em sprint pela primeira vez | H11: Itens que entraram na Sprint depois do planejamento, mas não são "Fura fila" | I11: Itens Fura-Fila que apareceram ao longo da Sprint | J11: Itens entregues na Sprint | K11: Itens que chegaram no backlog do time ao longo da semana, mas não na sprint | L11: Observações adicionais
B12: Não editar esses campos | G12: Preencher com os dados de cada semana
A13: Sprint | B13: Semana | C13: A fazer (melhor cenário) | D13: A fazer (pior cenário) | E13: A fazer (valocidade necessária) | F13: Itens Transbordo | G13: Itens Planejados (Planning) | H13: Itens não planejados na sprint | I13: (+) Expedite | J13: Realizado | K13: (+)(-) Escopo pro time | L13: OBSERVAÇÕES
B14: =C4 -> 46062 | C14: =$C$3 -> 20 | D14: =$C$3 -> 20 | E14: =$C$3 -> 20
A15: Sprint 11 | B15: =B14+$C$9 -> 46069 | C15: =IF(OR(C14="",C14=0),"",IF(ISBLANK($J14),IF(C14+$K14+$I14-$C$6<=0,IF(AND(C14>0,C14<>""),0,""),C14+$K14+$I14-$C$6),IF((C14-$J14)+$K14+$I14<=0,IF(AND(C14>0,C14<>""),0,""),(C14-$J14)+$K14+$I14))) -> 16 | D15: =IF(OR(D14="",D14=0),"",IF(ISBLANK($J14),IF(D14+$K14+$I14-$C$7<=0,IF(AND(D14>0,D14<>""),0,""),D14+$K14+$I14-$C$7),IF((D14-$J14)+$K14+$I14<=0,IF(AND(D14>0,D14<>""),0,""),(D14-$J14)+$K14+$I14))) -> 19 | E15: =IF(OR(E14="",E14=0),"",IF(ISBLANK($J14),IF(E14+$K14+$I14-$C$8<=0,IF(AND(E14>0,E14<>""),0,""),E14+$K14+$I14-$C$8),IF((E14-$J14)+$K14+$I14<=0,IF(AND(E14>0,E14<>""),0,""),(E14-$J14)+$K14+$I14))) -> 14 | F15: =IF(J14="","",IF(G14+F14+H14+I14-J14<0,0,G14+F14+H14+I14-J14))
A16: Sprint 12 | B16: =B15+$C$9 -> 46076 | C16: =IF(OR(C15="",C15=0),"",IF(ISBLANK(J15),IF(C15+K15+I15-$C$6<=0,IF(AND(C15>0,C15<>""),0,""),C15+K15+I15-$C$6),IF((C15-J15)+K15+I15<=0,IF(AND(C15>0,C15<>""),0,""),(C15-J15)+K15+I15))) -> 12 | D16: =IF(OR(D15="",D15=0),"",IF(ISBLANK($J15),IF(D15+$K15+$I15-$C$7<=0,IF(AND(D15>0,D15<>""),0,""),D15+$K15+$I15-$C$7),IF((D15-$J15)+$K15+$I15<=0,IF(AND(D15>0,D15<>""),0,""),(D15-$J15)+$K15+$I15))) -> 18 | E16: =IF(OR(E15="",E15=0),"",IF(ISBLANK($J15),IF(E15+$K15+$I15-$C$8<=0,IF(AND(E15>0,E15<>""),0,""),E15+$K15+$I15-$C$8),IF((E15-$J15)+$K15+$I15<=0,IF(AND(E15>0,E15<>""),0,""),(E15-$J15)+$K15+$I15))) -> 8 | F16: =IF(J15="","",IF(G15+F15+H15+I15-J15<0,0,G15+F15+H15+I15-J15))
A17: Sprint 13 | B17: =B16+$C$9 -> 46083 | C17: =IF(OR(C16="",C16=0),"",IF(ISBLANK(J16),IF(C16+K16+I16-$C$6<=0,IF(AND(C16>0,C16<>""),0,""),C16+K16+I16-$C$6),IF((C16-J16)+K16+I16<=0,IF(AND(C16>0,C16<>""),0,""),(C16-J16)+K16+I16))) -> 8 | D17: =IF(OR(D16="",D16=0),"",IF(ISBLANK($J16),IF(D16+$K16+$I16-$C$7<=0,IF(AND(D16>0,D16<>""),0,""),D16+$K16+$I16-$C$7),IF((D16-$J16)+$K16+$I16<=0,IF(AND(D16>0,D16<>""),0,""),(D16-$J16)+$K16+$I16))) -> 17 | E17: =IF(OR(E16="",E16=0),"",IF(ISBLANK($J16),IF(E16+$K16+$I16-$C$8<=0,IF(AND(E16>0,E16<>""),0,""),E16+$K16+$I16-$C$8),IF((E16-$J16)+$K16+$I16<=0,IF(AND(E16>0,E16<>""),0,""),(E16-$J16)+$K16+$I16))) -> 2 | F17: =IF(J16="","",IF(G16+F16+H16+I16-J16<0,0,G16+F16+H16+I16-J16))
A18: Sprint 14 | B18: =B17+$C$9 -> 46090 | C18: =IF(OR(C17="",C17=0),"",IF(ISBLANK(J17),IF(C17+K17+I17-$C$6<=0,IF(AND(C17>0,C17<>""),0,""),C17+K17+I17-$C$6),IF((C17-J17)+K17+I17<=0,IF(AND(C17>0,C17<>""),0,""),(C17-J17)+K17+I17))) -> 4 | D18: =IF(OR(D17="",D17=0),"",IF(ISBLANK($J17),IF(D17+$K17+$I17-$C$7<=0,IF(AND(D17>0,D17<>""),0,""),D17+$K17+$I17-$C$7),IF((D17-$J17)+$K17+$I17<=0,IF(AND(D17>0,D17<>""),0,""),(D17-$J17)+$K17+$I17))) -> 16 | E18: =IF(OR(E17="",E17=0),"",IF(ISBLANK($J17),IF(E17+$K17+$I17-$C$8<=0,IF(AND(E17>0,E17<>""),0,""),E17+$K17+$I17-$C$8),IF((E17-$J17)+$K17+$I17<=0,IF(AND(E17>0,E17<>""),0,""),(E17-$J17)+$K17+$I17))) -> 0 | F18: =IF(J17="","",IF(G17+F17+H17+I17-J17<0,0,G17+F17+H17+I17-J17))
A19: Sprint 15 | B19: =B18+$C$9 -> 46097 | C19: =IF(OR(C18="",C18=0),"",IF(ISBLANK(J18),IF(C18+K18+I18-$C$6<=0,IF(AND(C18>0,C18<>""),0,""),C18+K18+I18-$C$6),IF((C18-J18)+K18+I18<=0,IF(AND(C18>0,C18<>""),0,""),(C18-J18)+K18+I18))) -> 0 | D19: =IF(OR(D18="",D18=0),"",IF(ISBLANK($J18),IF(D18+$K18+$I18-$C$7<=0,IF(AND(D18>0,D18<>""),0,""),D18+$K18+$I18-$C$7),IF((D18-$J18)+$K18+$I18<=0,IF(AND(D18>0,D18<>""),0,""),(D18-$J18)+$K18+$I18))) -> 15 | E19: =IF(OR(E18="",E18=0),"",IF(ISBLANK($J18),IF(E18+$K18+$I18-$C$8<=0,IF(AND(E18>0,E18<>""),0,""),E18+$K18+$I18-$C$8),IF((E18-$J18)+$K18+$I18<=0,IF(AND(E18>0,E18<>""),0,""),(E18-$J18)+$K18+$I18))) | F19: =IF(J18="","",IF(G18+F18+H18+I18-J18<0,0,G18+F18+H18+I18-J18))
A20: Sprint 16 | B20: =B19+$C$9 -> 46104 | C20: =IF(OR(C19="",C19=0),"",IF(ISBLANK(J19),IF(C19+K19+I19-$C$6<=0,IF(AND(C19>0,C19<>""),0,""),C19+K19+I19-$C$6),IF((C19-J19)+K19+I19<=0,IF(AND(C19>0,C19<>""),0,""),(C19-J19)+K19+I19))) | D20: =IF(OR(D19="",D19=0),"",IF(ISBLANK($J19),IF(D19+$K19+$I19-$C$7<=0,IF(AND(D19>0,D19<>""),0,""),D19+$K19+$I19-$C$7),IF((D19-$J19)+$K19+$I19<=0,IF(AND(D19>0,D19<>""),0,""),(D19-$J19)+$K19+$I19))) -> 14 | E20: =IF(OR(E19="",E19=0),"",IF(ISBLANK($J19),IF(E19+$K19+$I19-$C$8<=0,IF(AND(E19>0,E19<>""),0,""),E19+$K19+$I19-$C$8),IF((E19-$J19)+$K19+$I19<=0,IF(AND(E19>0,E19<>""),0,""),(E19-$J19)+$K19+$I19))) | F20: =IF(J19="","",IF(G19+F19+H19+I19-J19<0,0,G19+F19+H19+I19-J19))
A21: Sprint 17 | B21: =B20+$C$9 -> 46111 | C21: =IF(OR(C20="",C20=0),"",IF(ISBLANK(J20),IF(C20+K20+I20-$C$6<=0,IF(AND(C20>0,C20<>""),0,""),C20+K20+I20-$C$6),IF((C20-J20)+K20+I20<=0,IF(AND(C20>0,C20<>""),0,""),(C20-J20)+K20+I20))) | D21: =IF(OR(D20="",D20=0),"",IF(ISBLANK($J20),IF(D20+$K20+$I20-$C$7<=0,IF(AND(D20>0,D20<>""),0,""),D20+$K20+$I20-$C$7),IF((D20-$J20)+$K20+$I20<=0,IF(AND(D20>0,D20<>""),0,""),(D20-$J20)+$K20+$I20))) -> 13 | E21: =IF(OR(E20="",E20=0),"",IF(ISBLANK($J20),IF(E20+$K20+$I20-$C$8<=0,IF(AND(E20>0,E20<>""),0,""),E20+$K20+$I20-$C$8),IF((E20-$J20)+$K20+$I20<=0,IF(AND(E20>0,E20<>""),0,""),(E20-$J20)+$K20+$I20))) | F21: =IF(J20="","",IF(G20+F20+H20+I20-J20<0,0,G20+F20+H20+I20-J20))
A22: Sprint 18 | B22: =B21+$C$9 -> 46118 | C22: =IF(OR(C21="",C21=0),"",IF(ISBLANK(J21),IF(C21+K21+I21-$C$6<=0,IF(AND(C21>0,C21<>""),0,""),C21+K21+I21-$C$6),IF((C21-J21)+K21+I21<=0,IF(AND(C21>0,C21<>""),0,""),(C21-J21)+K21+I21))) | D22: =IF(OR(D21="",D21=0),"",IF(ISBLANK($J21),IF(D21+$K21+$I21-$C$7<=0,IF(AND(D21>0,D21<>""),0,""),D21+$K21+$I21-$C$7),IF((D21-$J21)+$K21+$I21<=0,IF(AND(D21>0,D21<>""),0,""),(D21-$J21)+$K21+$I21))) -> 12 | E22: =IF(OR(E21="",E21=0),"",IF(ISBLANK($J21),IF(E21+$K21+$I21-$C$8<=0,IF(AND(E21>0,E21<>""),0,""),E21+$K21+$I21-$C$8),IF((E21-$J21)+$K21+$I21<=0,IF(AND(E21>0,E21<>""),0,""),(E21-$J21)+$K21+$I21))) | F22: =IF(J21="","",IF(G21+F21+H21+I21-J21<0,0,G21+F21+H21+I21-J21))
A23: Sprint 19 | B23: =B22+$C$9 -> 46125 | C23: =IF(OR(C22="",C22=0),"",IF(ISBLANK(J22),IF(C22+K22+I22-$C$6<=0,IF(AND(C22>0,C22<>""),0,""),C22+K22+I22-$C$6),IF((C22-J22)+K22+I22<=0,IF(AND(C22>0,C22<>""),0,""),(C22-J22)+K22+I22))) | D23: =IF(OR(D22="",D22=0),"",IF(ISBLANK($J22),IF(D22+$K22+$I22-$C$7<=0,IF(AND(D22>0,D22<>""),0,""),D22+$K22+$I22-$C$7),IF((D22-$J22)+$K22+$I22<=0,IF(AND(D22>0,D22<>""),0,""),(D22-$J22)+$K22+$I22))) -> 11 | E23: =IF(OR(E22="",E22=0),"",IF(ISBLANK($J22),IF(E22+$K22+$I22-$C$8<=0,IF(AND(E22>0,E22<>""),0,""),E22+$K22+$I22-$C$8),IF((E22-$J22)+$K22+$I22<=0,IF(AND(E22>0,E22<>""),0,""),(E22-$J22)+$K22+$I22))) | F23: =IF(J22="","",IF(G22+F22+H22+I22-J22<0,0,G22+F22+H22+I22-J22))
A24: Sprint 20 | B24: =B23+$C$9 -> 46132 | C24: =IF(OR(C23="",C23=0),"",IF(ISBLANK(J23),IF(C23+K23+I23-$C$6<=0,IF(AND(C23>0,C23<>""),0,""),C23+K23+I23-$C$6),IF((C23-J23)+K23+I23<=0,IF(AND(C23>0,C23<>""),0,""),(C23-J23)+K23+I23))) | D24: =IF(OR(D23="",D23=0),"",IF(ISBLANK($J23),IF(D23+$K23+$I23-$C$7<=0,IF(AND(D23>0,D23<>""),0,""),D23+$K23+$I23-$C$7),IF((D23-$J23)+$K23+$I23<=0,IF(AND(D23>0,D23<>""),0,""),(D23-$J23)+$K23+$I23))) -> 10 | E24: =IF(OR(E23="",E23=0),"",IF(ISBLANK($J23),IF(E23+$K23+$I23-$C$8<=0,IF(AND(E23>0,E23<>""),0,""),E23+$K23+$I23-$C$8),IF((E23-$J23)+$K23+$I23<=0,IF(AND(E23>0,E23<>""),0,""),(E23-$J23)+$K23+$I23))) | F24: =IF(J23="","",IF(G23+F23+H23+I23-J23<0,0,G23+F23+H23+I23-J23))
A25: Sprint 21 | B25: =B24+$C$9 -> 46139 | C25: =IF(OR(C24="",C24=0),"",IF(ISBLANK(J24),IF(C24+K24+I24-$C$6<=0,IF(AND(C24>0,C24<>""),0,""),C24+K24+I24-$C$6),IF((C24-J24)+K24+I24<=0,IF(AND(C24>0,C24<>""),0,""),(C24-J24)+K24+I24))) | D25: =IF(OR(D24="",D24=0),"",IF(ISBLANK($J24),IF(D24+$K24+$I24-$C$7<=0,IF(AND(D24>0,D24<>""),0,""),D24+$K24+$I24-$C$7),IF((D24-$J24)+$K24+$I24<=0,IF(AND(D24>0,D24<>""),0,""),(D24-$J24)+$K24+$I24))) -> 9 | E25: =IF(OR(E24="",E24=0),"",IF(ISBLANK($J24),IF(E24+$K24+$I24-$C$8<=0,IF(AND(E24>0,E24<>""),0,""),E24+$K24+$I24-$C$8),IF((E24-$J24)+$K24+$I24<=0,IF(AND(E24>0,E24<>""),0,""),(E24-$J24)+$K24+$I24))) | F25: =IF(J24="","",IF(G24+F24+H24+I24-J24<0,0,G24+F24+H24+I24-J24))
A26: Sprint 22 | B26: =B25+$C$9 -> 46146 | C26: =IF(OR(C25="",C25=0),"",IF(ISBLANK(J25),IF(C25+K25+I25-$C$6<=0,IF(AND(C25>0,C25<>""),0,""),C25+K25+I25-$C$6),IF((C25-J25)+K25+I25<=0,IF(AND(C25>0,C25<>""),0,""),(C25-J25)+K25+I25))) | D26: =IF(OR(D25="",D25=0),"",IF(ISBLANK($J25),IF(D25+$K25+$I25-$C$7<=0,IF(AND(D25>0,D25<>""),0,""),D25+$K25+$I25-$C$7),IF((D25-$J25)+$K25+$I25<=0,IF(AND(D25>0,D25<>""),0,""),(D25-$J25)+$K25+$I25))) -> 8 | E26: =IF(OR(E25="",E25=0),"",IF(ISBLANK($J25),IF(E25+$K25+$I25-$C$8<=0,IF(AND(E25>0,E25<>""),0,""),E25+$K25+$I25-$C$8),IF((E25-$J25)+$K25+$I25<=0,IF(AND(E25>0,E25<>""),0,""),(E25-$J25)+$K25+$I25))) | F26: =IF(J25="","",IF(G25+F25+H25+I25-J25<0,0,G25+F25+H25+I25-J25))
A27: Sprint 23 | B27: =B26+$C$9 -> 46153 | C27: =IF(OR(C26="",C26=0),"",IF(ISBLANK(J26),IF(C26+K26+I26-$C$6<=0,IF(AND(C26>0,C26<>""),0,""),C26+K26+I26-$C$6),IF((C26-J26)+K26+I26<=0,IF(AND(C26>0,C26<>""),0,""),(C26-J26)+K26+I26))) | D27: =IF(OR(D26="",D26=0),"",IF(ISBLANK($J26),IF(D26+$K26+$I26-$C$7<=0,IF(AND(D26>0,D26<>""),0,""),D26+$K26+$I26-$C$7),IF((D26-$J26)+$K26+$I26<=0,IF(AND(D26>0,D26<>""),0,""),(D26-$J26)+$K26+$I26))) -> 7 | E27: =IF(OR(E26="",E26=0),"",IF(ISBLANK($J26),IF(E26+$K26+$I26-$C$8<=0,IF(AND(E26>0,E26<>""),0,""),E26+$K26+$I26-$C$8),IF((E26-$J26)+$K26+$I26<=0,IF(AND(E26>0,E26<>""),0,""),(E26-$J26)+$K26+$I26))) | F27: =IF(J26="","",IF(G26+F26+H26+I26-J26<0,0,G26+F26+H26+I26-J26))
... A30: Sprint 26 | B30: =B29+$C$9 -> 46174 | C30: =IF(OR(C29="",C29=0),"",IF(ISBLANK(J29),IF(C29+K29+I29-$C$6<=0,IF(AND(C29>0,C29<>""),0,""),C29+K29+I29-$C$6),IF((C29-J29)+K29+I29<=0,IF(AND(C29>0,C29<>""),0,""),(C29-J29)+K29+I29))) | D30: =IF(OR(D29="",D29=0),"",IF(ISBLANK($J29),IF(D29+$K29+$I29-$C$7<=0,IF(AND(D29>0,D29<>""),0,""),D29+$K29+$I29-$C$7),IF((D29-$J29)+$K29+$I29<=0,IF(AND(D29>0,D29<>""),0,""),(D29-$J29)+$K29+$I29))) -> 4 | E30: =IF(OR(E29="",E29=0),"",IF(ISBLANK($J29),IF(E29+$K29+$I29-$C$8<=0,IF(AND(E29>0,E29<>""),0,""),E29+$K29+$I29-$C$8),IF((E29-$J29)+$K29+$I29<=0,IF(AND(E29>0,E29<>""),0,""),(E29-$J29)+$K29+$I29))) | F30: =IF(J29="","",IF(G29+F29+H29+I29-J29<0,0,G29+F29+H29+I29-J29))
B31: =B30+$C$9 -> 46181 | C31: =IF(OR(C30="",C30=0),"",IF(ISBLANK(J30),IF(C30+K30+I30-$C$6<=0,IF(AND(C30>0,C30<>""),0,""),C30+K30+I30-$C$6),IF((C30-J30)+K30+I30<=0,IF(AND(C30>0,C30<>""),0,""),(C30-J30)+K30+I30))) | D31: =IF(OR(D30="",D30=0),"",IF(ISBLANK($J30),IF(D30+$K30+$I30-$C$7<=0,IF(AND(D30>0,D30<>""),0,""),D30+$K30+$I30-$C$7),IF((D30-$J30)+$K30+$I30<=0,IF(AND(D30>0,D30<>""),0,""),(D30-$J30)+$K30+$I30))) -> 3 | E31: =IF(OR(E30="",E30=0),"",IF(ISBLANK($J30),IF(E30+$K30+$I30-$C$8<=0,IF(AND(E30>0,E30<>""),0,""),E30+$K30+$I30-$C$8),IF((E30-$J30)+$K30+$I30<=0,IF(AND(E30>0,E30<>""),0,""),(E30-$J30)+$K30+$I30))) | F31: =IF(J30="","",IF(G30+F30+H30+I30-J30<0,0,G30+F30+H30+I30-J30))
B32: =B31+$C$9 -> 46188 | C32: =IF(OR(C31="",C31=0),"",IF(ISBLANK(J31),IF(C31+K31+I31-$C$6<=0,IF(AND(C31>0,C31<>""),0,""),C31+K31+I31-$C$6),IF((C31-J31)+K31+I31<=0,IF(AND(C31>0,C31<>""),0,""),(C31-J31)+K31+I31))) | D32: =IF(OR(D31="",D31=0),"",IF(ISBLANK($J31),IF(D31+$K31+$I31-$C$7<=0,IF(AND(D31>0,D31<>""),0,""),D31+$K31+$I31-$C$7),IF((D31-$J31)+$K31+$I31<=0,IF(AND(D31>0,D31<>""),0,""),(D31-$J31)+$K31+$I31))) -> 2 | E32: =IF(OR(E31="",E31=0),"",IF(ISBLANK($J31),IF(E31+$K31+$I31-$C$8<=0,IF(AND(E31>0,E31<>""),0,""),E31+$K31+$I31-$C$8),IF((E31-$J31)+$K31+$I31<=0,IF(AND(E31>0,E31<>""),0,""),(E31-$J31)+$K31+$I31))) | F32: =IF(J31="","",IF(G31+F31+H31+I31-J31<0,0,G31+F31+H31+I31-J31))
B33: =B32+$C$9 -> 46195 | C33: =IF(OR(C32="",C32=0),"",IF(ISBLANK(J32),IF(C32+K32+I32-$C$6<=0,IF(AND(C32>0,C32<>""),0,""),C32+K32+I32-$C$6),IF((C32-J32)+K32+I32<=0,IF(AND(C32>0,C32<>""),0,""),(C32-J32)+K32+I32))) | D33: =IF(OR(D32="",D32=0),"",IF(ISBLANK($J32),IF(D32+$K32+$I32-$C$7<=0,IF(AND(D32>0,D32<>""),0,""),D32+$K32+$I32-$C$7),IF((D32-$J32)+$K32+$I32<=0,IF(AND(D32>0,D32<>""),0,""),(D32-$J32)+$K32+$I32))) -> 1 | E33: =IF(OR(E32="",E32=0),"",IF(ISBLANK($J32),IF(E32+$K32+$I32-$C$8<=0,IF(AND(E32>0,E32<>""),0,""),E32+$K32+$I32-$C$8),IF((E32-$J32)+$K32+$I32<=0,IF(AND(E32>0,E32<>""),0,""),(E32-$J32)+$K32+$I32))) | F33: =IF(J32="","",IF(G32+F32+H32+I32-J32<0,0,G32+F32+H32+I32-J32))
B34: =B33+$C$9 -> 46202 | C34: =IF(OR(C33="",C33=0),"",IF(ISBLANK(J33),IF(C33+K33+I33-$C$6<=0,IF(AND(C33>0,C33<>""),0,""),C33+K33+I33-$C$6),IF((C33-J33)+K33+I33<=0,IF(AND(C33>0,C33<>""),0,""),(C33-J33)+K33+I33))) | D34: =IF(OR(D33="",D33=0),"",IF(ISBLANK($J33),IF(D33+$K33+$I33-$C$7<=0,IF(AND(D33>0,D33<>""),0,""),D33+$K33+$I33-$C$7),IF((D33-$J33)+$K33+$I33<=0,IF(AND(D33>0,D33<>""),0,""),(D33-$J33)+$K33+$I33))) -> 0 | E34: =IF(OR(E33="",E33=0),"",IF(ISBLANK($J33),IF(E33+$K33+$I33-$C$8<=0,IF(AND(E33>0,E33<>""),0,""),E33+$K33+$I33-$C$8),IF((E33-$J33)+$K33+$I33<=0,IF(AND(E33>0,E33<>""),0,""),(E33-$J33)+$K33+$I33))) | F34: =IF(J33="","",IF(G33+F33+H33+I33-J33<0,0,G33+F33+H33+I33-J33))
B35: =B34+$C$9 -> 46209 | C35: =IF(OR(C34="",C34=0),"",IF(ISBLANK(J34),IF(C34+K34+I34-$C$6<=0,IF(AND(C34>0,C34<>""),0,""),C34+K34+I34-$C$6),IF((C34-J34)+K34+I34<=0,IF(AND(C34>0,C34<>""),0,""),(C34-J34)+K34+I34))) | D35: =IF(OR(D34="",D34=0),"",IF(ISBLANK($J34),IF(D34+$K34+$I34-$C$7<=0,IF(AND(D34>0,D34<>""),0,""),D34+$K34+$I34-$C$7),IF((D34-$J34)+$K34+$I34<=0,IF(AND(D34>0,D34<>""),0,""),(D34-$J34)+$K34+$I34))) | E35: =IF(OR(E34="",E34=0),"",IF(ISBLANK($J34),IF(E34+$K34+$I34-$C$8<=0,IF(AND(E34>0,E34<>""),0,""),E34+$K34+$I34-$C$8),IF((E34-$J34)+$K34+$I34<=0,IF(AND(E34>0,E34<>""),0,""),(E34-$J34)+$K34+$I34))) | F35: =IF(J34="","",IF(G34+F34+H34+I34-J34<0,0,G34+F34+H34+I34-J34))
B36: =B35+$C$9 -> 46216 | C36: =IF(OR(C35="",C35=0),"",IF(ISBLANK(J35),IF(C35+K35+I35-$C$6<=0,IF(AND(C35>0,C35<>""),0,""),C35+K35+I35-$C$6),IF((C35-J35)+K35+I35<=0,IF(AND(C35>0,C35<>""),0,""),(C35-J35)+K35+I35))) | D36: =IF(OR(D35="",D35=0),"",IF(ISBLANK($J35),IF(D35+$K35+$I35-$C$7<=0,IF(AND(D35>0,D35<>""),0,""),D35+$K35+$I35-$C$7),IF((D35-$J35)+$K35+$I35<=0,IF(AND(D35>0,D35<>""),0,""),(D35-$J35)+$K35+$I35))) | E36: =IF(OR(E35="",E35=0),"",IF(ISBLANK($J35),IF(E35+$K35+$I35-$C$8<=0,IF(AND(E35>0,E35<>""),0,""),E35+$K35+$I35-$C$8),IF((E35-$J35)+$K35+$I35<=0,IF(AND(E35>0,E35<>""),0,""),(E35-$J35)+$K35+$I35))) | F36: =IF(J35="","",IF(G35+F35+H35+I35-J35<0,0,G35+F35+H35+I35-J35))
B37: =B36+$C$9 -> 46223 | C37: =IF(OR(C36="",C36=0),"",IF(ISBLANK(J36),IF(C36+K36+I36-$C$6<=0,IF(AND(C36>0,C36<>""),0,""),C36+K36+I36-$C$6),IF((C36-J36)+K36+I36<=0,IF(AND(C36>0,C36<>""),0,""),(C36-J36)+K36+I36))) | D37: =IF(OR(D36="",D36=0),"",IF(ISBLANK($J36),IF(D36+$K36+$I36-$C$7<=0,IF(AND(D36>0,D36<>""),0,""),D36+$K36+$I36-$C$7),IF((D36-$J36)+$K36+$I36<=0,IF(AND(D36>0,D36<>""),0,""),(D36-$J36)+$K36+$I36))) | E37: =IF(OR(E36="",E36=0),"",IF(ISBLANK($J36),IF(E36+$K36+$I36-$C$8<=0,IF(AND(E36>0,E36<>""),0,""),E36+$K36+$I36-$C$8),IF((E36-$J36)+$K36+$I36<=0,IF(AND(E36>0,E36<>""),0,""),(E36-$J36)+$K36+$I36))) | F37: =IF(J36="","",IF(G36+F36+H36+I36-J36<0,0,G36+F36+H36+I36-J36))
B38: =B37+$C$9 -> 46230 | C38: =IF(OR(C37="",C37=0),"",IF(ISBLANK(J37),IF(C37+K37+I37-$C$6<=0,IF(AND(C37>0,C37<>""),0,""),C37+K37+I37-$C$6),IF((C37-J37)+K37+I37<=0,IF(AND(C37>0,C37<>""),0,""),(C37-J37)+K37+I37))) | D38: =IF(OR(D37="",D37=0),"",IF(ISBLANK($J37),IF(D37+$K37+$I37-$C$7<=0,IF(AND(D37>0,D37<>""),0,""),D37+$K37+$I37-$C$7),IF((D37-$J37)+$K37+$I37<=0,IF(AND(D37>0,D37<>""),0,""),(D37-$J37)+$K37+$I37))) | E38: =IF(OR(E37="",E37=0),"",IF(ISBLANK($J37),IF(E37+$K37+$I37-$C$8<=0,IF(AND(E37>0,E37<>""),0,""),E37+$K37+$I37-$C$8),IF((E37-$J37)+$K37+$I37<=0,IF(AND(E37>0,E37<>""),0,""),(E37-$J37)+$K37+$I37))) | F38: =IF(J37="","",IF(G37+F37+H37+I37-J37<0,0,G37+F37+H37+I37-J37))
B39: =B38+$C$9 -> 46237 | C39: =IF(OR(C38="",C38=0),"",IF(ISBLANK(J38),IF(C38+K38+I38-$C$6<=0,IF(AND(C38>0,C38<>""),0,""),C38+K38+I38-$C$6),IF((C38-J38)+K38+I38<=0,IF(AND(C38>0,C38<>""),0,""),(C38-J38)+K38+I38))) | D39: =IF(OR(D38="",D38=0),"",IF(ISBLANK($J38),IF(D38+$K38+$I38-$C$7<=0,IF(AND(D38>0,D38<>""),0,""),D38+$K38+$I38-$C$7),IF((D38-$J38)+$K38+$I38<=0,IF(AND(D38>0,D38<>""),0,""),(D38-$J38)+$K38+$I38))) | E39: =IF(OR(E38="",E38=0),"",IF(ISBLANK($J38),IF(E38+$K38+$I38-$C$8<=0,IF(AND(E38>0,E38<>""),0,""),E38+$K38+$I38-$C$8),IF((E38-$J38)+$K38+$I38<=0,IF(AND(E38>0,E38<>""),0,""),(E38-$J38)+$K38+$I38))) | F39: =IF(J38="","",IF(G38+F38+H38+I38-J38<0,0,G38+F38+H38+I38-J38))
B40: =B39+$C$9 -> 46244 | C40: =IF(OR(C39="",C39=0),"",IF(ISBLANK(J39),IF(C39+K39+I39-$C$6<=0,IF(AND(C39>0,C39<>""),0,""),C39+K39+I39-$C$6),IF((C39-J39)+K39+I39<=0,IF(AND(C39>0,C39<>""),0,""),(C39-J39)+K39+I39))) | D40: =IF(OR(D39="",D39=0),"",IF(ISBLANK($J39),IF(D39+$K39+$I39-$C$7<=0,IF(AND(D39>0,D39<>""),0,""),D39+$K39+$I39-$C$7),IF((D39-$J39)+$K39+$I39<=0,IF(AND(D39>0,D39<>""),0,""),(D39-$J39)+$K39+$I39))) | E40: =IF(OR(E39="",E39=0),"",IF(ISBLANK($J39),IF(E39+$K39+$I39-$C$8<=0,IF(AND(E39>0,E39<>""),0,""),E39+$K39+$I39-$C$8),IF((E39-$J39)+$K39+$I39<=0,IF(AND(E39>0,E39<>""),0,""),(E39-$J39)+$K39+$I39))) | F40: =IF(J39="","",IF(G39+F39+H39+I39-J39<0,0,G39+F39+H39+I39-J39))
B41: =B40+$C$9 -> 46251 | C41: =IF(OR(C40="",C40=0),"",IF(ISBLANK(J40),IF(C40+K40+I40-$C$6<=0,IF(AND(C40>0,C40<>""),0,""),C40+K40+I40-$C$6),IF((C40-J40)+K40+I40<=0,IF(AND(C40>0,C40<>""),0,""),(C40-J40)+K40+I40))) | D41: =IF(OR(D40="",D40=0),"",IF(ISBLANK($J40),IF(D40+$K40+$I40-$C$7<=0,IF(AND(D40>0,D40<>""),0,""),D40+$K40+$I40-$C$7),IF((D40-$J40)+$K40+$I40<=0,IF(AND(D40>0,D40<>""),0,""),(D40-$J40)+$K40+$I40))) | E41: =IF(OR(E40="",E40=0),"",IF(ISBLANK($J40),IF(E40+$K40+$I40-$C$8<=0,IF(AND(E40>0,E40<>""),0,""),E40+$K40+$I40-$C$8),IF((E40-$J40)+$K40+$I40<=0,IF(AND(E40>0,E40<>""),0,""),(E40-$J40)+$K40+$I40))) | F41: =IF(J40="","",IF(G40+F40+H40+I40-J40<0,0,G40+F40+H40+I40-J40))
B42: =B41+$C$9 -> 46258 | C42: =IF(OR(C41="",C41=0),"",IF(ISBLANK(J41),IF(C41+K41+I41-$C$6<=0,IF(AND(C41>0,C41<>""),0,""),C41+K41+I41-$C$6),IF((C41-J41)+K41+I41<=0,IF(AND(C41>0,C41<>""),0,""),(C41-J41)+K41+I41))) | D42: =IF(OR(D41="",D41=0),"",IF(ISBLANK($J41),IF(D41+$K41+$I41-$C$7<=0,IF(AND(D41>0,D41<>""),0,""),D41+$K41+$I41-$C$7),IF((D41-$J41)+$K41+$I41<=0,IF(AND(D41>0,D41<>""),0,""),(D41-$J41)+$K41+$I41))) | E42: =IF(OR(E41="",E41=0),"",IF(ISBLANK($J41),IF(E41+$K41+$I41-$C$8<=0,IF(AND(E41>0,E41<>""),0,""),E41+$K41+$I41-$C$8),IF((E41-$J41)+$K41+$I41<=0,IF(AND(E41>0,E41<>""),0,""),(E41-$J41)+$K41+$I41))) | F42: =IF(J41="","",IF(G41+F41+H41+I41-J41<0,0,G41+F41+H41+I41-J41))
... B54: =B53+$C$9 -> 46342 | C54: =IF(OR(C53="",C53=0),"",IF(ISBLANK(J53),IF(C53+K53+I53-$C$6<=0,IF(AND(C53>0,C53<>""),0,""),C53+K53+I53-$C$6),IF((C53-J53)+K53+I53<=0,IF(AND(C53>0,C53<>""),0,""),(C53-J53)+K53+I53))) | D54: =IF(OR(D53="",D53=0),"",IF(ISBLANK($J53),IF(D53+$K53+$I53-$C$7<=0,IF(AND(D53>0,D53<>""),0,""),D53+$K53+$I53-$C$7),IF((D53-$J53)+$K53+$I53<=0,IF(AND(D53>0,D53<>""),0,""),(D53-$J53)+$K53+$I53))) | E54: =IF(OR(E53="",E53=0),"",IF(ISBLANK($J53),IF(E53+$K53+$I53-$C$8<=0,IF(AND(E53>0,E53<>""),0,""),E53+$K53+$I53-$C$8),IF((E53-$J53)+$K53+$I53<=0,IF(AND(E53>0,E53<>""),0,""),(E53-$J53)+$K53+$I53))) | F54: =IF(J53="","",IF(G53+F53+H53+I53-J53<0,0,G53+F53+H53+I53-J53))
B92: =IF(#REF!="","",IF(#REF!+$C$9<=$C$5,#REF!+$C$9,"")) -> #REF! | C92: =IF(B92<>"",#REF!-$C$2/COUNT($B$17:$B$510),"") -> #REF!
B93: =IF(B92="","",IF(B92+$C$9<=$C$5,B92+$C$9,"")) -> #REF! | C93: =IF(B93<>"",C92-$C$2/COUNT($B$17:$B$510),"") -> #REF!
B94: =IF(B93="","",IF(B93+$C$9<=$C$5,B93+$C$9,"")) -> #REF! | C94: =IF(B94<>"",C93-$C$2/COUNT($B$17:$B$510),"") -> #REF!
B95: =IF(B94="","",IF(B94+$C$9<=$C$5,B94+$C$9,"")) -> #REF! | C95: =IF(B95<>"",C94-$C$2/COUNT($B$17:$B$510),"") -> #REF!
B96: =IF(B95="","",IF(B95+$C$9<=$C$5,B95+$C$9,"")) -> #REF! | C96: =IF(B96<>"",C95-$C$2/COUNT($B$17:$B$510),"") -> #REF!
B97: =IF(B96="","",IF(B96+$C$9<=$C$5,B96+$C$9,"")) -> #REF! | C97: =IF(B97<>"",C96-$C$2/COUNT($B$17:$B$510),"") -> #REF!
B98: =IF(B97="","",IF(B97+$C$9<=$C$5,B97+$C$9,"")) -> #REF! | C98: =IF(B98<>"",C97-$C$2/COUNT($B$17:$B$510),"") -> #REF!
B99: =IF(B98="","",IF(B98+$C$9<=$C$5,B98+$C$9,"")) -> #REF! | C99: =IF(B99<>"",C98-$C$2/COUNT($B$17:$B$510),"") -> #REF!
B100: =IF(B99="","",IF(B99+$C$9<=$C$5,B99+$C$9,"")) -> #REF! | C100: =IF(B100<>"",C99-$C$2/COUNT($B$17:$B$510),"") -> #REF!
B101: =IF(B100="","",IF(B100+$C$9<=$C$5,B100+$C$9,"")) -> #REF! | C101: =IF(B101<>"",C100-$C$2/COUNT($B$17:$B$510),"") -> #REF!
B102: =IF(B101="","",IF(B101+$C$9<=$C$5,B101+$C$9,"")) -> #REF! | C102: =IF(B102<>"",C101-$C$2/COUNT($B$17:$B$510),"") -> #REF!
B103: =IF(B102="","",IF(B102+$C$9<=$C$5,B102+$C$9,"")) -> #REF! | C103: =IF(B103<>"",C102-$C$2/COUNT($B$17:$B$510),"") -> #REF!
B104: =IF(B103="","",IF(B103+$C$9<=$C$5,B103+$C$9,"")) -> #REF! | C104: =IF(B104<>"",C103-$C$2/COUNT($B$17:$B$510),"") -> #REF!
... B511: =IF(B510="","",IF(B510+$C$9<=$C$5,B510+$C$9,"")) -> #REF! | C511: =IF(B511<>"",C510-$C$2/COUNT($B$17:$B$510),"") -> #REF!

Sheet OPTMIUS - TESTE
A1: Cone: baseado na nossa vazão, chegaremos na data alvo? O que cabe até data alvo?
B2: Quantidade de Épicos | D2: Épicos | E2: considerar apenas os épicos que estão no mapa de release
B3: Features | C3: 53 | D3: Story / Tarefa / Bug / Spike | E3: considerar o trabalho de todos os integrantes do time, inclsuive tasks de dívidas técnicas e automação
B4: Data início | C4: 46062 | D4: Primeria sprint da release
B5: Data fim esperada | C5: 46118 | D5: Data entregada release
B6: Melhor cenário | C6: 4 | D6: itens por semana | E6: considerar sempre as ultimas 4 sprints para atualizar os números
B7: Pior cenário | C7: 1 | D7: itens por semana | E7: considerar sempre as ultimas 4 sprints para atualizar os números
B8: Velocidade necessária | C8: 6 | D8: itens por semana
B9: Acompanhar a cada | C9: 7 | D9: dias
B11: Data do Início da Semana | C11: Se seguirmos nossa melhor vazão, quando entregamos? | D11: Se seguirmos nossa pior vazão, quando entregamos? | E11: Vazão ideal para atender à data | F11: Itens da sprint anterior que não foram concluídos | G11: Itens que entram em sprint pela primeira vez | H11: Itens que entraram na Sprint depois do planejamento, mas não são "Fura fila" | I11: Itens Fura-Fila que apareceram ao longo da Sprint | J11: Itens entregues na Sprint | K11: Itens que chegaram no backlog do time ao longo da semana, mas não na sprint | L11: Observações adicionais
B12: Não editar esses campos | G12: Preencher com os dados de cada semana
A13: Sprint | B13: Semana | C13: A fazer (melhor cenário) | D13: A fazer (pior cenário) | E13: A fazer (valocidade necessária) | F13: Itens Transbordo | G13: Itens Planejados (Planning) | H13: Itens não planejados na sprint | I13: (+) Expedite | J13: Realizado | K13: (+)(-) Escopo pro time | L13: OBSERVAÇÕES
B14: =C4 -> 46062 | C14: =$C$3 -> 53 | D14: =$C$3 -> 53 | E14: =$C$3 -> 53
A15: Sprint 11 | B15: =B14+$C$9 -> 46069 | C15: =IF(OR(C14="",C14=0),"",IF(ISBLANK($J14),IF(C14+$K14+$I14-$C$6<=0,IF(AND(C14>0,C14<>""),0,""),C14+$K14+$I14-$C$6),IF((C14-$J14)+$K14+$I14<=0,IF(AND(C14>0,C14<>""),0,""),(C14-$J14)+$K14+$I14))) -> 49 | D15: =IF(OR(D14="",D14=0),"",IF(ISBLANK($J14),IF(D14+$K14+$I14-$C$7<=0,IF(AND(D14>0,D14<>""),0,""),D14+$K14+$I14-$C$7),IF((D14-$J14)+$K14+$I14<=0,IF(AND(D14>0,D14<>""),0,""),(D14-$J14)+$K14+$I14))) -> 52 | E15: =IF(OR(E14="",E14=0),"",IF(ISBLANK($J14),IF(E14+$K14+$I14-$C$8<=0,IF(AND(E14>0,E14<>""),0,""),E14+$K14+$I14-$C$8),IF((E14-$J14)+$K14+$I14<=0,IF(AND(E14>0,E14<>""),0,""),(E14-$J14)+$K14+$I14))) -> 47 | F15: =IF(J14="","",IF(G14+F14+H14+I14-J14<0,0,G14+F14+H14+I14-J14))
A16: Sprint 12 | B16: =B15+$C$9 -> 46076 | C16: =IF(OR(C15="",C15=0),"",IF(ISBLANK(J15),IF(C15+K15+I15-$C$6<=0,IF(AND(C15>0,C15<>""),0,""),C15+K15+I15-$C$6),IF((C15-J15)+K15+I15<=0,IF(AND(C15>0,C15<>""),0,""),(C15-J15)+K15+I15))) -> 45 | D16: =IF(OR(D15="",D15=0),"",IF(ISBLANK($J15),IF(D15+$K15+$I15-$C$7<=0,IF(AND(D15>0,D15<>""),0,""),D15+$K15+$I15-$C$7),IF((D15-$J15)+$K15+$I15<=0,IF(AND(D15>0,D15<>""),0,""),(D15-$J15)+$K15+$I15))) -> 51 | E16: =IF(OR(E15="",E15=0),"",IF(ISBLANK($J15),IF(E15+$K15+$I15-$C$8<=0,IF(AND(E15>0,E15<>""),0,""),E15+$K15+$I15-$C$8),IF((E15-$J15)+$K15+$I15<=0,IF(AND(E15>0,E15<>""),0,""),(E15-$J15)+$K15+$I15))) -> 41 | F16: =IF(J15="","",IF(G15+F15+H15+I15-J15<0,0,G15+F15+H15+I15-J15))
A17: Sprint 13 | B17: =B16+$C$9 -> 46083 | C17: =IF(OR(C16="",C16=0),"",IF(ISBLANK(J16),IF(C16+K16+I16-$C$6<=0,IF(AND(C16>0,C16<>""),0,""),C16+K16+I16-$C$6),IF((C16-J16)+K16+I16<=0,IF(AND(C16>0,C16<>""),0,""),(C16-J16)+K16+I16))) -> 41 | D17: =IF(OR(D16="",D16=0),"",IF(ISBLANK($J16),IF(D16+$K16+$I16-$C$7<=0,IF(AND(D16>0,D16<>""),0,""),D16+$K16+$I16-$C$7),IF((D16-$J16)+$K16+$I16<=0,IF(AND(D16>0,D16<>""),0,""),(D16-$J16)+$K16+$I16))) -> 50 | E17: =IF(OR(E16="",E16=0),"",IF(ISBLANK($J16),IF(E16+$K16+$I16-$C$8<=0,IF(AND(E16>0,E16<>""),0,""),E16+$K16+$I16-$C$8),IF((E16-$J16)+$K16+$I16<=0,IF(AND(E16>0,E16<>""),0,""),(E16-$J16)+$K16+$I16))) -> 35 | F17: =IF(J16="","",IF(G16+F16+H16+I16-J16<0,0,G16+F16+H16+I16-J16))
A18: Sprint 14 | B18: =B17+$C$9 -> 46090 | C18: =IF(OR(C17="",C17=0),"",IF(ISBLANK(J17),IF(C17+K17+I17-$C$6<=0,IF(AND(C17>0,C17<>""),0,""),C17+K17+I17-$C$6),IF((C17-J17)+K17+I17<=0,IF(AND(C17>0,C17<>""),0,""),(C17-J17)+K17+I17))) -> 37 | D18: =IF(OR(D17="",D17=0),"",IF(ISBLANK($J17),IF(D17+$K17+$I17-$C$7<=0,IF(AND(D17>0,D17<>""),0,""),D17+$K17+$I17-$C$7),IF((D17-$J17)+$K17+$I17<=0,IF(AND(D17>0,D17<>""),0,""),(D17-$J17)+$K17+$I17))) -> 49 | E18: =IF(OR(E17="",E17=0),"",IF(ISBLANK($J17),IF(E17+$K17+$I17-$C$8<=0,IF(AND(E17>0,E17<>""),0,""),E17+$K17+$I17-$C$8),IF((E17-$J17)+$K17+$I17<=0,IF(AND(E17>0,E17<>""),0,""),(E17-$J17)+$K17+$I17))) -> 29 | F18: =IF(J17="","",IF(G17+F17+H17+I17-J17<0,0,G17+F17+H17+I17-J17))
A19: Sprint 15 | B19: =B18+$C$9 -> 46097 | C19: =IF(OR(C18="",C18=0),"",IF(ISBLANK(J18),IF(C18+K18+I18-$C$6<=0,IF(AND(C18>0,C18<>""),0,""),C18+K18+I18-$C$6),IF((C18-J18)+K18+I18<=0,IF(AND(C18>0,C18<>""),0,""),(C18-J18)+K18+I18))) -> 33 | D19: =IF(OR(D18="",D18=0),"",IF(ISBLANK($J18),IF(D18+$K18+$I18-$C$7<=0,IF(AND(D18>0,D18<>""),0,""),D18+$K18+$I18-$C$7),IF((D18-$J18)+$K18+$I18<=0,IF(AND(D18>0,D18<>""),0,""),(D18-$J18)+$K18+$I18))) -> 48 | E19: =IF(OR(E18="",E18=0),"",IF(ISBLANK($J18),IF(E18+$K18+$I18-$C$8<=0,IF(AND(E18>0,E18<>""),0,""),E18+$K18+$I18-$C$8),IF((E18-$J18)+$K18+$I18<=0,IF(AND(E18>0,E18<>""),0,""),(E18-$J18)+$K18+$I18))) -> 23 | F19: =IF(J18="","",IF(G18+F18+H18+I18-J18<0,0,G18+F18+H18+I18-J18))
A20: Sprint 16 | B20: =B19+$C$9 -> 46104 | C20: =IF(OR(C19="",C19=0),"",IF(ISBLANK(J19),IF(C19+K19+I19-$C$6<=0,IF(AND(C19>0,C19<>""),0,""),C19+K19+I19-$C$6),IF((C19-J19)+K19+I19<=0,IF(AND(C19>0,C19<>""),0,""),(C19-J19)+K19+I19))) -> 29 | D20: =IF(OR(D19="",D19=0),"",IF(ISBLANK($J19),IF(D19+$K19+$I19-$C$7<=0,IF(AND(D19>0,D19<>""),0,""),D19+$K19+$I19-$C$7),IF((D19-$J19)+$K19+$I19<=0,IF(AND(D19>0,D19<>""),0,""),(D19-$J19)+$K19+$I19))) -> 47 | E20: =IF(OR(E19="",E19=0),"",IF(ISBLANK($J19),IF(E19+$K19+$I19-$C$8<=0,IF(AND(E19>0,E19<>""),0,""),E19+$K19+$I19-$C$8),IF((E19-$J19)+$K19+$I19<=0,IF(AND(E19>0,E19<>""),0,""),(E19-$J19)+$K19+$I19))) -> 17 | F20: =IF(J19="","",IF(G19+F19+H19+I19-J19<0,0,G19+F19+H19+I19-J19))
A21: Sprint 17 | B21: =B20+$C$9 -> 46111 | C21: =IF(OR(C20="",C20=0),"",IF(ISBLANK(J20),IF(C20+K20+I20-$C$6<=0,IF(AND(C20>0,C20<>""),0,""),C20+K20+I20-$C$6),IF((C20-J20)+K20+I20<=0,IF(AND(C20>0,C20<>""),0,""),(C20-J20)+K20+I20))) -> 25 | D21: =IF(OR(D20="",D20=0),"",IF(ISBLANK($J20),IF(D20+$K20+$I20-$C$7<=0,IF(AND(D20>0,D20<>""),0,""),D20+$K20+$I20-$C$7),IF((D20-$J20)+$K20+$I20<=0,IF(AND(D20>0,D20<>""),0,""),(D20-$J20)+$K20+$I20))) -> 46 | E21: =IF(OR(E20="",E20=0),"",IF(ISBLANK($J20),IF(E20+$K20+$I20-$C$8<=0,IF(AND(E20>0,E20<>""),0,""),E20+$K20+$I20-$C$8),IF((E20-$J20)+$K20+$I20<=0,IF(AND(E20>0,E20<>""),0,""),(E20-$J20)+$K20+$I20))) -> 11 | F21: =IF(J20="","",IF(G20+F20+H20+I20-J20<0,0,G20+F20+H20+I20-J20))
A22: Sprint 18 | B22: =B21+$C$9 -> 46118 | C22: =IF(OR(C21="",C21=0),"",IF(ISBLANK(J21),IF(C21+K21+I21-$C$6<=0,IF(AND(C21>0,C21<>""),0,""),C21+K21+I21-$C$6),IF((C21-J21)+K21+I21<=0,IF(AND(C21>0,C21<>""),0,""),(C21-J21)+K21+I21))) -> 21 | D22: =IF(OR(D21="",D21=0),"",IF(ISBLANK($J21),IF(D21+$K21+$I21-$C$7<=0,IF(AND(D21>0,D21<>""),0,""),D21+$K21+$I21-$C$7),IF((D21-$J21)+$K21+$I21<=0,IF(AND(D21>0,D21<>""),0,""),(D21-$J21)+$K21+$I21))) -> 45 | E22: =IF(OR(E21="",E21=0),"",IF(ISBLANK($J21),IF(E21+$K21+$I21-$C$8<=0,IF(AND(E21>0,E21<>""),0,""),E21+$K21+$I21-$C$8),IF((E21-$J21)+$K21+$I21<=0,IF(AND(E21>0,E21<>""),0,""),(E21-$J21)+$K21+$I21))) -> 5 | F22: =IF(J21="","",IF(G21+F21+H21+I21-J21<0,0,G21+F21+H21+I21-J21))
A23: Sprint 19 | B23: =B22+$C$9 -> 46125 | C23: =IF(OR(C22="",C22=0),"",IF(ISBLANK(J22),IF(C22+K22+I22-$C$6<=0,IF(AND(C22>0,C22<>""),0,""),C22+K22+I22-$C$6),IF((C22-J22)+K22+I22<=0,IF(AND(C22>0,C22<>""),0,""),(C22-J22)+K22+I22))) -> 17 | D23: =IF(OR(D22="",D22=0),"",IF(ISBLANK($J22),IF(D22+$K22+$I22-$C$7<=0,IF(AND(D22>0,D22<>""),0,""),D22+$K22+$I22-$C$7),IF((D22-$J22)+$K22+$I22<=0,IF(AND(D22>0,D22<>""),0,""),(D22-$J22)+$K22+$I22))) -> 44 | E23: =IF(OR(E22="",E22=0),"",IF(ISBLANK($J22),IF(E22+$K22+$I22-$C$8<=0,IF(AND(E22>0,E22<>""),0,""),E22+$K22+$I22-$C$8),IF((E22-$J22)+$K22+$I22<=0,IF(AND(E22>0,E22<>""),0,""),(E22-$J22)+$K22+$I22))) -> 0 | F23: =IF(J22="","",IF(G22+F22+H22+I22-J22<0,0,G22+F22+H22+I22-J22))
A24: Sprint 20 | B24: =B23+$C$9 -> 46132 | C24: =IF(OR(C23="",C23=0),"",IF(ISBLANK(J23),IF(C23+K23+I23-$C$6<=0,IF(AND(C23>0,C23<>""),0,""),C23+K23+I23-$C$6),IF((C23-J23)+K23+I23<=0,IF(AND(C23>0,C23<>""),0,""),(C23-J23)+K23+I23))) -> 13 | D24: =IF(OR(D23="",D23=0),"",IF(ISBLANK($J23),IF(D23+$K23+$I23-$C$7<=0,IF(AND(D23>0,D23<>""),0,""),D23+$K23+$I23-$C$7),IF((D23-$J23)+$K23+$I23<=0,IF(AND(D23>0,D23<>""),0,""),(D23-$J23)+$K23+$I23))) -> 43 | E24: =IF(OR(E23="",E23=0),"",IF(ISBLANK($J23),IF(E23+$K23+$I23-$C$8<=0,IF(AND(E23>0,E23<>""),0,""),E23+$K23+$I23-$C$8),IF((E23-$J23)+$K23+$I23<=0,IF(AND(E23>0,E23<>""),0,""),(E23-$J23)+$K23+$I23))) | F24: =IF(J23="","",IF(G23+F23+H23+I23-J23<0,0,G23+F23+H23+I23-J23))
A25: Sprint 21 | B25: =B24+$C$9 -> 46139 | C25: =IF(OR(C24="",C24=0),"",IF(ISBLANK(J24),IF(C24+K24+I24-$C$6<=0,IF(AND(C24>0,C24<>""),0,""),C24+K24+I24-$C$6),IF((C24-J24)+K24+I24<=0,IF(AND(C24>0,C24<>""),0,""),(C24-J24)+K24+I24))) -> 9 | D25: =IF(OR(D24="",D24=0),"",IF(ISBLANK($J24),IF(D24+$K24+$I24-$C$7<=0,IF(AND(D24>0,D24<>""),0,""),D24+$K24+$I24-$C$7),IF((D24-$J24)+$K24+$I24<=0,IF(AND(D24>0,D24<>""),0,""),(D24-$J24)+$K24+$I24))) -> 42 | E25: =IF(OR(E24="",E24=0),"",IF(ISBLANK($J24),IF(E24+$K24+$I24-$C$8<=0,IF(AND(E24>0,E24<>""),0,""),E24+$K24+$I24-$C$8),IF((E24-$J24)+$K24+$I24<=0,IF(AND(E24>0,E24<>""),0,""),(E24-$J24)+$K24+$I24))) | F25: =IF(J24="","",IF(G24+F24+H24+I24-J24<0,0,G24+F24+H24+I24-J24))
A26: Sprint 22 | B26: =B25+$C$9 -> 46146 | C26: =IF(OR(C25="",C25=0),"",IF(ISBLANK(J25),IF(C25+K25+I25-$C$6<=0,IF(AND(C25>0,C25<>""),0,""),C25+K25+I25-$C$6),IF((C25-J25)+K25+I25<=0,IF(AND(C25>0,C25<>""),0,""),(C25-J25)+K25+I25))) -> 5 | D26: =IF(OR(D25="",D25=0),"",IF(ISBLANK($J25),IF(D25+$K25+$I25-$C$7<=0,IF(AND(D25>0,D25<>""),0,""),D25+$K25+$I25-$C$7),IF((D25-$J25)+$K25+$I25<=0,IF(AND(D25>0,D25<>""),0,""),(D25-$J25)+$K25+$I25))) -> 41 | E26: =IF(OR(E25="",E25=0),"",IF(ISBLANK($J25),IF(E25+$K25+$I25-$C$8<=0,IF(AND(E25>0,E25<>""),0,""),E25+$K25+$I25-$C$8),IF((E25-$J25)+$K25+$I25<=0,IF(AND(E25>0,E25<>""),0,""),(E25-$J25)+$K25+$I25))) | F26: =IF(J25="","",IF(G25+F25+H25+I25-J25<0,0,G25+F25+H25+I25-J25))
A27: Sprint 23 | B27: =B26+$C$9 -> 46153 | C27: =IF(OR(C26="",C26=0),"",IF(ISBLANK(J26),IF(C26+K26+I26-$C$6<=0,IF(AND(C26>0,C26<>""),0,""),C26+K26+I26-$C$6),IF((C26-J26)+K26+I26<=0,IF(AND(C26>0,C26<>""),0,""),(C26-J26)+K26+I26))) -> 1 | D27: =IF(OR(D26="",D26=0),"",IF(ISBLANK($J26),IF(D26+$K26+$I26-$C$7<=0,IF(AND(D26>0,D26<>""),0,""),D26+$K26+$I26-$C$7),IF((D26-$J26)+$K26+$I26<=0,IF(AND(D26>0,D26<>""),0,""),(D26-$J26)+$K26+$I26))) -> 40 | E27: =IF(OR(E26="",E26=0),"",IF(ISBLANK($J26),IF(E26+$K26+$I26-$C$8<=0,IF(AND(E26>0,E26<>""),0,""),E26+$K26+$I26-$C$8),IF((E26-$J26)+$K26+$I26<=0,IF(AND(E26>0,E26<>""),0,""),(E26-$J26)+$K26+$I26))) | F27: =IF(J26="","",IF(G26+F26+H26+I26-J26<0,0,G26+F26+H26+I26-J26))
... A30: Sprint 26 | B30: =B29+$C$9 -> 46174 | C30: =IF(OR(C29="",C29=0),"",IF(ISBLANK(J29),IF(C29+K29+I29-$C$6<=0,IF(AND(C29>0,C29<>""),0,""),C29+K29+I29-$C$6),IF((C29-J29)+K29+I29<=0,IF(AND(C29>0,C29<>""),0,""),(C29-J29)+K29+I29))) | D30: =IF(OR(D29="",D29=0),"",IF(ISBLANK($J29),IF(D29+$K29+$I29-$C$7<=0,IF(AND(D29>0,D29<>""),0,""),D29+$K29+$I29-$C$7),IF((D29-$J29)+$K29+$I29<=0,IF(AND(D29>0,D29<>""),0,""),(D29-$J29)+$K29+$I29))) -> 37 | E30: =IF(OR(E29="",E29=0),"",IF(ISBLANK($J29),IF(E29+$K29+$I29-$C$8<=0,IF(AND(E29>0,E29<>""),0,""),E29+$K29+$I29-$C$8),IF((E29-$J29)+$K29+$I29<=0,IF(AND(E29>0,E29<>""),0,""),(E29-$J29)+$K29+$I29))) | F30: =IF(J29="","",IF(G29+F29+H29+I29-J29<0,0,G29+F29+H29+I29-J29))
B31: =B30+$C$9 -> 46181 | C31: =IF(OR(C30="",C30=0),"",IF(ISBLANK(J30),IF(C30+K30+I30-$C$6<=0,IF(AND(C30>0,C30<>""),0,""),C30+K30+I30-$C$6),IF((C30-J30)+K30+I30<=0,IF(AND(C30>0,C30<>""),0,""),(C30-J30)+K30+I30))) | D31: =IF(OR(D30="",D30=0),"",IF(ISBLANK($J30),IF(D30+$K30+$I30-$C$7<=0,IF(AND(D30>0,D30<>""),0,""),D30+$K30+$I30-$C$7),IF((D30-$J30)+$K30+$I30<=0,IF(AND(D30>0,D30<>""),0,""),(D30-$J30)+$K30+$I30))) -> 36 | E31: =IF(OR(E30="",E30=0),"",IF(ISBLANK($J30),IF(E30+$K30+$I30-$C$8<=0,IF(AND(E30>0,E30<>""),0,""),E30+$K30+$I30-$C$8),IF((E30-$J30)+$K30+$I30<=0,IF(AND(E30>0,E30<>""),0,""),(E30-$J30)+$K30+$I30))) | F31: =IF(J30="","",IF(G30+F30+H30+I30-J30<0,0,G30+F30+H30+I30-J30))
B32: =B31+$C$9 -> 46188 | C32: =IF(OR(C31="",C31=0),"",IF(ISBLANK(J31),IF(C31+K31+I31-$C$6<=0,IF(AND(C31>0,C31<>""),0,""),C31+K31+I31-$C$6),IF((C31-J31)+K31+I31<=0,IF(AND(C31>0,C31<>""),0,""),(C31-J31)+K31+I31))) | D32: =IF(OR(D31="",D31=0),"",IF(ISBLANK($J31),IF(D31+$K31+$I31-$C$7<=0,IF(AND(D31>0,D31<>""),0,""),D31+$K31+$I31-$C$7),IF((D31-$J31)+$K31+$I31<=0,IF(AND(D31>0,D31<>""),0,""),(D31-$J31)+$K31+$I31))) -> 35 | E32: =IF(OR(E31="",E31=0),"",IF(ISBLANK($J31),IF(E31+$K31+$I31-$C$8<=0,IF(AND(E31>0,E31<>""),0,""),E31+$K31+$I31-$C$8),IF((E31-$J31)+$K31+$I31<=0,IF(AND(E31>0,E31<>""),0,""),(E31-$J31)+$K31+$I31))) | F32: =IF(J31="","",IF(G31+F31+H31+I31-J31<0,0,G31+F31+H31+I31-J31))
B33: =B32+$C$9 -> 46195 | C33: =IF(OR(C32="",C32=0),"",IF(ISBLANK(J32),IF(C32+K32+I32-$C$6<=0,IF(AND(C32>0,C32<>""),0,""),C32+K32+I32-$C$6),IF((C32-J32)+K32+I32<=0,IF(AND(C32>0,C32<>""),0,""),(C32-J32)+K32+I32))) | D33: =IF(OR(D32="",D32=0),"",IF(ISBLANK($J32),IF(D32+$K32+$I32-$C$7<=0,IF(AND(D32>0,D32<>""),0,""),D32+$K32+$I32-$C$7),IF((D32-$J32)+$K32+$I32<=0,IF(AND(D32>0,D32<>""),0,""),(D32-$J32)+$K32+$I32))) -> 34 | E33: =IF(OR(E32="",E32=0),"",IF(ISBLANK($J32),IF(E32+$K32+$I32-$C$8<=0,IF(AND(E32>0,E32<>""),0,""),E32+$K32+$I32-$C$8),IF((E32-$J32)+$K32+$I32<=0,IF(AND(E32>0,E32<>""),0,""),(E32-$J32)+$K32+$I32))) | F33: =IF(J32="","",IF(G32+F32+H32+I32-J32<0,0,G32+F32+H32+I32-J32))
B34: =B33+$C$9 -> 46202 | C34: =IF(OR(C33="",C33=0),"",IF(ISBLANK(J33),IF(C33+K33+I33-$C$6<=0,IF(AND(C33>0,C33<>""),0,""),C33+K33+I33-$C$6),IF((C33-J33)+K33+I33<=0,IF(AND(C33>0,C33<>""),0,""),(C33-J33)+K33+I33))) | D34: =IF(OR(D33="",D33=0),"",IF(ISBLANK($J33),IF(D33+$K33+$I33-$C$7<=0,IF(AND(D33>0,D33<>""),0,""),D33+$K33+$I33-$C$7),IF((D33-$J33)+$K33+$I33<=0,IF(AND(D33>0,D33<>""),0,""),(D33-$J33)+$K33+$I33))) -> 33 | E34: =IF(OR(E33="",E33=0),"",IF(ISBLANK($J33),IF(E33+$K33+$I33-$C$8<=0,IF(AND(E33>0,E33<>""),0,""),E33+$K33+$I33-$C$8),IF((E33-$J33)+$K33+$I33<=0,IF(AND(E33>0,E33<>""),0,""),(E33-$J33)+$K33+$I33))) | F34: =IF(J33="","",IF(G33+F33+H33+I33-J33<0,0,G33+F33+H33+I33-J33))
B35: =B34+$C$9 -> 46209 | C35: =IF(OR(C34="",C34=0),"",IF(ISBLANK(J34),IF(C34+K34+I34-$C$6<=0,IF(AND(C34>0,C34<>""),0,""),C34+K34+I34-$C$6),IF((C34-J34)+K34+I34<=0,IF(AND(C34>0,C34<>""),0,""),(C34-J34)+K34+I34))) | D35: =IF(OR(D34="",D34=0),"",IF(ISBLANK($J34),IF(D34+$K34+$I34-$C$7<=0,IF(AND(D34>0,D34<>""),0,""),D34+$K34+$I34-$C$7),IF((D34-$J34)+$K34+$I34<=0,IF(AND(D34>0,D34<>""),0,""),(D34-$J34)+$K34+$I34))) -> 32 | E35: =IF(OR(E34="",E34=0),"",IF(ISBLANK($J34),IF(E34+$K34+$I34-$C$8<=0,IF(AND(E34>0,E34<>""),0,""),E34+$K34+$I34-$C$8),IF((E34-$J34)+$K34+$I34<=0,IF(AND(E34>0,E34<>""),0,""),(E34-$J34)+$K34+$I34))) | F35: =IF(J34="","",IF(G34+F34+H34+I34-J34<0,0,G34+F34+H34+I34-J34))
B36: =B35+$C$9 -> 46216 | C36: =IF(OR(C35="",C35=0),"",IF(ISBLANK(J35),IF(C35+K35+I35-$C$6<=0,IF(AND(C35>0,C35<>""),0,""),C35+K35+I35-$C$6),IF((C35-J35)+K35+I35<=0,IF(AND(C35>0,C35<>""),0,""),(C35-J35)+K35+I35))) | D36: =IF(OR(D35="",D35=0),"",IF(ISBLANK($J35),IF(D35+$K35+$I35-$C$7<=0,IF(AND(D35>0,D35<>""),0,""),D35+$K35+$I35-$C$7),IF((D35-$J35)+$K35+$I35<=0,IF(AND(D35>0,D35<>""),0,""),(D35-$J35)+$K35+$I35))) -> 31 | E36: =IF(OR(E35="",E35=0),"",IF(ISBLANK($J35),IF(E35+$K35+$I35-$C$8<=0,IF(AND(E35>0,E35<>""),0,""),E35+$K35+$I35-$C$8),IF((E35-$J35)+$K35+$I35<=0,IF(AND(E35>0,E35<>""),0,""),(E35-$J35)+$K35+$I35))) | F36: =IF(J35="","",IF(G35+F35+H35+I35-J35<0,0,G35+F35+H35+I35-J35))
B37: =B36+$C$9 -> 46223 | C37: =IF(OR(C36="",C36=0),"",IF(ISBLANK(J36),IF(C36+K36+I36-$C$6<=0,IF(AND(C36>0,C36<>""),0,""),C36+K36+I36-$C$6),IF((C36-J36)+K36+I36<=0,IF(AND(C36>0,C36<>""),0,""),(C36-J36)+K36+I36))) | D37: =IF(OR(D36="",D36=0),"",IF(ISBLANK($J36),IF(D36+$K36+$I36-$C$7<=0,IF(AND(D36>0,D36<>""),0,""),D36+$K36+$I36-$C$7),IF((D36-$J36)+$K36+$I36<=0,IF(AND(D36>0,D36<>""),0,""),(D36-$J36)+$K36+$I36))) -> 30 | E37: =IF(OR(E36="",E36=0),"",IF(ISBLANK($J36),IF(E36+$K36+$I36-$C$8<=0,IF(AND(E36>0,E36<>""),0,""),E36+$K36+$I36-$C$8),IF((E36-$J36)+$K36+$I36<=0,IF(AND(E36>0,E36<>""),0,""),(E36-$J36)+$K36+$I36))) | F37: =IF(J36="","",IF(G36+F36+H36+I36-J36<0,0,G36+F36+H36+I36-J36))
B38: =B37+$C$9 -> 46230 | C38: =IF(OR(C37="",C37=0),"",IF(ISBLANK(J37),IF(C37+K37+I37-$C$6<=0,IF(AND(C37>0,C37<>""),0,""),C37+K37+I37-$C$6),IF((C37-J37)+K37+I37<=0,IF(AND(C37>0,C37<>""),0,""),(C37-J37)+K37+I37))) | D38: =IF(OR(D37="",D37=0),"",IF(ISBLANK($J37),IF(D37+$K37+$I37-$C$7<=0,IF(AND(D37>0,D37<>""),0,""),D37+$K37+$I37-$C$7),IF((D37-$J37)+$K37+$I37<=0,IF(AND(D37>0,D37<>""),0,""),(D37-$J37)+$K37+$I37))) -> 29 | E38: =IF(OR(E37="",E37=0),"",IF(ISBLANK($J37),IF(E37+$K37+$I37-$C$8<=0,IF(AND(E37>0,E37<>""),0,""),E37+$K37+$I37-$C$8),IF((E37-$J37)+$K37+$I37<=0,IF(AND(E37>0,E37<>""),0,""),(E37-$J37)+$K37+$I37))) | F38: =IF(J37="","",IF(G37+F37+H37+I37-J37<0,0,G37+F37+H37+I37-J37))
B39: =B38+$C$9 -> 46237 | C39: =IF(OR(C38="",C38=0),"",IF(ISBLANK(J38),IF(C38+K38+I38-$C$6<=0,IF(AND(C38>0,C38<>""),0,""),C38+K38+I38-$C$6),IF((C38-J38)+K38+I38<=0,IF(AND(C38>0,C38<>""),0,""),(C38-J38)+K38+I38))) | D39: =IF(OR(D38="",D38=0),"",IF(ISBLANK($J38),IF(D38+$K38+$I38-$C$7<=0,IF(AND(D38>0,D38<>""),0,""),D38+$K38+$I38-$C$7),IF((D38-$J38)+$K38+$I38<=0,IF(AND(D38>0,D38<>""),0,""),(D38-$J38)+$K38+$I38))) -> 28 | E39: =IF(OR(E38="",E38=0),"",IF(ISBLANK($J38),IF(E38+$K38+$I38-$C$8<=0,IF(AND(E38>0,E38<>""),0,""),E38+$K38+$I38-$C$8),IF((E38-$J38)+$K38+$I38<=0,IF(AND(E38>0,E38<>""),0,""),(E38-$J38)+$K38+$I38))) | F39: =IF(J38="","",IF(G38+F38+H38+I38-J38<0,0,G38+F38+H38+I38-J38))
B40: =B39+$C$9 -> 46244 | C40: =IF(OR(C39="",C39=0),"",IF(ISBLANK(J39),IF(C39+K39+I39-$C$6<=0,IF(AND(C39>0,C39<>""),0,""),C39+K39+I39-$C$6),IF((C39-J39)+K39+I39<=0,IF(AND(C39>0,C39<>""),0,""),(C39-J39)+K39+I39))) | D40: =IF(OR(D39="",D39=0),"",IF(ISBLANK($J39),IF(D39+$K39+$I39-$C$7<=0,IF(AND(D39>0,D39<>""),0,""),D39+$K39+$I39-$C$7),IF((D39-$J39)+$K39+$I39<=0,IF(AND(D39>0,D39<>""),0,""),(D39-$J39)+$K39+$I39))) -> 27 | E40: =IF(OR(E39="",E39=0),"",IF(ISBLANK($J39),IF(E39+$K39+$I39-$C$8<=0,IF(AND(E39>0,E39<>""),0,""),E39+$K39+$I39-$C$8),IF((E39-$J39)+$K39+$I39<=0,IF(AND(E39>0,E39<>""),0,""),(E39-$J39)+$K39+$I39))) | F40: =IF(J39="","",IF(G39+F39+H39+I39-J39<0,0,G39+F39+H39+I39-J39))
B41: =B40+$C$9 -> 46251 | C41: =IF(OR(C40="",C40=0),"",IF(ISBLANK(J40),IF(C40+K40+I40-$C$6<=0,IF(AND(C40>0,C40<>""),0,""),C40+K40+I40-$C$6),IF((C40-J40)+K40+I40<=0,IF(AND(C40>0,C40<>""),0,""),(C40-J40)+K40+I40))) | D41: =IF(OR(D40="",D40=0),"",IF(ISBLANK($J40),IF(D40+$K40+$I40-$C$7<=0,IF(AND(D40>0,D40<>""),0,""),D40+$K40+$I40-$C$7),IF((D40-$J40)+$K40+$I40<=0,IF(AND(D40>0,D40<>""),0,""),(D40-$J40)+$K40+$I40))) -> 26 | E41: =IF(OR(E40="",E40=0),"",IF(ISBLANK($J40),IF(E40+$K40+$I40-$C$8<=0,IF(AND(E40>0,E40<>""),0,""),E40+$K40+$I40-$C$8),IF((E40-$J40)+$K40+$I40<=0,IF(AND(E40>0,E40<>""),0,""),(E40-$J40)+$K40+$I40))) | F41: =IF(J40="","",IF(G40+F40+H40+I40-J40<0,0,G40+F40+H40+I40-J40))
B42: =B41+$C$9 -> 46258 | C42: =IF(OR(C41="",C41=0),"",IF(ISBLANK(J41),IF(C41+K41+I41-$C$6<=0,IF(AND(C41>0,C41<>""),0,""),C41+K41+I41-$C$6),IF((C41-J41)+K41+I41<=0,IF(AND(C41>0,C41<>""),0,""),(C41-J41)+K41+I41))) | D42: =IF(OR(D41="",D41=0),"",IF(ISBLANK($J41),IF(D41+$K41+$I41-$C$7<=0,IF(AND(D41>0,D41<>""),0,""),D41+$K41+$I41-$C$7),IF((D41-$J41)+$K41+$I41<=0,IF(AND(D41>0,D41<>""),0,""),(D41-$J41)+$K41+$I41))) -> 25 | E42: =IF(OR(E41="",E41=0),"",IF(ISBLANK($J41),IF(E41+$K41+$I41-$C$8<=0,IF(AND(E41>0,E41<>""),0,""),E41+$K41+$I41-$C$8),IF((E41-$J41)+$K41+$I41<=0,IF(AND(E41>0,E41<>""),0,""),(E41-$J41)+$K41+$I41))) | F42: =IF(J41="","",IF(G41+F41+H41+I41-J41<0,0,G41+F41+H41+I41-J41))
... B54: =B53+$C$9 -> 46342 | C54: =IF(OR(C53="",C53=0),"",IF(ISBLANK(J53),IF(C53+K53+I53-$C$6<=0,IF(AND(C53>0,C53<>""),0,""),C53+K53+I53-$C$6),IF((C53-J53)+K53+I53<=0,IF(AND(C53>0,C53<>""),0,""),(C53-J53)+K53+I53))) | D54: =IF(OR(D53="",D53=0),"",IF(ISBLANK($J53),IF(D53+$K53+$I53-$C$7<=0,IF(AND(D53>0,D53<>""),0,""),D53+$K53+$I53-$C$7),IF((D53-$J53)+$K53+$I53<=0,IF(AND(D53>0,D53<>""),0,""),(D53-$J53)+$K53+$I53))) -> 13 | E54: =IF(OR(E53="",E53=0),"",IF(ISBLANK($J53),IF(E53+$K53+$I53-$C$8<=0,IF(AND(E53>0,E53<>""),0,""),E53+$K53+$I53-$C$8),IF((E53-$J53)+$K53+$I53<=0,IF(AND(E53>0,E53<>""),0,""),(E53-$J53)+$K53+$I53))) | F54: =IF(J53="","",IF(G53+F53+H53+I53-J53<0,0,G53+F53+H53+I53-J53))
B92: =IF(#REF!="","",IF(#REF!+$C$9<=$C$5,#REF!+$C$9,"")) -> #REF! | C92: =IF(B92<>"",#REF!-$C$2/COUNT($B$17:$B$510),"") -> #REF!
B93: =IF(B92="","",IF(B92+$C$9<=$C$5,B92+$C$9,"")) -> #REF! | C93: =IF(B93<>"",C92-$C$2/COUNT($B$17:$B$510),"") -> #REF!
B94: =IF(B93="","",IF(B93+$C$9<=$C$5,B93+$C$9,"")) -> #REF! | C94: =IF(B94<>"",C93-$C$2/COUNT($B$17:$B$510),"") -> #REF!
B95: =IF(B94="","",IF(B94+$C$9<=$C$5,B94+$C$9,"")) -> #REF! | C95: =IF(B95<>"",C94-$C$2/COUNT($B$17:$B$510),"") -> #REF!
B96: =IF(B95="","",IF(B95+$C$9<=$C$5,B95+$C$9,"")) -> #REF! | C96: =IF(B96<>"",C95-$C$2/COUNT($B$17:$B$510),"") -> #REF!
B97: =IF(B96="","",IF(B96+$C$9<=$C$5,B96+$C$9,"")) -> #REF! | C97: =IF(B97<>"",C96-$C$2/COUNT($B$17:$B$510),"") -> #REF!
B98: =IF(B97="","",IF(B97+$C$9<=$C$5,B97+$C$9,"")) -> #REF! | C98: =IF(B98<>"",C97-$C$2/COUNT($B$17:$B$510),"") -> #REF!
B99: =IF(B98="","",IF(B98+$C$9<=$C$5,B98+$C$9,"")) -> #REF! | C99: =IF(B99<>"",C98-$C$2/COUNT($B$17:$B$510),"") -> #REF!
B100: =IF(B99="","",IF(B99+$C$9<=$C$5,B99+$C$9,"")) -> #REF! | C100: =IF(B100<>"",C99-$C$2/COUNT($B$17:$B$510),"") -> #REF!
B101: =IF(B100="","",IF(B100+$C$9<=$C$5,B100+$C$9,"")) -> #REF! | C101: =IF(B101<>"",C100-$C$2/COUNT($B$17:$B$510),"") -> #REF!
B102: =IF(B101="","",IF(B101+$C$9<=$C$5,B101+$C$9,"")) -> #REF! | C102: =IF(B102<>"",C101-$C$2/COUNT($B$17:$B$510),"") -> #REF!
B103: =IF(B102="","",IF(B102+$C$9<=$C$5,B102+$C$9,"")) -> #REF! | C103: =IF(B103<>"",C102-$C$2/COUNT($B$17:$B$510),"") -> #REF!
B104: =IF(B103="","",IF(B103+$C$9<=$C$5,B103+$C$9,"")) -> #REF! | C104: =IF(B104<>"",C103-$C$2/COUNT($B$17:$B$510),"") -> #REF!
... B511: =IF(B510="","",IF(B510+$C$9<=$C$5,B510+$C$9,"")) -> #REF! | C511: =IF(B511<>"",C510-$C$2/COUNT($B$17:$B$510),"") -> #REF!

Sheet GOL (R1.5)
A1: Cone: baseado na nossa vazão, chegaremos na data alvo? O que cabe até data alvo?
B2: Quantidade de Épicos | C2: 48 | D2: Épicos | E2: considerar apenas os épicos que estão no mapa de release
B3: Qtd de Story / Task / Bug / Spike | C3: 63 | D3: Story / Tarefa / Bug / Spike | E3: considerar o trabalho de todos os integrantes do time, inclsuive tasks de dívidas técnicas e automação
B4: Data início | C4: 45943 | D4: Primeria sprint da release
B5: Data fim esperada | C5: 46014 | D5: Data entregada release
B6: Melhor cenário | C6: 2 | D6: itens por semana | E6: considerar sempre as ultimas 4 sprints para atualizar os números
B7: Pior cenário | C7: 1 | D7: itens por semana | E7: considerar sempre as ultimas 4 sprints para atualizar os números
B8: Velocidade necessária | C8: 6 | D8: itens por semana
B9: Acompanhar a cada | C9: 7 | D9: dias
B11: Data do Início da Semana | C11: Se seguirmos nossa melhor vazão, quando entregamos? | D11: Se seguirmos nossa pior vazão, quando entregamos? | E11: Vazão ideal para atender à data | F11: Itens da sprint anterior que não foram concluídos | G11: Itens que entram em sprint pela primeira vez | H11: Itens que entraram na Sprint depois do planejamento, mas não são "Fura fila" | I11: Itens Fura-Fila que apareceram ao longo da Sprint | J11: Itens entregues na Sprint | K11: Itens que chegaram no backlog do time ao longo da semana, mas não na sprint | L11: Observações adicionais
B12: Não editar esses campos | G12: Preencher com os dados de cada semana
A13: Sprint | B13: Semana | C13: A fazer (melhor cenário) | D13: A fazer (pior cenário) | E13: A fazer (valocidade necessária) | F13: Itens Transbordo | G13: Itens Planejados (Planning) | H13: Itens não planejados na sprint | I13: (+) Expedite | J13: Realizado | K13: (+)(-) Escopo pro time | L13: OBSERVAÇÕES
B14: =C4 -> 45943 | C14: =$C$3 -> 63 | D14: =$C$3 -> 63 | E14: =$C$3 -> 63 | J14: 0 | L14: Refinamentos
A15: Sprint 1 | B15: =B14+$C$9 -> 45950 | C15: =IF(OR(C14="",C14=0),"",IF(ISBLANK($J14),IF(C14+$K14+$I14-$C$6<=0,IF(AND(C14>0,C14<>""),0,""),C14+$K14+$I14-$C$6),IF((C14-$J14)+$K14+$I14<=0,IF(AND(C14>0,C14<>""),0,""),(C14-$J14)+$K14+$I14))) -> 63 | D15: =IF(OR(D14="",D14=0),"",IF(ISBLANK($J14),IF(D14+$K14+$I14-$C$7<=0,IF(AND(D14>0,D14<>""),0,""),D14+$K14+$I14-$C$7),IF((D14-$J14)+$K14+$I14<=0,IF(AND(D14>0,D14<>""),0,""),(D14-$J14)+$K14+$I14))) -> 63 | E15: =IF(OR(E14="",E14=0),"",IF(ISBLANK($J14),IF(E14+$K14+$I14-$C$8<=0,IF(AND(E14>0,E14<>""),0,""),E14+$K14+$I14-$C$8),IF((E14-$J14)+$K14+$I14<=0,IF(AND(E14>0,E14<>""),0,""),(E14-$J14)+$K14+$I14))) -> 63 | F15: =IF(J14="","",IF(G14+F14+H14+I14-J14<0,0,G14+F14+H14+I14-J14)) -> 0 | G15: 5 | H15: 2 | I15: 1 | J15: 2
A16: Sprint 2 | B16: =B15+$C$9 -> 45957 | C16: =IF(OR(C15="",C15=0),"",IF(ISBLANK(J15),IF(C15+K15+I15-$C$6<=0,IF(AND(C15>0,C15<>""),0,""),C15+K15+I15-$C$6),IF((C15-J15)+K15+I15<=0,IF(AND(C15>0,C15<>""),0,""),(C15-J15)+K15+I15))) -> 62 | D16: =IF(OR(D15="",D15=0),"",IF(ISBLANK($J15),IF(D15+$K15+$I15-$C$7<=0,IF(AND(D15>0,D15<>""),0,""),D15+$K15+$I15-$C$7),IF((D15-$J15)+$K15+$I15<=0,IF(AND(D15>0,D15<>""),0,""),(D15-$J15)+$K15+$I15))) -> 62 | E16: =IF(OR(E15="",E15=0),"",IF(ISBLANK($J15),IF(E15+$K15+$I15-$C$8<=0,IF(AND(E15>0,E15<>""),0,""),E15+$K15+$I15-$C$8),IF((E15-$J15)+$K15+$I15<=0,IF(AND(E15>0,E15<>""),0,""),(E15-$J15)+$K15+$I15))) -> 62 | F16: =IF(J15="","",IF(G15+F15+H15+I15-J15<0,0,G15+F15+H15+I15-J15)) -> 6 | G16: 2 | H16: 2 | J16: 0 | L16: Liberação de ambiente QA
A17: Sprint 3 | B17: =B16+$C$9 -> 45964 | C17: =IF(OR(C16="",C16=0),"",IF(ISBLANK(J16),IF(C16+K16+I16-$C$6<=0,IF(AND(C16>0,C16<>""),0,""),C16+K16+I16-$C$6),IF((C16-J16)+K16+I16<=0,IF(AND(C16>0,C16<>""),0,""),(C16-J16)+K16+I16))) -> 62 | D17: =IF(OR(D16="",D16=0),"",IF(ISBLANK($J16),IF(D16+$K16+$I16-$C$7<=0,IF(AND(D16>0,D16<>""),0,""),D16+$K16+$I16-$C$7),IF((D16-$J16)+$K16+$I16<=0,IF(AND(D16>0,D16<>""),0,""),(D16-$J16)+$K16+$I16))) -> 62 | E17: =IF(OR(E16="",E16=0),"",IF(ISBLANK($J16),IF(E16+$K16+$I16-$C$8<=0,IF(AND(E16>0,E16<>""),0,""),E16+$K16+$I16-$C$8),IF((E16-$J16)+$K16+$I16<=0,IF(AND(E16>0,E16<>""),0,""),(E16-$J16)+$K16+$I16))) -> 62 | F17: =IF(J16="","",IF(G16+F16+H16+I16-J16<0,0,G16+F16+H16+I16-J16)) -> 10 | G17: 2 | H17: 2 | J17: 0 | L17: Liberação de ambiente QA evento WS
A18: Sprint 4 | B18: =B17+$C$9 -> 45971 | C18: =IF(OR(C17="",C17=0),"",IF(ISBLANK(J17),IF(C17+K17+I17-$C$6<=0,IF(AND(C17>0,C17<>""),0,""),C17+K17+I17-$C$6),IF((C17-J17)+K17+I17<=0,IF(AND(C17>0,C17<>""),0,""),(C17-J17)+K17+I17))) -> 62 | D18: =IF(OR(D17="",D17=0),"",IF(ISBLANK($J17),IF(D17+$K17+$I17-$C$7<=0,IF(AND(D17>0,D17<>""),0,""),D17+$K17+$I17-$C$7),IF((D17-$J17)+$K17+$I17<=0,IF(AND(D17>0,D17<>""),0,""),(D17-$J17)+$K17+$I17))) -> 62 | E18: =IF(OR(E17="",E17=0),"",IF(ISBLANK($J17),IF(E17+$K17+$I17-$C$8<=0,IF(AND(E17>0,E17<>""),0,""),E17+$K17+$I17-$C$8),IF((E17-$J17)+$K17+$I17<=0,IF(AND(E17>0,E17<>""),0,""),(E17-$J17)+$K17+$I17))) -> 62 | F18: 12 | I18: 2 | J18: 8 | L18: Liberação do S3 (bastante entregas que estavam represadas)
A19: Sprint 5 | B19: =B18+$C$9 -> 45978 | C19: =IF(OR(C18="",C18=0),"",IF(ISBLANK(J18),IF(C18+K18+I18-$C$6<=0,IF(AND(C18>0,C18<>""),0,""),C18+K18+I18-$C$6),IF((C18-J18)+K18+I18<=0,IF(AND(C18>0,C18<>""),0,""),(C18-J18)+K18+I18))) -> 56 | D19: =IF(OR(D18="",D18=0),"",IF(ISBLANK($J18),IF(D18+$K18+$I18-$C$7<=0,IF(AND(D18>0,D18<>""),0,""),D18+$K18+$I18-$C$7),IF((D18-$J18)+$K18+$I18<=0,IF(AND(D18>0,D18<>""),0,""),(D18-$J18)+$K18+$I18))) -> 56 | E19: =IF(OR(E18="",E18=0),"",IF(ISBLANK($J18),IF(E18+$K18+$I18-$C$8<=0,IF(AND(E18>0,E18<>""),0,""),E18+$K18+$I18-$C$8),IF((E18-$J18)+$K18+$I18<=0,IF(AND(E18>0,E18<>""),0,""),(E18-$J18)+$K18+$I18))) -> 56 | F19: =IF(J18="","",IF(G18+F18+H18+I18-J18<0,0,G18+F18+H18+I18-J18)) -> 6 | G19: 2 | J19: 2 | K19: 29 | L19: 1 dia de feriado
A20: Sprint 6 | B20: =B19+$C$9 -> 45985 | C20: =IF(OR(C19="",C19=0),"",IF(ISBLANK(J19),IF(C19+K19+I19-$C$6<=0,IF(AND(C19>0,C19<>""),0,""),C19+K19+I19-$C$6),IF((C19-J19)+K19+I19<=0,IF(AND(C19>0,C19<>""),0,""),(C19-J19)+K19+I19))) -> 83 | D20: =IF(OR(D19="",D19=0),"",IF(ISBLANK($J19),IF(D19+$K19+$I19-$C$7<=0,IF(AND(D19>0,D19<>""),0,""),D19+$K19+$I19-$C$7),IF((D19-$J19)+$K19+$I19<=0,IF(AND(D19>0,D19<>""),0,""),(D19-$J19)+$K19+$I19))) -> 83 | E20: =IF(OR(E19="",E19=0),"",IF(ISBLANK($J19),IF(E19+$K19+$I19-$C$8<=0,IF(AND(E19>0,E19<>""),0,""),E19+$K19+$I19-$C$8),IF((E19-$J19)+$K19+$I19<=0,IF(AND(E19>0,E19<>""),0,""),(E19-$J19)+$K19+$I19))) -> 83 | F20: =IF(J19="","",IF(G19+F19+H19+I19-J19<0,0,G19+F19+H19+I19-J19)) -> 6 | G20: 0 | H20: -1 | J20: 3 | K20: -1 | L20: Finalizar as homologações e definições de escopo
A21: Sprint 7 | B21: =B20+$C$9 -> 45992 | C21: =IF(OR(C20="",C20=0),"",IF(ISBLANK(J20),IF(C20+K20+I20-$C$6<=0,IF(AND(C20>0,C20<>""),0,""),C20+K20+I20-$C$6),IF((C20-J20)+K20+I20<=0,IF(AND(C20>0,C20<>""),0,""),(C20-J20)+K20+I20))) -> 79 | D21: =IF(OR(D20="",D20=0),"",IF(ISBLANK($J20),IF(D20+$K20+$I20-$C$7<=0,IF(AND(D20>0,D20<>""),0,""),D20+$K20+$I20-$C$7),IF((D20-$J20)+$K20+$I20<=0,IF(AND(D20>0,D20<>""),0,""),(D20-$J20)+$K20+$I20))) -> 79 | E21: =IF(OR(E20="",E20=0),"",IF(ISBLANK($J20),IF(E20+$K20+$I20-$C$8<=0,IF(AND(E20>0,E20<>""),0,""),E20+$K20+$I20-$C$8),IF((E20-$J20)+$K20+$I20<=0,IF(AND(E20>0,E20<>""),0,""),(E20-$J20)+$K20+$I20))) -> 79 | F21: =IF(J20="","",IF(G20+F20+H20+I20-J20<0,0,G20+F20+H20+I20-J20)) -> 2 | G21: 2 | H21: 3 | J21: 2
A22: Sprint 8 | B22: =B21+$C$9 -> 45999 | C22: =IF(OR(C21="",C21=0),"",IF(ISBLANK(J21),IF(C21+K21+I21-$C$6<=0,IF(AND(C21>0,C21<>""),0,""),C21+K21+I21-$C$6),IF((C21-J21)+K21+I21<=0,IF(AND(C21>0,C21<>""),0,""),(C21-J21)+K21+I21))) -> 77 | D22: =IF(OR(D21="",D21=0),"",IF(ISBLANK($J21),IF(D21+$K21+$I21-$C$7<=0,IF(AND(D21>0,D21<>""),0,""),D21+$K21+$I21-$C$7),IF((D21-$J21)+$K21+$I21<=0,IF(AND(D21>0,D21<>""),0,""),(D21-$J21)+$K21+$I21))) -> 77 | E22: =IF(OR(E21="",E21=0),"",IF(ISBLANK($J21),IF(E21+$K21+$I21-$C$8<=0,IF(AND(E21>0,E21<>""),0,""),E21+$K21+$I21-$C$8),IF((E21-$J21)+$K21+$I21<=0,IF(AND(E21>0,E21<>""),0,""),(E21-$J21)+$K21+$I21))) -> 77 | F22: =IF(J21="","",IF(G21+F21+H21+I21-J21<0,0,G21+F21+H21+I21-J21)) -> 5 | J22: 3 | L22: Bug encontrado em ambiente DEV, dependendo do TAOS para resolver
A23: Sprint 9 | B23: =B22+$C$9 -> 46006 | C23: =IF(OR(C22="",C22=0),"",IF(ISBLANK(J22),IF(C22+K22+I22-$C$6<=0,IF(AND(C22>0,C22<>""),0,""),C22+K22+I22-$C$6),IF((C22-J22)+K22+I22<=0,IF(AND(C22>0,C22<>""),0,""),(C22-J22)+K22+I22))) -> 74 | D23: =IF(OR(D22="",D22=0),"",IF(ISBLANK($J22),IF(D22+$K22+$I22-$C$7<=0,IF(AND(D22>0,D22<>""),0,""),D22+$K22+$I22-$C$7),IF((D22-$J22)+$K22+$I22<=0,IF(AND(D22>0,D22<>""),0,""),(D22-$J22)+$K22+$I22))) -> 74 | E23: =IF(OR(E22="",E22=0),"",IF(ISBLANK($J22),IF(E22+$K22+$I22-$C$8<=0,IF(AND(E22>0,E22<>""),0,""),E22+$K22+$I22-$C$8),IF((E22-$J22)+$K22+$I22<=0,IF(AND(E22>0,E22<>""),0,""),(E22-$J22)+$K22+$I22))) -> 74 | F23: =IF(J22="","",IF(G22+F22+H22+I22-J22<0,0,G22+F22+H22+I22-J22)) -> 2 | G23: 2 | H23: 1 | J23: 2 | L23: Ainda aguardando solução do BUG L!-952
A24: Sprint 10 | B24: =B23+$C$9 -> 46013 | C24: =IF(OR(C23="",C23=0),"",IF(ISBLANK(J23),IF(C23+K23+I23-$C$6<=0,IF(AND(C23>0,C23<>""),0,""),C23+K23+I23-$C$6),IF((C23-J23)+K23+I23<=0,IF(AND(C23>0,C23<>""),0,""),(C23-J23)+K23+I23))) -> 72 | D24: =IF(OR(D23="",D23=0),"",IF(ISBLANK($J23),IF(D23+$K23+$I23-$C$7<=0,IF(AND(D23>0,D23<>""),0,""),D23+$K23+$I23-$C$7),IF((D23-$J23)+$K23+$I23<=0,IF(AND(D23>0,D23<>""),0,""),(D23-$J23)+$K23+$I23))) -> 72 | E24: =IF(OR(E23="",E23=0),"",IF(ISBLANK($J23),IF(E23+$K23+$I23-$C$8<=0,IF(AND(E23>0,E23<>""),0,""),E23+$K23+$I23-$C$8),IF((E23-$J23)+$K23+$I23<=0,IF(AND(E23>0,E23<>""),0,""),(E23-$J23)+$K23+$I23))) -> 72 | F24: =IF(J23="","",IF(G23+F23+H23+I23-J23<0,0,G23+F23+H23+I23-J23)) -> 3 | G24: 1 | J24: 1
A25: Sprint 11 | B25: =B24+$C$9 -> 46020 | C25: =IF(OR(C24="",C24=0),"",IF(ISBLANK(J24),IF(C24+K24+I24-$C$6<=0,IF(AND(C24>0,C24<>""),0,""),C24+K24+I24-$C$6),IF((C24-J24)+K24+I24<=0,IF(AND(C24>0,C24<>""),0,""),(C24-J24)+K24+I24))) -> 71 | D25: =IF(OR(D24="",D24=0),"",IF(ISBLANK($J24),IF(D24+$K24+$I24-$C$7<=0,IF(AND(D24>0,D24<>""),0,""),D24+$K24+$I24-$C$7),IF((D24-$J24)+$K24+$I24<=0,IF(AND(D24>0,D24<>""),0,""),(D24-$J24)+$K24+$I24))) -> 71 | E25: =IF(OR(E24="",E24=0),"",IF(ISBLANK($J24),IF(E24+$K24+$I24-$C$8<=0,IF(AND(E24>0,E24<>""),0,""),E24+$K24+$I24-$C$8),IF((E24-$J24)+$K24+$I24<=0,IF(AND(E24>0,E24<>""),0,""),(E24-$J24)+$K24+$I24))) -> 71 | F25: =IF(J24="","",IF(G24+F24+H24+I24-J24<0,0,G24+F24+H24+I24-J24)) -> 3 | G25: 1 | J25: 1 | K25: 1
A26: Sprint 12 | B26: =B25+$C$9 -> 46027 | C26: =IF(OR(C25="",C25=0),"",IF(ISBLANK(J25),IF(C25+K25+I25-$C$6<=0,IF(AND(C25>0,C25<>""),0,""),C25+K25+I25-$C$6),IF((C25-J25)+K25+I25<=0,IF(AND(C25>0,C25<>""),0,""),(C25-J25)+K25+I25))) -> 71 | D26: =IF(OR(D25="",D25=0),"",IF(ISBLANK($J25),IF(D25+$K25+$I25-$C$7<=0,IF(AND(D25>0,D25<>""),0,""),D25+$K25+$I25-$C$7),IF((D25-$J25)+$K25+$I25<=0,IF(AND(D25>0,D25<>""),0,""),(D25-$J25)+$K25+$I25))) -> 71 | E26: =IF(OR(E25="",E25=0),"",IF(ISBLANK($J25),IF(E25+$K25+$I25-$C$8<=0,IF(AND(E25>0,E25<>""),0,""),E25+$K25+$I25-$C$8),IF((E25-$J25)+$K25+$I25<=0,IF(AND(E25>0,E25<>""),0,""),(E25-$J25)+$K25+$I25))) -> 71 | F26: =IF(J25="","",IF(G25+F25+H25+I25-J25<0,0,G25+F25+H25+I25-J25)) -> 3 | H26: 1 | J26: 2
A27: Sprint 13 | B27: =B26+$C$9 -> 46034 | C27: =IF(OR(C26="",C26=0),"",IF(ISBLANK(J26),IF(C26+K26+I26-$C$6<=0,IF(AND(C26>0,C26<>""),0,""),C26+K26+I26-$C$6),IF((C26-J26)+K26+I26<=0,IF(AND(C26>0,C26<>""),0,""),(C26-J26)+K26+I26))) -> 69 | D27: =IF(OR(D26="",D26=0),"",IF(ISBLANK($J26),IF(D26+$K26+$I26-$C$7<=0,IF(AND(D26>0,D26<>""),0,""),D26+$K26+$I26-$C$7),IF((D26-$J26)+$K26+$I26<=0,IF(AND(D26>0,D26<>""),0,""),(D26-$J26)+$K26+$I26))) -> 69 | E27: =IF(OR(E26="",E26=0),"",IF(ISBLANK($J26),IF(E26+$K26+$I26-$C$8<=0,IF(AND(E26>0,E26<>""),0,""),E26+$K26+$I26-$C$8),IF((E26-$J26)+$K26+$I26<=0,IF(AND(E26>0,E26<>""),0,""),(E26-$J26)+$K26+$I26))) -> 69 | F27: =IF(J26="","",IF(G26+F26+H26+I26-J26<0,0,G26+F26+H26+I26-J26)) -> 2 | H27: 1
A28: Sprint 14 | B28: =B27+$C$9 -> 46041 | C28: =IF(OR(C27="",C27=0),"",IF(ISBLANK(J27),IF(C27+K27+I27-$C$6<=0,IF(AND(C27>0,C27<>""),0,""),C27+K27+I27-$C$6),IF((C27-J27)+K27+I27<=0,IF(AND(C27>0,C27<>""),0,""),(C27-J27)+K27+I27))) -> 67 | D28: =IF(OR(D27="",D27=0),"",IF(ISBLANK($J27),IF(D27+$K27+$I27-$C$7<=0,IF(AND(D27>0,D27<>""),0,""),D27+$K27+$I27-$C$7),IF((D27-$J27)+$K27+$I27<=0,IF(AND(D27>0,D27<>""),0,""),(D27-$J27)+$K27+$I27))) -> 68 | E28: =IF(OR(E27="",E27=0),"",IF(ISBLANK($J27),IF(E27+$K27+$I27-$C$8<=0,IF(AND(E27>0,E27<>""),0,""),E27+$K27+$I27-$C$8),IF((E27-$J27)+$K27+$I27<=0,IF(AND(E27>0,E27<>""),0,""),(E27-$J27)+$K27+$I27))) -> 63 | F28: =IF(J27="","",IF(G27+F27+H27+I27-J27<0,0,G27+F27+H27+I27-J27))
A29: Sprint 15 | B29: =B28+$C$9 -> 46048 | C29: =IF(OR(C28="",C28=0),"",IF(ISBLANK(J28),IF(C28+K28+I28-$C$6<=0,IF(AND(C28>0,C28<>""),0,""),C28+K28+I28-$C$6),IF((C28-J28)+K28+I28<=0,IF(AND(C28>0,C28<>""),0,""),(C28-J28)+K28+I28))) -> 65 | D29: =IF(OR(D28="",D28=0),"",IF(ISBLANK($J28),IF(D28+$K28+$I28-$C$7<=0,IF(AND(D28>0,D28<>""),0,""),D28+$K28+$I28-$C$7),IF((D28-$J28)+$K28+$I28<=0,IF(AND(D28>0,D28<>""),0,""),(D28-$J28)+$K28+$I28))) -> 67 | E29: =IF(OR(E28="",E28=0),"",IF(ISBLANK($J28),IF(E28+$K28+$I28-$C$8<=0,IF(AND(E28>0,E28<>""),0,""),E28+$K28+$I28-$C$8),IF((E28-$J28)+$K28+$I28<=0,IF(AND(E28>0,E28<>""),0,""),(E28-$J28)+$K28+$I28))) -> 57 | F29: =IF(J28="","",IF(G28+F28+H28+I28-J28<0,0,G28+F28+H28+I28-J28))
B30: =B29+$C$9 -> 46055 | C30: =IF(OR(C29="",C29=0),"",IF(ISBLANK(J29),IF(C29+K29+I29-$C$6<=0,IF(AND(C29>0,C29<>""),0,""),C29+K29+I29-$C$6),IF((C29-J29)+K29+I29<=0,IF(AND(C29>0,C29<>""),0,""),(C29-J29)+K29+I29))) -> 63 | D30: =IF(OR(D29="",D29=0),"",IF(ISBLANK($J29),IF(D29+$K29+$I29-$C$7<=0,IF(AND(D29>0,D29<>""),0,""),D29+$K29+$I29-$C$7),IF((D29-$J29)+$K29+$I29<=0,IF(AND(D29>0,D29<>""),0,""),(D29-$J29)+$K29+$I29))) -> 66 | E30: =IF(OR(E29="",E29=0),"",IF(ISBLANK($J29),IF(E29+$K29+$I29-$C$8<=0,IF(AND(E29>0,E29<>""),0,""),E29+$K29+$I29-$C$8),IF((E29-$J29)+$K29+$I29<=0,IF(AND(E29>0,E29<>""),0,""),(E29-$J29)+$K29+$I29))) -> 51 | F30: =IF(J29="","",IF(G29+F29+H29+I29-J29<0,0,G29+F29+H29+I29-J29))
B31: =B30+$C$9 -> 46062 | C31: =IF(OR(C30="",C30=0),"",IF(ISBLANK(J30),IF(C30+K30+I30-$C$6<=0,IF(AND(C30>0,C30<>""),0,""),C30+K30+I30-$C$6),IF((C30-J30)+K30+I30<=0,IF(AND(C30>0,C30<>""),0,""),(C30-J30)+K30+I30))) -> 61 | D31: =IF(OR(D30="",D30=0),"",IF(ISBLANK($J30),IF(D30+$K30+$I30-$C$7<=0,IF(AND(D30>0,D30<>""),0,""),D30+$K30+$I30-$C$7),IF((D30-$J30)+$K30+$I30<=0,IF(AND(D30>0,D30<>""),0,""),(D30-$J30)+$K30+$I30))) -> 65 | E31: =IF(OR(E30="",E30=0),"",IF(ISBLANK($J30),IF(E30+$K30+$I30-$C$8<=0,IF(AND(E30>0,E30<>""),0,""),E30+$K30+$I30-$C$8),IF((E30-$J30)+$K30+$I30<=0,IF(AND(E30>0,E30<>""),0,""),(E30-$J30)+$K30+$I30))) -> 45 | F31: =IF(J30="","",IF(G30+F30+H30+I30-J30<0,0,G30+F30+H30+I30-J30))
B32: =B31+$C$9 -> 46069 | C32: =IF(OR(C31="",C31=0),"",IF(ISBLANK(J31),IF(C31+K31+I31-$C$6<=0,IF(AND(C31>0,C31<>""),0,""),C31+K31+I31-$C$6),IF((C31-J31)+K31+I31<=0,IF(AND(C31>0,C31<>""),0,""),(C31-J31)+K31+I31))) -> 59 | D32: =IF(OR(D31="",D31=0),"",IF(ISBLANK($J31),IF(D31+$K31+$I31-$C$7<=0,IF(AND(D31>0,D31<>""),0,""),D31+$K31+$I31-$C$7),IF((D31-$J31)+$K31+$I31<=0,IF(AND(D31>0,D31<>""),0,""),(D31-$J31)+$K31+$I31))) -> 64 | E32: =IF(OR(E31="",E31=0),"",IF(ISBLANK($J31),IF(E31+$K31+$I31-$C$8<=0,IF(AND(E31>0,E31<>""),0,""),E31+$K31+$I31-$C$8),IF((E31-$J31)+$K31+$I31<=0,IF(AND(E31>0,E31<>""),0,""),(E31-$J31)+$K31+$I31))) -> 39 | F32: =IF(J31="","",IF(G31+F31+H31+I31-J31<0,0,G31+F31+H31+I31-J31))
B33: =B32+$C$9 -> 46076 | C33: =IF(OR(C32="",C32=0),"",IF(ISBLANK(J32),IF(C32+K32+I32-$C$6<=0,IF(AND(C32>0,C32<>""),0,""),C32+K32+I32-$C$6),IF((C32-J32)+K32+I32<=0,IF(AND(C32>0,C32<>""),0,""),(C32-J32)+K32+I32))) -> 57 | D33: =IF(OR(D32="",D32=0),"",IF(ISBLANK($J32),IF(D32+$K32+$I32-$C$7<=0,IF(AND(D32>0,D32<>""),0,""),D32+$K32+$I32-$C$7),IF((D32-$J32)+$K32+$I32<=0,IF(AND(D32>0,D32<>""),0,""),(D32-$J32)+$K32+$I32))) -> 63 | E33: =IF(OR(E32="",E32=0),"",IF(ISBLANK($J32),IF(E32+$K32+$I32-$C$8<=0,IF(AND(E32>0,E32<>""),0,""),E32+$K32+$I32-$C$8),IF((E32-$J32)+$K32+$I32<=0,IF(AND(E32>0,E32<>""),0,""),(E32-$J32)+$K32+$I32))) -> 33 | F33: =IF(J32="","",IF(G32+F32+H32+I32-J32<0,0,G32+F32+H32+I32-J32))
B34: =B33+$C$9 -> 46083 | C34: =IF(OR(C33="",C33=0),"",IF(ISBLANK(J33),IF(C33+K33+I33-$C$6<=0,IF(AND(C33>0,C33<>""),0,""),C33+K33+I33-$C$6),IF((C33-J33)+K33+I33<=0,IF(AND(C33>0,C33<>""),0,""),(C33-J33)+K33+I33))) -> 55 | D34: =IF(OR(D33="",D33=0),"",IF(ISBLANK($J33),IF(D33+$K33+$I33-$C$7<=0,IF(AND(D33>0,D33<>""),0,""),D33+$K33+$I33-$C$7),IF((D33-$J33)+$K33+$I33<=0,IF(AND(D33>0,D33<>""),0,""),(D33-$J33)+$K33+$I33))) -> 62 | E34: =IF(OR(E33="",E33=0),"",IF(ISBLANK($J33),IF(E33+$K33+$I33-$C$8<=0,IF(AND(E33>0,E33<>""),0,""),E33+$K33+$I33-$C$8),IF((E33-$J33)+$K33+$I33<=0,IF(AND(E33>0,E33<>""),0,""),(E33-$J33)+$K33+$I33))) -> 27 | F34: =IF(J33="","",IF(G33+F33+H33+I33-J33<0,0,G33+F33+H33+I33-J33))
B35: =B34+$C$9 -> 46090 | C35: =IF(OR(C34="",C34=0),"",IF(ISBLANK(J34),IF(C34+K34+I34-$C$6<=0,IF(AND(C34>0,C34<>""),0,""),C34+K34+I34-$C$6),IF((C34-J34)+K34+I34<=0,IF(AND(C34>0,C34<>""),0,""),(C34-J34)+K34+I34))) -> 53 | D35: =IF(OR(D34="",D34=0),"",IF(ISBLANK($J34),IF(D34+$K34+$I34-$C$7<=0,IF(AND(D34>0,D34<>""),0,""),D34+$K34+$I34-$C$7),IF((D34-$J34)+$K34+$I34<=0,IF(AND(D34>0,D34<>""),0,""),(D34-$J34)+$K34+$I34))) -> 61 | E35: =IF(OR(E34="",E34=0),"",IF(ISBLANK($J34),IF(E34+$K34+$I34-$C$8<=0,IF(AND(E34>0,E34<>""),0,""),E34+$K34+$I34-$C$8),IF((E34-$J34)+$K34+$I34<=0,IF(AND(E34>0,E34<>""),0,""),(E34-$J34)+$K34+$I34))) -> 21 | F35: =IF(J34="","",IF(G34+F34+H34+I34-J34<0,0,G34+F34+H34+I34-J34))
B36: =B35+$C$9 -> 46097 | C36: =IF(OR(C35="",C35=0),"",IF(ISBLANK(J35),IF(C35+K35+I35-$C$6<=0,IF(AND(C35>0,C35<>""),0,""),C35+K35+I35-$C$6),IF((C35-J35)+K35+I35<=0,IF(AND(C35>0,C35<>""),0,""),(C35-J35)+K35+I35))) -> 51 | D36: =IF(OR(D35="",D35=0),"",IF(ISBLANK($J35),IF(D35+$K35+$I35-$C$7<=0,IF(AND(D35>0,D35<>""),0,""),D35+$K35+$I35-$C$7),IF((D35-$J35)+$K35+$I35<=0,IF(AND(D35>0,D35<>""),0,""),(D35-$J35)+$K35+$I35))) -> 60 | E36: =IF(OR(E35="",E35=0),"",IF(ISBLANK($J35),IF(E35+$K35+$I35-$C$8<=0,IF(AND(E35>0,E35<>""),0,""),E35+$K35+$I35-$C$8),IF((E35-$J35)+$K35+$I35<=0,IF(AND(E35>0,E35<>""),0,""),(E35-$J35)+$K35+$I35))) -> 15 | F36: =IF(J35="","",IF(G35+F35+H35+I35-J35<0,0,G35+F35+H35+I35-J35))
B37: =B36+$C$9 -> 46104 | C37: =IF(OR(C36="",C36=0),"",IF(ISBLANK(J36),IF(C36+K36+I36-$C$6<=0,IF(AND(C36>0,C36<>""),0,""),C36+K36+I36-$C$6),IF((C36-J36)+K36+I36<=0,IF(AND(C36>0,C36<>""),0,""),(C36-J36)+K36+I36))) -> 49 | D37: =IF(OR(D36="",D36=0),"",IF(ISBLANK($J36),IF(D36+$K36+$I36-$C$7<=0,IF(AND(D36>0,D36<>""),0,""),D36+$K36+$I36-$C$7),IF((D36-$J36)+$K36+$I36<=0,IF(AND(D36>0,D36<>""),0,""),(D36-$J36)+$K36+$I36))) -> 59 | E37: =IF(OR(E36="",E36=0),"",IF(ISBLANK($J36),IF(E36+$K36+$I36-$C$8<=0,IF(AND(E36>0,E36<>""),0,""),E36+$K36+$I36-$C$8),IF((E36-$J36)+$K36+$I36<=0,IF(AND(E36>0,E36<>""),0,""),(E36-$J36)+$K36+$I36))) -> 9 | F37: =IF(J36="","",IF(G36+F36+H36+I36-J36<0,0,G36+F36+H36+I36-J36))
B38: =B37+$C$9 -> 46111 | C38: =IF(OR(C37="",C37=0),"",IF(ISBLANK(J37),IF(C37+K37+I37-$C$6<=0,IF(AND(C37>0,C37<>""),0,""),C37+K37+I37-$C$6),IF((C37-J37)+K37+I37<=0,IF(AND(C37>0,C37<>""),0,""),(C37-J37)+K37+I37))) -> 47 | D38: =IF(OR(D37="",D37=0),"",IF(ISBLANK($J37),IF(D37+$K37+$I37-$C$7<=0,IF(AND(D37>0,D37<>""),0,""),D37+$K37+$I37-$C$7),IF((D37-$J37)+$K37+$I37<=0,IF(AND(D37>0,D37<>""),0,""),(D37-$J37)+$K37+$I37))) -> 58 | E38: =IF(OR(E37="",E37=0),"",IF(ISBLANK($J37),IF(E37+$K37+$I37-$C$8<=0,IF(AND(E37>0,E37<>""),0,""),E37+$K37+$I37-$C$8),IF((E37-$J37)+$K37+$I37<=0,IF(AND(E37>0,E37<>""),0,""),(E37-$J37)+$K37+$I37))) -> 3 | F38: =IF(J37="","",IF(G37+F37+H37+I37-J37<0,0,G37+F37+H37+I37-J37))
B39: =B38+$C$9 -> 46118 | C39: =IF(OR(C38="",C38=0),"",IF(ISBLANK(J38),IF(C38+K38+I38-$C$6<=0,IF(AND(C38>0,C38<>""),0,""),C38+K38+I38-$C$6),IF((C38-J38)+K38+I38<=0,IF(AND(C38>0,C38<>""),0,""),(C38-J38)+K38+I38))) -> 45 | D39: =IF(OR(D38="",D38=0),"",IF(ISBLANK($J38),IF(D38+$K38+$I38-$C$7<=0,IF(AND(D38>0,D38<>""),0,""),D38+$K38+$I38-$C$7),IF((D38-$J38)+$K38+$I38<=0,IF(AND(D38>0,D38<>""),0,""),(D38-$J38)+$K38+$I38))) -> 57 | E39: =IF(OR(E38="",E38=0),"",IF(ISBLANK($J38),IF(E38+$K38+$I38-$C$8<=0,IF(AND(E38>0,E38<>""),0,""),E38+$K38+$I38-$C$8),IF((E38-$J38)+$K38+$I38<=0,IF(AND(E38>0,E38<>""),0,""),(E38-$J38)+$K38+$I38))) -> 0 | F39: =IF(J38="","",IF(G38+F38+H38+I38-J38<0,0,G38+F38+H38+I38-J38))
B40: =B39+$C$9 -> 46125 | C40: =IF(OR(C39="",C39=0),"",IF(ISBLANK(J39),IF(C39+K39+I39-$C$6<=0,IF(AND(C39>0,C39<>""),0,""),C39+K39+I39-$C$6),IF((C39-J39)+K39+I39<=0,IF(AND(C39>0,C39<>""),0,""),(C39-J39)+K39+I39))) -> 43 | D40: =IF(OR(D39="",D39=0),"",IF(ISBLANK($J39),IF(D39+$K39+$I39-$C$7<=0,IF(AND(D39>0,D39<>""),0,""),D39+$K39+$I39-$C$7),IF((D39-$J39)+$K39+$I39<=0,IF(AND(D39>0,D39<>""),0,""),(D39-$J39)+$K39+$I39))) -> 56 | E40: =IF(OR(E39="",E39=0),"",IF(ISBLANK($J39),IF(E39+$K39+$I39-$C$8<=0,IF(AND(E39>0,E39<>""),0,""),E39+$K39+$I39-$C$8),IF((E39-$J39)+$K39+$I39<=0,IF(AND(E39>0,E39<>""),0,""),(E39-$J39)+$K39+$I39))) | F40: =IF(J39="","",IF(G39+F39+H39+I39-J39<0,0,G39+F39+H39+I39-J39))
B41: =B40+$C$9 -> 46132 | C41: =IF(OR(C40="",C40=0),"",IF(ISBLANK(J40),IF(C40+K40+I40-$C$6<=0,IF(AND(C40>0,C40<>""),0,""),C40+K40+I40-$C$6),IF((C40-J40)+K40+I40<=0,IF(AND(C40>0,C40<>""),0,""),(C40-J40)+K40+I40))) -> 41 | D41: =IF(OR(D40="",D40=0),"",IF(ISBLANK($J40),IF(D40+$K40+$I40-$C$7<=0,IF(AND(D40>0,D40<>""),0,""),D40+$K40+$I40-$C$7),IF((D40-$J40)+$K40+$I40<=0,IF(AND(D40>0,D40<>""),0,""),(D40-$J40)+$K40+$I40))) -> 55 | E41: =IF(OR(E40="",E40=0),"",IF(ISBLANK($J40),IF(E40+$K40+$I40-$C$8<=0,IF(AND(E40>0,E40<>""),0,""),E40+$K40+$I40-$C$8),IF((E40-$J40)+$K40+$I40<=0,IF(AND(E40>0,E40<>""),0,""),(E40-$J40)+$K40+$I40))) | F41: =IF(J40="","",IF(G40+F40+H40+I40-J40<0,0,G40+F40+H40+I40-J40))
... B54: =B53+$C$9 -> 46223 | C54: =IF(OR(C53="",C53=0),"",IF(ISBLANK(J53),IF(C53+K53+I53-$C$6<=0,IF(AND(C53>0,C53<>""),0,""),C53+K53+I53-$C$6),IF((C53-J53)+K53+I53<=0,IF(AND(C53>0,C53<>""),0,""),(C53-J53)+K53+I53))) -> 15 | D54: =IF(OR(D53="",D53=0),"",IF(ISBLANK($J53),IF(D53+$K53+$I53-$C$7<=0,IF(AND(D53>0,D53<>""),0,""),D53+$K53+$I53-$C$7),IF((D53-$J53)+$K53+$I53<=0,IF(AND(D53>0,D53<>""),0,""),(D53-$J53)+$K53+$I53))) -> 42 | E54: =IF(OR(E53="",E53=0),"",IF(ISBLANK($J53),IF(E53+$K53+$I53-$C$8<=0,IF(AND(E53>0,E53<>""),0,""),E53+$K53+$I53-$C$8),IF((E53-$J53)+$K53+$I53<=0,IF(AND(E53>0,E53<>""),0,""),(E53-$J53)+$K53+$I53))) | F54: =IF(J53="","",IF(G53+F53+H53+I53-J53<0,0,G53+F53+H53+I53-J53))
B92: =IF(#REF!="","",IF(#REF!+$C$9<=$C$5,#REF!+$C$9,"")) -> #REF! | C92: =IF(B92<>"",#REF!-$C$2/COUNT($B$17:$B$510),"") -> #REF!
B93: =IF(B92="","",IF(B92+$C$9<=$C$5,B92+$C$9,"")) -> #REF! | C93: =IF(B93<>"",C92-$C$2/COUNT($B$17:$B$510),"") -> #REF!
B94: =IF(B93="","",IF(B93+$C$9<=$C$5,B93+$C$9,"")) -> #REF! | C94: =IF(B94<>"",C93-$C$2/COUNT($B$17:$B$510),"") -> #REF!
B95: =IF(B94="","",IF(B94+$C$9<=$C$5,B94+$C$9,"")) -> #REF! | C95: =IF(B95<>"",C94-$C$2/COUNT($B$17:$B$510),"") -> #REF!
B96: =IF(B95="","",IF(B95+$C$9<=$C$5,B95+$C$9,"")) -> #REF! | C96: =IF(B96<>"",C95-$C$2/COUNT($B$17:$B$510),"") -> #REF!
B97: =IF(B96="","",IF(B96+$C$9<=$C$5,B96+$C$9,"")) -> #REF! | C97: =IF(B97<>"",C96-$C$2/COUNT($B$17:$B$510),"") -> #REF!
B98: =IF(B97="","",IF(B97+$C$9<=$C$5,B97+$C$9,"")) -> #REF! | C98: =IF(B98<>"",C97-$C$2/COUNT($B$17:$B$510),"") -> #REF!
B99: =IF(B98="","",IF(B98+$C$9<=$C$5,B98+$C$9,"")) -> #REF! | C99: =IF(B99<>"",C98-$C$2/COUNT($B$17:$B$510),"") -> #REF!
B100: =IF(B99="","",IF(B99+$C$9<=$C$5,B99+$C$9,"")) -> #REF! | C100: =IF(B100<>"",C99-$C$2/COUNT($B$17:$B$510),"") -> #REF!
B101: =IF(B100="","",IF(B100+$C$9<=$C$5,B100+$C$9,"")) -> #REF! | C101: =IF(B101<>"",C100-$C$2/COUNT($B$17:$B$510),"") -> #REF!
B102: =IF(B101="","",IF(B101+$C$9<=$C$5,B101+$C$9,"")) -> #REF! | C102: =IF(B102<>"",C101-$C$2/COUNT($B$17:$B$510),"") -> #REF!
B103: =IF(B102="","",IF(B102+$C$9<=$C$5,B102+$C$9,"")) -> #REF! | C103: =IF(B103<>"",C102-$C$2/COUNT($B$17:$B$510),"") -> #REF!
B104: =IF(B103="","",IF(B103+$C$9<=$C$5,B103+$C$9,"")) -> #REF! | C104: =IF(B104<>"",C103-$C$2/COUNT($B$17:$B$510),"") -> #REF!
... B511: =IF(B510="","",IF(B510+$C$9<=$C$5,B510+$C$9,"")) -> #REF! | C511: =IF(B511<>"",C510-$C$2/COUNT($B$17:$B$510),"") -> #REF!

Sheet Tera
A1: Cone: baseado na nossa vazão, chegaremos na data alvo? O que cabe até data alvo?
B2: Quantidade de Épicos | C2: 1 | D2: Épicos | E2: considerar apenas os épicos que estão no mapa de release
B3: Qtd de Story / Task / Bug / Spike | C3: 3 | D3: Story / Tarefa / Bug / Spike | E3: considerar o trabalho de todos os integrantes do time, inclsuive tasks de dívidas técnicas e automação
B4: Data início | C4: 45971 | D4: Primeria sprint da release
B5: Data fim esperada | C5: 46014 | D5: Data entregada release
B6: Melhor cenário | C6: 1 | D6: itens por semana | E6: considerar sempre as ultimas 4 sprints para atualizar os números
B7: Pior cenário | C7: 1 | D7: itens por semana | E7: considerar sempre as ultimas 4 sprints para atualizar os números
B8: Velocidade necessária | C8: 30 | D8: itens por semana
B9: Acompanhar a cada | C9: 7 | D9: dias
B11: Data do Início da Semana | C11: Se seguirmos nossa melhor vazão, quando entregamos? | D11: Se seguirmos nossa pior vazão, quando entregamos? | E11: Vazão ideal para atender à data | F11: Itens da sprint anterior que não foram concluídos | G11: Itens que entram em sprint pela primeira vez | H11: Itens que entraram na Sprint depois do planejamento, mas não são "Fura fila" | I11: Itens Fura-Fila que apareceram ao longo da Sprint | J11: Itens entregues na Sprint | K11: Itens que chegaram no backlog do time ao longo da semana, mas não na sprint | L11: Observações adicionais
B12: Não editar esses campos | G12: Preencher com os dados de cada semana
A13: Sprint | B13: Semana | C13: A fazer (melhor cenário) | D13: A fazer (pior cenário) | E13: A fazer (valocidade necessária) | F13: Itens Transbordo | G13: Itens Planejados (Planning) | H13: Itens não planejados na sprint | I13: (+) Expedite | J13: Realizado | K13: (+)(-) Escopo pro time | L13: OBSERVAÇÕES
A14: MS-SPRINT Sprint 24 | B14: =$C$4 -> 45971 | C14: =$C$3 -> 3 | D14: =$C$3 -> 3 | E14: =$C$3 -> 3 | G14: 2 | H14: 0 | I14: 0 | J14: 0 | K14: 1 | L14: Adição de uma Spike para visibilidade
A15: MS-SPRINT Sprint 25 | B15: =B14+$C$9 -> 45978 | C15: =IF(OR(C14="",C14=0),"",IF(ISBLANK($J14),IF(C14+$K14+$I14-$C$6<=0,IF(AND(C14>0,C14<>""),0,""),C14+$K14+$I14-$C$6),IF((C14-$J14)+$K14+$I14<=0,IF(AND(C14>0,C14<>""),0,""),(C14-$J14)+$K14+$I14))) -> 4 | D15: =IF(OR(D14="",D14=0),"",IF(ISBLANK($J14),IF(D14+$K14+$I14-$C$7<=0,IF(AND(D14>0,D14<>""),0,""),D14+$K14+$I14-$C$7),IF((D14-$J14)+$K14+$I14<=0,IF(AND(D14>0,D14<>""),0,""),(D14-$J14)+$K14+$I14))) -> 4 | E15: =IF(OR(E14="",E14=0),"",IF(ISBLANK($J14),IF(E14+$K14+$I14-$C$8<=0,IF(AND(E14>0,E14<>""),0,""),E14+$K14+$I14-$C$8),IF((E14-$J14)+$K14+$I14<=0,IF(AND(E14>0,E14<>""),0,""),(E14-$J14)+$K14+$I14))) -> 4 | F15: =IF(J14="","",IF(G14+F14+H14+I14-J14<0,0,G14+F14+H14+I14-J14)) -> 2 | G15: 0 | H15: 0 | I15: 0 | J15: 0 | K15: 13 | L15: Estimativa de todo o escopo para R1
A16: MS-SPRINT Sprint 26 | B16: =B15+$C$9 -> 45985 | C16: =IF(OR(C15="",C15=0),"",IF(ISBLANK(J15),IF(C15+K15+I15-$C$6<=0,IF(AND(C15>0,C15<>""),0,""),C15+K15+I15-$C$6),IF((C15-J15)+K15+I15<=0,IF(AND(C15>0,C15<>""),0,""),(C15-J15)+K15+I15))) -> 17 | D16: =IF(OR(D15="",D15=0),"",IF(ISBLANK($J15),IF(D15+$K15+$I15-$C$7<=0,IF(AND(D15>0,D15<>""),0,""),D15+$K15+$I15-$C$7),IF((D15-$J15)+$K15+$I15<=0,IF(AND(D15>0,D15<>""),0,""),(D15-$J15)+$K15+$I15))) -> 17 | E16: =IF(OR(E15="",E15=0),"",IF(ISBLANK($J15),IF(E15+$K15+$I15-$C$8<=0,IF(AND(E15>0,E15<>""),0,""),E15+$K15+$I15-$C$8),IF((E15-$J15)+$K15+$I15<=0,IF(AND(E15>0,E15<>""),0,""),(E15-$J15)+$K15+$I15))) -> 17 | F16: =IF(J15="","",IF(G15+F15+H15+I15-J15<0,0,G15+F15+H15+I15-J15)) -> 2 | G16: 0 | H16: 1 | I16: 0 | J16: 0
A17: MS-SPRINT Sprint 27 | B17: =B16+$C$9 -> 45992 | C17: =IF(OR(C16="",C16=0),"",IF(ISBLANK(J16),IF(C16+K16+I16-$C$6<=0,IF(AND(C16>0,C16<>""),0,""),C16+K16+I16-$C$6),IF((C16-J16)+K16+I16<=0,IF(AND(C16>0,C16<>""),0,""),(C16-J16)+K16+I16))) -> 17 | D17: =IF(OR(D16="",D16=0),"",IF(ISBLANK($J16),IF(D16+$K16+$I16-$C$7<=0,IF(AND(D16>0,D16<>""),0,""),D16+$K16+$I16-$C$7),IF((D16-$J16)+$K16+$I16<=0,IF(AND(D16>0,D16<>""),0,""),(D16-$J16)+$K16+$I16))) -> 17 | E17: =IF(OR(E16="",E16=0),"",IF(ISBLANK($J16),IF(E16+$K16+$I16-$C$8<=0,IF(AND(E16>0,E16<>""),0,""),E16+$K16+$I16-$C$8),IF((E16-$J16)+$K16+$I16<=0,IF(AND(E16>0,E16<>""),0,""),(E16-$J16)+$K16+$I16))) -> 17 | F17: =IF(J16="","",IF(G16+F16+H16+I16-J16<0,0,G16+F16+H16+I16-J16)) -> 3
A18: MS-SPRINT Sprint 28 | B18: =B17+$C$9 -> 45999 | C18: =IF(OR(C17="",C17=0),"",IF(ISBLANK(J17),IF(C17+K17+I17-$C$6<=0,IF(AND(C17>0,C17<>""),0,""),C17+K17+I17-$C$6),IF((C17-J17)+K17+I17<=0,IF(AND(C17>0,C17<>""),0,""),(C17-J17)+K17+I17))) -> 16 | D18: =IF(OR(D17="",D17=0),"",IF(ISBLANK($J17),IF(D17+$K17+$I17-$C$7<=0,IF(AND(D17>0,D17<>""),0,""),D17+$K17+$I17-$C$7),IF((D17-$J17)+$K17+$I17<=0,IF(AND(D17>0,D17<>""),0,""),(D17-$J17)+$K17+$I17))) -> 16 | E18: =IF(OR(E17="",E17=0),"",IF(ISBLANK($J17),IF(E17+$K17+$I17-$C$8<=0,IF(AND(E17>0,E17<>""),0,""),E17+$K17+$I17-$C$8),IF((E17-$J17)+$K17+$I17<=0,IF(AND(E17>0,E17<>""),0,""),(E17-$J17)+$K17+$I17))) -> 0 | F18: =IF(J17="","",IF(G17+F17+H17+I17-J17<0,0,G17+F17+H17+I17-J17))
A19: MS-SPRINT Sprint 29 | B19: =B18+$C$9 -> 46006 | C19: =IF(OR(C18="",C18=0),"",IF(ISBLANK(J18),IF(C18+K18+I18-$C$6<=0,IF(AND(C18>0,C18<>""),0,""),C18+K18+I18-$C$6),IF((C18-J18)+K18+I18<=0,IF(AND(C18>0,C18<>""),0,""),(C18-J18)+K18+I18))) -> 15 | D19: =IF(OR(D18="",D18=0),"",IF(ISBLANK($J18),IF(D18+$K18+$I18-$C$7<=0,IF(AND(D18>0,D18<>""),0,""),D18+$K18+$I18-$C$7),IF((D18-$J18)+$K18+$I18<=0,IF(AND(D18>0,D18<>""),0,""),(D18-$J18)+$K18+$I18))) -> 15 | E19: =IF(OR(E18="",E18=0),"",IF(ISBLANK($J18),IF(E18+$K18+$I18-$C$8<=0,IF(AND(E18>0,E18<>""),0,""),E18+$K18+$I18-$C$8),IF((E18-$J18)+$K18+$I18<=0,IF(AND(E18>0,E18<>""),0,""),(E18-$J18)+$K18+$I18))) | F19: =IF(J18="","",IF(G18+F18+H18+I18-J18<0,0,G18+F18+H18+I18-J18))
A20: MS-SPRINT Sprint 30 | B20: =B19+$C$9 -> 46013 | C20: =IF(OR(C19="",C19=0),"",IF(ISBLANK(J19),IF(C19+K19+I19-$C$6<=0,IF(AND(C19>0,C19<>""),0,""),C19+K19+I19-$C$6),IF((C19-J19)+K19+I19<=0,IF(AND(C19>0,C19<>""),0,""),(C19-J19)+K19+I19))) -> 14 | D20: =IF(OR(D19="",D19=0),"",IF(ISBLANK($J19),IF(D19+$K19+$I19-$C$7<=0,IF(AND(D19>0,D19<>""),0,""),D19+$K19+$I19-$C$7),IF((D19-$J19)+$K19+$I19<=0,IF(AND(D19>0,D19<>""),0,""),(D19-$J19)+$K19+$I19))) -> 14 | E20: =IF(OR(E19="",E19=0),"",IF(ISBLANK($J19),IF(E19+$K19+$I19-$C$8<=0,IF(AND(E19>0,E19<>""),0,""),E19+$K19+$I19-$C$8),IF((E19-$J19)+$K19+$I19<=0,IF(AND(E19>0,E19<>""),0,""),(E19-$J19)+$K19+$I19))) | F20: =IF(J19="","",IF(G19+F19+H19+I19-J19<0,0,G19+F19+H19+I19-J19))
A21: MS-SPRINT Sprint 31 | B21: =B20+$C$9 -> 46020 | C21: =IF(OR(C20="",C20=0),"",IF(ISBLANK(J20),IF(C20+K20+I20-$C$6<=0,IF(AND(C20>0,C20<>""),0,""),C20+K20+I20-$C$6),IF((C20-J20)+K20+I20<=0,IF(AND(C20>0,C20<>""),0,""),(C20-J20)+K20+I20))) -> 13 | D21: =IF(OR(D20="",D20=0),"",IF(ISBLANK($J20),IF(D20+$K20+$I20-$C$7<=0,IF(AND(D20>0,D20<>""),0,""),D20+$K20+$I20-$C$7),IF((D20-$J20)+$K20+$I20<=0,IF(AND(D20>0,D20<>""),0,""),(D20-$J20)+$K20+$I20))) -> 13 | E21: =IF(OR(E20="",E20=0),"",IF(ISBLANK($J20),IF(E20+$K20+$I20-$C$8<=0,IF(AND(E20>0,E20<>""),0,""),E20+$K20+$I20-$C$8),IF((E20-$J20)+$K20+$I20<=0,IF(AND(E20>0,E20<>""),0,""),(E20-$J20)+$K20+$I20))) | F21: =IF(J20="","",IF(G20+F20+H20+I20-J20<0,0,G20+F20+H20+I20-J20))
B22: =B21+$C$9 -> 46027 | C22: =IF(OR(C21="",C21=0),"",IF(ISBLANK(J21),IF(C21+K21+I21-$C$6<=0,IF(AND(C21>0,C21<>""),0,""),C21+K21+I21-$C$6),IF((C21-J21)+K21+I21<=0,IF(AND(C21>0,C21<>""),0,""),(C21-J21)+K21+I21))) -> 12 | D22: =IF(OR(D21="",D21=0),"",IF(ISBLANK($J21),IF(D21+$K21+$I21-$C$7<=0,IF(AND(D21>0,D21<>""),0,""),D21+$K21+$I21-$C$7),IF((D21-$J21)+$K21+$I21<=0,IF(AND(D21>0,D21<>""),0,""),(D21-$J21)+$K21+$I21))) -> 12 | E22: =IF(OR(E21="",E21=0),"",IF(ISBLANK($J21),IF(E21+$K21+$I21-$C$8<=0,IF(AND(E21>0,E21<>""),0,""),E21+$K21+$I21-$C$8),IF((E21-$J21)+$K21+$I21<=0,IF(AND(E21>0,E21<>""),0,""),(E21-$J21)+$K21+$I21))) | F22: =IF(J21="","",IF(G21+F21+H21+I21-J21<0,0,G21+F21+H21+I21-J21))
B23: =B22+$C$9 -> 46034 | C23: =IF(OR(C22="",C22=0),"",IF(ISBLANK(J22),IF(C22+K22+I22-$C$6<=0,IF(AND(C22>0,C22<>""),0,""),C22+K22+I22-$C$6),IF((C22-J22)+K22+I22<=0,IF(AND(C22>0,C22<>""),0,""),(C22-J22)+K22+I22))) -> 11 | D23: =IF(OR(D22="",D22=0),"",IF(ISBLANK($J22),IF(D22+$K22+$I22-$C$7<=0,IF(AND(D22>0,D22<>""),0,""),D22+$K22+$I22-$C$7),IF((D22-$J22)+$K22+$I22<=0,IF(AND(D22>0,D22<>""),0,""),(D22-$J22)+$K22+$I22))) -> 11 | E23: =IF(OR(E22="",E22=0),"",IF(ISBLANK($J22),IF(E22+$K22+$I22-$C$8<=0,IF(AND(E22>0,E22<>""),0,""),E22+$K22+$I22-$C$8),IF((E22-$J22)+$K22+$I22<=0,IF(AND(E22>0,E22<>""),0,""),(E22-$J22)+$K22+$I22))) | F23: =IF(J22="","",IF(G22+F22+H22+I22-J22<0,0,G22+F22+H22+I22-J22))
B24: =B23+$C$9 -> 46041 | C24: =IF(OR(C23="",C23=0),"",IF(ISBLANK(J23),IF(C23+K23+I23-$C$6<=0,IF(AND(C23>0,C23<>""),0,""),C23+K23+I23-$C$6),IF((C23-J23)+K23+I23<=0,IF(AND(C23>0,C23<>""),0,""),(C23-J23)+K23+I23))) -> 10 | D24: =IF(OR(D23="",D23=0),"",IF(ISBLANK($J23),IF(D23+$K23+$I23-$C$7<=0,IF(AND(D23>0,D23<>""),0,""),D23+$K23+$I23-$C$7),IF((D23-$J23)+$K23+$I23<=0,IF(AND(D23>0,D23<>""),0,""),(D23-$J23)+$K23+$I23))) -> 10 | E24: =IF(OR(E23="",E23=0),"",IF(ISBLANK($J23),IF(E23+$K23+$I23-$C$8<=0,IF(AND(E23>0,E23<>""),0,""),E23+$K23+$I23-$C$8),IF((E23-$J23)+$K23+$I23<=0,IF(AND(E23>0,E23<>""),0,""),(E23-$J23)+$K23+$I23))) | F24: =IF(J23="","",IF(G23+F23+H23+I23-J23<0,0,G23+F23+H23+I23-J23))
B25: =B24+$C$9 -> 46048 | C25: =IF(OR(C24="",C24=0),"",IF(ISBLANK(J24),IF(C24+K24+I24-$C$6<=0,IF(AND(C24>0,C24<>""),0,""),C24+K24+I24-$C$6),IF((C24-J24)+K24+I24<=0,IF(AND(C24>0,C24<>""),0,""),(C24-J24)+K24+I24))) -> 9 | D25: =IF(OR(D24="",D24=0),"",IF(ISBLANK($J24),IF(D24+$K24+$I24-$C$7<=0,IF(AND(D24>0,D24<>""),0,""),D24+$K24+$I24-$C$7),IF((D24-$J24)+$K24+$I24<=0,IF(AND(D24>0,D24<>""),0,""),(D24-$J24)+$K24+$I24))) -> 9 | E25: =IF(OR(E24="",E24=0),"",IF(ISBLANK($J24),IF(E24+$K24+$I24-$C$8<=0,IF(AND(E24>0,E24<>""),0,""),E24+$K24+$I24-$C$8),IF((E24-$J24)+$K24+$I24<=0,IF(AND(E24>0,E24<>""),0,""),(E24-$J24)+$K24+$I24))) | F25: =IF(J24="","",IF(G24+F24+H24+I24-J24<0,0,G24+F24+H24+I24-J24))
B26: =B25+$C$9 -> 46055 | C26: =IF(OR(C25="",C25=0),"",IF(ISBLANK(J25),IF(C25+K25+I25-$C$6<=0,IF(AND(C25>0,C25<>""),0,""),C25+K25+I25-$C$6),IF((C25-J25)+K25+I25<=0,IF(AND(C25>0,C25<>""),0,""),(C25-J25)+K25+I25))) -> 8 | D26: =IF(OR(D25="",D25=0),"",IF(ISBLANK($J25),IF(D25+$K25+$I25-$C$7<=0,IF(AND(D25>0,D25<>""),0,""),D25+$K25+$I25-$C$7),IF((D25-$J25)+$K25+$I25<=0,IF(AND(D25>0,D25<>""),0,""),(D25-$J25)+$K25+$I25))) -> 8 | E26: =IF(OR(E25="",E25=0),"",IF(ISBLANK($J25),IF(E25+$K25+$I25-$C$8<=0,IF(AND(E25>0,E25<>""),0,""),E25+$K25+$I25-$C$8),IF((E25-$J25)+$K25+$I25<=0,IF(AND(E25>0,E25<>""),0,""),(E25-$J25)+$K25+$I25))) | F26: =IF(J25="","",IF(G25+F25+H25+I25-J25<0,0,G25+F25+H25+I25-J25))
B27: =B26+$C$9 -> 46062 | C27: =IF(OR(C26="",C26=0),"",IF(ISBLANK(J26),IF(C26+K26+I26-$C$6<=0,IF(AND(C26>0,C26<>""),0,""),C26+K26+I26-$C$6),IF((C26-J26)+K26+I26<=0,IF(AND(C26>0,C26<>""),0,""),(C26-J26)+K26+I26))) -> 7 | D27: =IF(OR(D26="",D26=0),"",IF(ISBLANK($J26),IF(D26+$K26+$I26-$C$7<=0,IF(AND(D26>0,D26<>""),0,""),D26+$K26+$I26-$C$7),IF((D26-$J26)+$K26+$I26<=0,IF(AND(D26>0,D26<>""),0,""),(D26-$J26)+$K26+$I26))) -> 7 | E27: =IF(OR(E26="",E26=0),"",IF(ISBLANK($J26),IF(E26+$K26+$I26-$C$8<=0,IF(AND(E26>0,E26<>""),0,""),E26+$K26+$I26-$C$8),IF((E26-$J26)+$K26+$I26<=0,IF(AND(E26>0,E26<>""),0,""),(E26-$J26)+$K26+$I26))) | F27: =IF(J26="","",IF(G26+F26+H26+I26-J26<0,0,G26+F26+H26+I26-J26))
B28: =B27+$C$9 -> 46069 | C28: =IF(OR(C27="",C27=0),"",IF(ISBLANK(J27),IF(C27+K27+I27-$C$6<=0,IF(AND(C27>0,C27<>""),0,""),C27+K27+I27-$C$6),IF((C27-J27)+K27+I27<=0,IF(AND(C27>0,C27<>""),0,""),(C27-J27)+K27+I27))) -> 6 | D28: =IF(OR(D27="",D27=0),"",IF(ISBLANK($J27),IF(D27+$K27+$I27-$C$7<=0,IF(AND(D27>0,D27<>""),0,""),D27+$K27+$I27-$C$7),IF((D27-$J27)+$K27+$I27<=0,IF(AND(D27>0,D27<>""),0,""),(D27-$J27)+$K27+$I27))) -> 6 | E28: =IF(OR(E27="",E27=0),"",IF(ISBLANK($J27),IF(E27+$K27+$I27-$C$8<=0,IF(AND(E27>0,E27<>""),0,""),E27+$K27+$I27-$C$8),IF((E27-$J27)+$K27+$I27<=0,IF(AND(E27>0,E27<>""),0,""),(E27-$J27)+$K27+$I27))) | F28: =IF(J27="","",IF(G27+F27+H27+I27-J27<0,0,G27+F27+H27+I27-J27))
B29: =B28+$C$9 -> 46076 | C29: =IF(OR(C28="",C28=0),"",IF(ISBLANK(J28),IF(C28+K28+I28-$C$6<=0,IF(AND(C28>0,C28<>""),0,""),C28+K28+I28-$C$6),IF((C28-J28)+K28+I28<=0,IF(AND(C28>0,C28<>""),0,""),(C28-J28)+K28+I28))) -> 5 | D29: =IF(OR(D28="",D28=0),"",IF(ISBLANK($J28),IF(D28+$K28+$I28-$C$7<=0,IF(AND(D28>0,D28<>""),0,""),D28+$K28+$I28-$C$7),IF((D28-$J28)+$K28+$I28<=0,IF(AND(D28>0,D28<>""),0,""),(D28-$J28)+$K28+$I28))) -> 5 | E29: =IF(OR(E28="",E28=0),"",IF(ISBLANK($J28),IF(E28+$K28+$I28-$C$8<=0,IF(AND(E28>0,E28<>""),0,""),E28+$K28+$I28-$C$8),IF((E28-$J28)+$K28+$I28<=0,IF(AND(E28>0,E28<>""),0,""),(E28-$J28)+$K28+$I28))) | F29: =IF(J28="","",IF(G28+F28+H28+I28-J28<0,0,G28+F28+H28+I28-J28))
B30: =B29+$C$9 -> 46083 | C30: =IF(OR(C29="",C29=0),"",IF(ISBLANK(J29),IF(C29+K29+I29-$C$6<=0,IF(AND(C29>0,C29<>""),0,""),C29+K29+I29-$C$6),IF((C29-J29)+K29+I29<=0,IF(AND(C29>0,C29<>""),0,""),(C29-J29)+K29+I29))) -> 4 | D30: =IF(OR(D29="",D29=0),"",IF(ISBLANK($J29),IF(D29+$K29+$I29-$C$7<=0,IF(AND(D29>0,D29<>""),0,""),D29+$K29+$I29-$C$7),IF((D29-$J29)+$K29+$I29<=0,IF(AND(D29>0,D29<>""),0,""),(D29-$J29)+$K29+$I29))) -> 4 | E30: =IF(OR(E29="",E29=0),"",IF(ISBLANK($J29),IF(E29+$K29+$I29-$C$8<=0,IF(AND(E29>0,E29<>""),0,""),E29+$K29+$I29-$C$8),IF((E29-$J29)+$K29+$I29<=0,IF(AND(E29>0,E29<>""),0,""),(E29-$J29)+$K29+$I29))) | F30: =IF(J29="","",IF(G29+F29+H29+I29-J29<0,0,G29+F29+H29+I29-J29))
B31: =B30+$C$9 -> 46090 | C31: =IF(OR(C30="",C30=0),"",IF(ISBLANK(J30),IF(C30+K30+I30-$C$6<=0,IF(AND(C30>0,C30<>""),0,""),C30+K30+I30-$C$6),IF((C30-J30)+K30+I30<=0,IF(AND(C30>0,C30<>""),0,""),(C30-J30)+K30+I30))) -> 3 | D31: =IF(OR(D30="",D30=0),"",IF(ISBLANK($J30),IF(D30+$K30+$I30-$C$7<=0,IF(AND(D30>0,D30<>""),0,""),D30+$K30+$I30-$C$7),IF((D30-$J30)+$K30+$I30<=0,IF(AND(D30>0,D30<>""),0,""),(D30-$J30)+$K30+$I30))) -> 3 | E31: =IF(OR(E30="",E30=0),"",IF(ISBLANK($J30),IF(E30+$K30+$I30-$C$8<=0,IF(AND(E30>0,E30<>""),0,""),E30+$K30+$I30-$C$8),IF((E30-$J30)+$K30+$I30<=0,IF(AND(E30>0,E30<>""),0,""),(E30-$J30)+$K30+$I30))) | F31: =IF(J30="","",IF(G30+F30+H30+I30-J30<0,0,G30+F30+H30+I30-J30))
B32: =B31+$C$9 -> 46097 | C32: =IF(OR(C31="",C31=0),"",IF(ISBLANK(J31),IF(C31+K31+I31-$C$6<=0,IF(AND(C31>0,C31<>""),0,""),C31+K31+I31-$C$6),IF((C31-J31)+K31+I31<=0,IF(AND(C31>0,C31<>""),0,""),(C31-J31)+K31+I31))) -> 2 | D32: =IF(OR(D31="",D31=0),"",IF(ISBLANK($J31),IF(D31+$K31+$I31-$C$7<=0,IF(AND(D31>0,D31<>""),0,""),D31+$K31+$I31-$C$7),IF((D31-$J31)+$K31+$I31<=0,IF(AND(D31>0,D31<>""),0,""),(D31-$J31)+$K31+$I31))) -> 2 | E32: =IF(OR(E31="",E31=0),"",IF(ISBLANK($J31),IF(E31+$K31+$I31-$C$8<=0,IF(AND(E31>0,E31<>""),0,""),E31+$K31+$I31-$C$8),IF((E31-$J31)+$K31+$I31<=0,IF(AND(E31>0,E31<>""),0,""),(E31-$J31)+$K31+$I31))) | F32: =IF(J31="","",IF(G31+F31+H31+I31-J31<0,0,G31+F31+H31+I31-J31))
B33: =B32+$C$9 -> 46104 | C33: =IF(OR(C32="",C32=0),"",IF(ISBLANK(J32),IF(C32+K32+I32-$C$6<=0,IF(AND(C32>0,C32<>""),0,""),C32+K32+I32-$C$6),IF((C32-J32)+K32+I32<=0,IF(AND(C32>0,C32<>""),0,""),(C32-J32)+K32+I32))) -> 1 | D33: =IF(OR(D32="",D32=0),"",IF(ISBLANK($J32),IF(D32+$K32+$I32-$C$7<=0,IF(AND(D32>0,D32<>""),0,""),D32+$K32+$I32-$C$7),IF((D32-$J32)+$K32+$I32<=0,IF(AND(D32>0,D32<>""),0,""),(D32-$J32)+$K32+$I32))) -> 1 | E33: =IF(OR(E32="",E32=0),"",IF(ISBLANK($J32),IF(E32+$K32+$I32-$C$8<=0,IF(AND(E32>0,E32<>""),0,""),E32+$K32+$I32-$C$8),IF((E32-$J32)+$K32+$I32<=0,IF(AND(E32>0,E32<>""),0,""),(E32-$J32)+$K32+$I32))) | F33: =IF(J32="","",IF(G32+F32+H32+I32-J32<0,0,G32+F32+H32+I32-J32))
... B54: =B53+$C$9 -> 46251 | C54: =IF(OR(C53="",C53=0),"",IF(ISBLANK(J53),IF(C53+K53+I53-$C$6<=0,IF(AND(C53>0,C53<>""),0,""),C53+K53+I53-$C$6),IF((C53-J53)+K53+I53<=0,IF(AND(C53>0,C53<>""),0,""),(C53-J53)+K53+I53))) | D54: =IF(OR(D53="",D53=0),"",IF(ISBLANK($J53),IF(D53+$K53+$I53-$C$7<=0,IF(AND(D53>0,D53<>""),0,""),D53+$K53+$I53-$C$7),IF((D53-$J53)+$K53+$I53<=0,IF(AND(D53>0,D53<>""),0,""),(D53-$J53)+$K53+$I53))) | E54: =IF(OR(E53="",E53=0),"",IF(ISBLANK($J53),IF(E53+$K53+$I53-$C$8<=0,IF(AND(E53>0,E53<>""),0,""),E53+$K53+$I53-$C$8),IF((E53-$J53)+$K53+$I53<=0,IF(AND(E53>0,E53<>""),0,""),(E53-$J53)+$K53+$I53))) | F54: =IF(J53="","",IF(G53+F53+H53+I53-J53<0,0,G53+F53+H53+I53-J53))
C81: =D90 -> 0
B87: =IF(B86="","",IF(B86+$C$9<=$C$5,B86+$C$9,"")) | C87: =IF(B87<>"",C86-$C$2/COUNT($B$17:$B$510),"")
B88: =IF(B87="","",IF(B87+$C$9<=$C$5,B87+$C$9,"")) | C88: =IF(B88<>"",C87-$C$2/COUNT($B$17:$B$510),"")
B89: =IF(B88="","",IF(B88+$C$9<=$C$5,B88+$C$9,"")) | C89: =IF(B89<>"",C88-$C$2/COUNT($B$17:$B$510),"")
B90: =IF(B89="","",IF(B89+$C$9<=$C$5,B89+$C$9,"")) | C90: =IF(B90<>"",C89-$C$2/COUNT($B$17:$B$510),"")
B91: =IF(B90="","",IF(B90+$C$9<=$C$5,B90+$C$9,"")) | C91: =IF(B91<>"",C90-$C$2/COUNT($B$17:$B$510),"")
B92: =IF(B91="","",IF(B91+$C$9<=$C$5,B91+$C$9,"")) | C92: =IF(B92<>"",C91-$C$2/COUNT($B$17:$B$510),"")
B93: =IF(B92="","",IF(B92+$C$9<=$C$5,B92+$C$9,"")) | C93: =IF(B93<>"",C92-$C$2/COUNT($B$17:$B$510),"")
B94: =IF(B93="","",IF(B93+$C$9<=$C$5,B93+$C$9,"")) | C94: =IF(B94<>"",C93-$C$2/COUNT($B$17:$B$510),"")
B95: =IF(B94="","",IF(B94+$C$9<=$C$5,B94+$C$9,"")) | C95: =IF(B95<>"",C94-$C$2/COUNT($B$17:$B$510),"")
B96: =IF(B95="","",IF(B95+$C$9<=$C$5,B95+$C$9,"")) | C96: =IF(B96<>"",C95-$C$2/COUNT($B$17:$B$510),"")
B97: =IF(B96="","",IF(B96+$C$9<=$C$5,B96+$C$9,"")) | C97: =IF(B97<>"",C96-$C$2/COUNT($B$17:$B$510),"")
B98: =IF(B97="","",IF(B97+$C$9<=$C$5,B97+$C$9,"")) | C98: =IF(B98<>"",C97-$C$2/COUNT($B$17:$B$510),"")
... B511: =IF(B510="","",IF(B510+$C$9<=$C$5,B510+$C$9,"")) | C511: =IF(B511<>"",C510-$C$2/COUNT($B$17:$B$510),"")

Sheet MATRIZ TIME - excluir
A1: Cone: baseado na nossa vazão, chegaremos na data alvo? O que cabe até data alvo?
B2: TIME | C2: OPTIMUS | D2: Épicos | E2: considerar apenas os épicos que estão no mapa de release
B3: Features | C3: =COUNTIF(#REF!,C2) -> #REF! | D3: Story / Tarefa / Bug / Spike | E3: considerar o trabalho de todos os integrantes do time, inclsuive tasks de dívidas técnicas e automação
B4: Data início | C4: 45987 | D4: Primeria sprint da release
B5: Data fim esperada | C5: 46113 | D5: Data entregada release
B6: Melhor cenário | C6: {=MAX(INDEX(J:J, LARGE(IF(J:J<>"", ROW(J:J)), {1;2;3;4})))} -> #REF! | D6: itens por semana | E6: considerar sempre as ultimas 4 sprints para atualizar os números
B7: Pior cenário | C7: {=IF(MIN(INDEX(J:J, LARGE(IF(J:J<>"", ROW(J:J)), {1;2;3;4})))=0, 1, MIN(INDEX(J:J, LARGE(IF(J:J<>"", ROW(J:J)), {1;2;3;4}))))} -> #REF! | D7: itens por semana | E7: considerar sempre as ultimas 4 sprints para atualizar os números
B8: Velocidade necessária | C8: 2 | D8: itens por semana
B9: Acompanhar a cada | C9: 7 | D9: dias
B11: Data do Início da Semana | C11: Se seguirmos nossa melhor vazão, quando entregamos? | D11: Se seguirmos nossa pior vazão, quando entregamos? | E11: Vazão ideal para atender à data | F11: Itens da sprint anterior que não foram concluídos | G11: Itens que entram em sprint pela primeira vez | H11: Itens que entraram na Sprint depois do planejamento, mas não são "Fura fila" | I11: Itens Fura-Fila que apareceram ao longo da Sprint | J11: Itens entregues na Sprint | K11: Itens que chegaram no backlog do time ao longo da semana, mas não na sprint | L11: Observações adicionais
B12: Não editar esses campos | G12: Preencher com os dados de cada semana
A13: Sprint | B13: Semana | C13: A fazer (melhor cenário) | D13: A fazer (pior cenário) | E13: A fazer (valocidade necessária) | F13: Itens Transbordo | G13: Itens Planejados (Planning) | H13: Itens não planejados na sprint | I13: (+) Expedite | J13: Realizado | K13: (+)(-) Escopo pro time | L13: OBSERVAÇÕES
A14: Semana 1 | B14: =C4 -> 45987 | C14: =$C$3 -> #REF! | D14: =$C$3 -> #REF! | E14: =$C$3 -> #REF! | G14: =COUNTIFS(#REF!, ">=" & INT(B14),#REF!, "<" & INT(B14)+6,#REF!, $C$2,#REF!, "<>BUG") -> #REF! | H14: =COUNTIFS(#REF!, ">=" &(INT(B14)+1),#REF!, "<" &(INT(B14)+6),#REF!, $C$2,#REF!, "<>BUG") -> #REF! | I14: =COUNTIFS(#REF!, $C$2,#REF!, "BUG",#REF!, ">=" & INT(B14),#REF!, "<" & INT(B14)+7) -> #REF! | J14: =COUNTIFS(#REF!, $C$2,#REF!, "<>" & "",#REF!, ">=" & INT(B14),#REF!, "<" & INT(B14)+7) -> #REF! | K14: =-COUNTIFS(#REF!, ">=" & INT(B14),#REF!, "<" & INT(B14)+7,#REF!, "Descartado",#REF!,$C$2) -> #REF!
A15: Semana 2 | B15: =B14+$C$9 -> 45994 | C15: =IF(OR(C14="",C14=0),"",IF(ISBLANK($J14),IF(C14+$K14+$I14-$C$6<=0,IF(AND(C14>0,C14<>""),0,""),C14+$K14+$I14-$C$6),IF((C14-$J14)+$K14+$I14<=0,IF(AND(C14>0,C14<>""),0,""),(C14-$J14)+$K14+$I14))) -> #REF! | D15: =IF(OR(D14="",D14=0),"",IF(ISBLANK($J14),IF(D14+$K14+$I14-$C$7<=0,IF(AND(D14>0,D14<>""),0,""),D14+$K14+$I14-$C$7),IF((D14-$J14)+$K14+$I14<=0,IF(AND(D14>0,D14<>""),0,""),(D14-$J14)+$K14+$I14))) -> #REF! | E15: =IF(OR(E14="",E14=0),"",IF(ISBLANK($J14),IF(E14+$K14+$I14-$C$8<=0,IF(AND(E14>0,E14<>""),0,""),E14+$K14+$I14-$C$8),IF((E14-$J14)+$K14+$I14<=0,IF(AND(E14>0,E14<>""),0,""),(E14-$J14)+$K14+$I14))) -> #REF! | F15: =IF(J14="","",IF(G14+F14+H14+I14-J14<0,0,G14+F14+H14+I14-J14)) -> #REF! | G15: =COUNTIFS(#REF!, ">=" & INT(B15),#REF!, "<" & INT(B15)+6,#REF!, $C$2,#REF!, "<>BUG") -> #REF! | H15: =COUNTIFS(#REF!, ">=" &(INT(B15)+1),#REF!, "<" &(INT(B15)+6),#REF!, $C$2,#REF!, "<>BUG") -> #REF! | I15: =COUNTIFS(#REF!, $C$2,#REF!, "BUG",#REF!, ">=" & INT(B15),#REF!, "<" & INT(B15)+7) -> #REF! | J15: =COUNTIFS(#REF!, $C$2,#REF!, "<>" & "",#REF!, ">=" & INT(B15),#REF!, "<" & INT(B15)+7) -> #REF! | K15: =-COUNTIFS(#REF!, ">=" & INT(B15),#REF!, "<" & INT(B15)+7,#REF!, "Descartado",#REF!,$C$2) -> #REF!
A16: Semana 3 | B16: =B15+$C$9 -> 46001 | C16: =IF(OR(C15="",C15=0),"",IF(ISBLANK(J15),IF(C15+K15+I15-$C$6<=0,IF(AND(C15>0,C15<>""),0,""),C15+K15+I15-$C$6),IF((C15-J15)+K15+I15<=0,IF(AND(C15>0,C15<>""),0,""),(C15-J15)+K15+I15))) -> #REF! | D16: =IF(OR(D15="",D15=0),"",IF(ISBLANK($J15),IF(D15+$K15+$I15-$C$7<=0,IF(AND(D15>0,D15<>""),0,""),D15+$K15+$I15-$C$7),IF((D15-$J15)+$K15+$I15<=0,IF(AND(D15>0,D15<>""),0,""),(D15-$J15)+$K15+$I15))) -> #REF! | E16: =IF(OR(E15="",E15=0),"",IF(ISBLANK($J15),IF(E15+$K15+$I15-$C$8<=0,IF(AND(E15>0,E15<>""),0,""),E15+$K15+$I15-$C$8),IF((E15-$J15)+$K15+$I15<=0,IF(AND(E15>0,E15<>""),0,""),(E15-$J15)+$K15+$I15))) -> #REF! | F16: =IF(J15="","",IF(G15+F15+H15+I15-J15<0,0,G15+F15+H15+I15-J15)) -> #REF! | G16: =COUNTIFS(#REF!, ">=" & INT(B16),#REF!, "<" & INT(B16)+6,#REF!, $C$2,#REF!, "<>BUG") -> #REF! | H16: =COUNTIFS(#REF!, ">=" &(INT(B16)+1),#REF!, "<" &(INT(B16)+6),#REF!, $C$2,#REF!, "<>BUG") -> #REF! | I16: =COUNTIFS(#REF!, $C$2,#REF!, "BUG",#REF!, ">=" & INT(B16),#REF!, "<" & INT(B16)+7) -> #REF! | J16: =COUNTIFS(#REF!, $C$2,#REF!, "<>" & "",#REF!, ">=" & INT(B16),#REF!, "<" & INT(B16)+7) -> #REF! | K16: =-COUNTIFS(#REF!, ">=" & INT(B16),#REF!, "<" & INT(B16)+7,#REF!, "Descartado",#REF!,$C$2) -> #REF!
A17: Semana 4 | B17: =B16+$C$9 -> 46008 | C17: =IF(OR(C16="",C16=0),"",IF(ISBLANK(J16),IF(C16+K16+I16-$C$6<=0,IF(AND(C16>0,C16<>""),0,""),C16+K16+I16-$C$6),IF((C16-J16)+K16+I16<=0,IF(AND(C16>0,C16<>""),0,""),(C16-J16)+K16+I16))) -> #REF! | D17: =IF(OR(D16="",D16=0),"",IF(ISBLANK($J16),IF(D16+$K16+$I16-$C$7<=0,IF(AND(D16>0,D16<>""),0,""),D16+$K16+$I16-$C$7),IF((D16-$J16)+$K16+$I16<=0,IF(AND(D16>0,D16<>""),0,""),(D16-$J16)+$K16+$I16))) -> #REF! | E17: =IF(OR(E16="",E16=0),"",IF(ISBLANK($J16),IF(E16+$K16+$I16-$C$8<=0,IF(AND(E16>0,E16<>""),0,""),E16+$K16+$I16-$C$8),IF((E16-$J16)+$K16+$I16<=0,IF(AND(E16>0,E16<>""),0,""),(E16-$J16)+$K16+$I16))) -> #REF! | F17: =IF(J16="","",IF(G16+F16+H16+I16-J16<0,0,G16+F16+H16+I16-J16)) -> #REF! | G17: =COUNTIFS(#REF!, ">=" & INT(B17),#REF!, "<" & INT(B17)+6,#REF!, $C$2,#REF!, "<>BUG") -> #REF! | H17: =COUNTIFS(#REF!, ">=" &(INT(B17)+1),#REF!, "<" &(INT(B17)+6),#REF!, $C$2,#REF!, "<>BUG") -> #REF! | I17: =COUNTIFS(#REF!, $C$2,#REF!, "BUG",#REF!, ">=" & INT(B17),#REF!, "<" & INT(B17)+7) -> #REF! | J17: =COUNTIFS(#REF!, $C$2,#REF!, "<>" & "",#REF!, ">=" & INT(B17),#REF!, "<" & INT(B17)+7) -> #REF! | K17: =-COUNTIFS(#REF!, ">=" & INT(B17),#REF!, "<" & INT(B17)+7,#REF!, "Descartado",#REF!,$C$2) -> #REF!
A18: Semana 5 | B18: =B17+$C$9 -> 46015 | C18: =IF(OR(C17="",C17=0),"",IF(ISBLANK(J17),IF(C17+K17+I17-$C$6<=0,IF(AND(C17>0,C17<>""),0,""),C17+K17+I17-$C$6),IF((C17-J17)+K17+I17<=0,IF(AND(C17>0,C17<>""),0,""),(C17-J17)+K17+I17))) -> #REF! | D18: =IF(OR(D17="",D17=0),"",IF(ISBLANK($J17),IF(D17+$K17+$I17-$C$7<=0,IF(AND(D17>0,D17<>""),0,""),D17+$K17+$I17-$C$7),IF((D17-$J17)+$K17+$I17<=0,IF(AND(D17>0,D17<>""),0,""),(D17-$J17)+$K17+$I17))) -> #REF! | E18: =IF(OR(E17="",E17=0),"",IF(ISBLANK($J17),IF(E17+$K17+$I17-$C$8<=0,IF(AND(E17>0,E17<>""),0,""),E17+$K17+$I17-$C$8),IF((E17-$J17)+$K17+$I17<=0,IF(AND(E17>0,E17<>""),0,""),(E17-$J17)+$K17+$I17))) -> #REF! | F18: =IF(J17="","",IF(G17+F17+H17+I17-J17<0,0,G17+F17+H17+I17-J17)) -> #REF! | G18: =COUNTIFS(#REF!, ">=" & INT(B18),#REF!, "<" & INT(B18)+6,#REF!, $C$2,#REF!, "<>BUG") -> #REF! | H18: =COUNTIFS(#REF!, ">=" &(INT(B18)+1),#REF!, "<" &(INT(B18)+6),#REF!, $C$2,#REF!, "<>BUG") -> #REF! | I18: =COUNTIFS(#REF!, $C$2,#REF!, "BUG",#REF!, ">=" & INT(B18),#REF!, "<" & INT(B18)+7) -> #REF! | J18: =COUNTIFS(#REF!, $C$2,#REF!, "<>" & "",#REF!, ">=" & INT(B18),#REF!, "<" & INT(B18)+7) -> #REF! | K18: =-COUNTIFS(#REF!, ">=" & INT(B18),#REF!, "<" & INT(B18)+7,#REF!, "Descartado",#REF!,$C$2) -> #REF!
A19: Semana 6 | B19: =B18+$C$9 -> 46022 | C19: =IF(OR(C18="",C18=0),"",IF(ISBLANK(J18),IF(C18+K18+I18-$C$6<=0,IF(AND(C18>0,C18<>""),0,""),C18+K18+I18-$C$6),IF((C18-J18)+K18+I18<=0,IF(AND(C18>0,C18<>""),0,""),(C18-J18)+K18+I18))) -> #REF! | D19: =IF(OR(D18="",D18=0),"",IF(ISBLANK($J18),IF(D18+$K18+$I18-$C$7<=0,IF(AND(D18>0,D18<>""),0,""),D18+$K18+$I18-$C$7),IF((D18-$J18)+$K18+$I18<=0,IF(AND(D18>0,D18<>""),0,""),(D18-$J18)+$K18+$I18))) -> #REF! | E19: =IF(OR(E18="",E18=0),"",IF(ISBLANK($J18),IF(E18+$K18+$I18-$C$8<=0,IF(AND(E18>0,E18<>""),0,""),E18+$K18+$I18-$C$8),IF((E18-$J18)+$K18+$I18<=0,IF(AND(E18>0,E18<>""),0,""),(E18-$J18)+$K18+$I18))) -> #REF! | F19: =IF(J18="","",IF(G18+F18+H18+I18-J18<0,0,G18+F18+H18+I18-J18)) -> #REF! | G19: =COUNTIFS(#REF!, ">=" & INT(B19),#REF!, "<" & INT(B19)+6,#REF!, $C$2,#REF!, "<>BUG") -> #REF! | H19: =COUNTIFS(#REF!, ">=" &(INT(B19)+1),#REF!, "<" &(INT(B19)+6),#REF!, $C$2,#REF!, "<>BUG") -> #REF! | I19: =COUNTIFS(#REF!, $C$2,#REF!, "BUG",#REF!, ">=" & INT(B19),#REF!, "<" & INT(B19)+7) -> #REF! | J19: =COUNTIFS(#REF!, $C$2,#REF!, "<>" & "",#REF!, ">=" & INT(B19),#REF!, "<" & INT(B19)+7) -> #REF! | K19: =-COUNTIFS(#REF!, ">=" & INT(B19),#REF!, "<" & INT(B19)+7,#REF!, "Descartado",#REF!,$C$2) -> #REF!
A20: Semana 7 | B20: =B19+$C$9 -> 46029 | C20: =IF(OR(C19="",C19=0),"",IF(ISBLANK(J19),IF(C19+K19+I19-$C$6<=0,IF(AND(C19>0,C19<>""),0,""),C19+K19+I19-$C$6),IF((C19-J19)+K19+I19<=0,IF(AND(C19>0,C19<>""),0,""),(C19-J19)+K19+I19))) -> #REF! | D20: =IF(OR(D19="",D19=0),"",IF(ISBLANK($J19),IF(D19+$K19+$I19-$C$7<=0,IF(AND(D19>0,D19<>""),0,""),D19+$K19+$I19-$C$7),IF((D19-$J19)+$K19+$I19<=0,IF(AND(D19>0,D19<>""),0,""),(D19-$J19)+$K19+$I19))) -> #REF! | E20: =IF(OR(E19="",E19=0),"",IF(ISBLANK($J19),IF(E19+$K19+$I19-$C$8<=0,IF(AND(E19>0,E19<>""),0,""),E19+$K19+$I19-$C$8),IF((E19-$J19)+$K19+$I19<=0,IF(AND(E19>0,E19<>""),0,""),(E19-$J19)+$K19+$I19))) -> #REF! | F20: =IF(J19="","",IF(G19+F19+H19+I19-J19<0,0,G19+F19+H19+I19-J19)) -> #REF! | G20: =COUNTIFS(#REF!, ">=" & INT(B20),#REF!, "<" & INT(B20)+6,#REF!, $C$2,#REF!, "<>BUG") -> #REF! | H20: =COUNTIFS(#REF!, ">=" &(INT(B20)+1),#REF!, "<" &(INT(B20)+6),#REF!, $C$2,#REF!, "<>BUG") -> #REF! | I20: =COUNTIFS(#REF!, $C$2,#REF!, "BUG",#REF!, ">=" & INT(B20),#REF!, "<" & INT(B20)+7) -> #REF! | J20: =COUNTIFS(#REF!, $C$2,#REF!, "<>" & "",#REF!, ">=" & INT(B20),#REF!, "<" & INT(B20)+7) -> #REF! | K20: =-COUNTIFS(#REF!, ">=" & INT(B20),#REF!, "<" & INT(B20)+7,#REF!, "Descartado",#REF!,$C$2) -> #REF!
A21: Semana 8 | B21: =B20+$C$9 -> 46036 | C21: =IF(OR(C20="",C20=0),"",IF(ISBLANK(J20),IF(C20+K20+I20-$C$6<=0,IF(AND(C20>0,C20<>""),0,""),C20+K20+I20-$C$6),IF((C20-J20)+K20+I20<=0,IF(AND(C20>0,C20<>""),0,""),(C20-J20)+K20+I20))) -> #REF! | D21: =IF(OR(D20="",D20=0),"",IF(ISBLANK($J20),IF(D20+$K20+$I20-$C$7<=0,IF(AND(D20>0,D20<>""),0,""),D20+$K20+$I20-$C$7),IF((D20-$J20)+$K20+$I20<=0,IF(AND(D20>0,D20<>""),0,""),(D20-$J20)+$K20+$I20))) -> #REF! | E21: =IF(OR(E20="",E20=0),"",IF(ISBLANK($J20),IF(E20+$K20+$I20-$C$8<=0,IF(AND(E20>0,E20<>""),0,""),E20+$K20+$I20-$C$8),IF((E20-$J20)+$K20+$I20<=0,IF(AND(E20>0,E20<>""),0,""),(E20-$J20)+$K20+$I20))) -> #REF! | F21: =IF(J20="","",IF(G20+F20+H20+I20-J20<0,0,G20+F20+H20+I20-J20)) -> #REF! | G21: =COUNTIFS(#REF!, ">=" & INT(B21),#REF!, "<" & INT(B21)+6,#REF!, $C$2,#REF!, "<>BUG") -> #REF! | H21: =COUNTIFS(#REF!, ">=" &(INT(B21)+1),#REF!, "<" &(INT(B21)+6),#REF!, $C$2,#REF!, "<>BUG") -> #REF! | I21: =COUNTIFS(#REF!, $C$2,#REF!, "BUG",#REF!, ">=" & INT(B21),#REF!, "<" & INT(B21)+7) -> #REF! | J21: =COUNTIFS(#REF!, $C$2,#REF!, "<>" & "",#REF!, ">=" & INT(B21),#REF!, "<" & INT(B21)+7) -> #REF! | K21: =-COUNTIFS(#REF!, ">=" & INT(B21),#REF!, "<" & INT(B21)+7,#REF!, "Descartado",#REF!,$C$2) -> #REF!
A22: Semana 9 | B22: =B21+$C$9 -> 46043 | C22: =IF(OR(C21="",C21=0),"",IF(ISBLANK(J21),IF(C21+K21+I21-$C$6<=0,IF(AND(C21>0,C21<>""),0,""),C21+K21+I21-$C$6),IF((C21-J21)+K21+I21<=0,IF(AND(C21>0,C21<>""),0,""),(C21-J21)+K21+I21))) -> #REF! | D22: =IF(OR(D21="",D21=0),"",IF(ISBLANK($J21),IF(D21+$K21+$I21-$C$7<=0,IF(AND(D21>0,D21<>""),0,""),D21+$K21+$I21-$C$7),IF((D21-$J21)+$K21+$I21<=0,IF(AND(D21>0,D21<>""),0,""),(D21-$J21)+$K21+$I21))) -> #REF! | E22: =IF(OR(E21="",E21=0),"",IF(ISBLANK($J21),IF(E21+$K21+$I21-$C$8<=0,IF(AND(E21>0,E21<>""),0,""),E21+$K21+$I21-$C$8),IF((E21-$J21)+$K21+$I21<=0,IF(AND(E21>0,E21<>""),0,""),(E21-$J21)+$K21+$I21))) -> #REF! | F22: =IF(J21="","",IF(G21+F21+H21+I21-J21<0,0,G21+F21+H21+I21-J21)) -> #REF! | G22: =COUNTIFS(#REF!, ">=" & INT(B22),#REF!, "<" & INT(B22)+6,#REF!, $C$2,#REF!, "<>BUG") -> #REF! | H22: =COUNTIFS(#REF!, ">=" &(INT(B22)+1),#REF!, "<" &(INT(B22)+6),#REF!, $C$2,#REF!, "<>BUG") -> #REF! | I22: =COUNTIFS(#REF!, $C$2,#REF!, "BUG",#REF!, ">=" & INT(B22),#REF!, "<" & INT(B22)+7) -> #REF! | J22: =COUNTIFS(#REF!, $C$2,#REF!, "<>" & "",#REF!, ">=" & INT(B22),#REF!, "<" & INT(B22)+7) -> #REF! | K22: =-COUNTIFS(#REF!, ">=" & INT(B22),#REF!, "<" & INT(B22)+7,#REF!, "Descartado",#REF!,$C$2) -> #REF!
A23: Semana 10 | B23: =B22+$C$9 -> 46050 | C23: =IF(OR(C22="",C22=0),"",IF(ISBLANK(J22),IF(C22+K22+I22-$C$6<=0,IF(AND(C22>0,C22<>""),0,""),C22+K22+I22-$C$6),IF((C22-J22)+K22+I22<=0,IF(AND(C22>0,C22<>""),0,""),(C22-J22)+K22+I22))) -> #REF! | D23: =IF(OR(D22="",D22=0),"",IF(ISBLANK($J22),IF(D22+$K22+$I22-$C$7<=0,IF(AND(D22>0,D22<>""),0,""),D22+$K22+$I22-$C$7),IF((D22-$J22)+$K22+$I22<=0,IF(AND(D22>0,D22<>""),0,""),(D22-$J22)+$K22+$I22))) -> #REF! | E23: =IF(OR(E22="",E22=0),"",IF(ISBLANK($J22),IF(E22+$K22+$I22-$C$8<=0,IF(AND(E22>0,E22<>""),0,""),E22+$K22+$I22-$C$8),IF((E22-$J22)+$K22+$I22<=0,IF(AND(E22>0,E22<>""),0,""),(E22-$J22)+$K22+$I22))) -> #REF! | F23: =IF(J22="","",IF(G22+F22+H22+I22-J22<0,0,G22+F22+H22+I22-J22)) -> #REF! | G23: =COUNTIFS(#REF!, ">=" & INT(B23),#REF!, "<" & INT(B23)+6,#REF!, $C$2,#REF!, "<>BUG") -> #REF! | H23: =COUNTIFS(#REF!, ">=" &(INT(B23)+1),#REF!, "<" &(INT(B23)+6),#REF!, $C$2,#REF!, "<>BUG") -> #REF! | I23: =COUNTIFS(#REF!, $C$2,#REF!, "BUG",#REF!, ">=" & INT(B23),#REF!, "<" & INT(B23)+7) -> #REF! | J23: =COUNTIFS(#REF!, $C$2,#REF!, "<>" & "",#REF!, ">=" & INT(B23),#REF!, "<" & INT(B23)+7) -> #REF! | K23: =-COUNTIFS(#REF!, ">=" & INT(B23),#REF!, "<" & INT(B23)+7,#REF!, "Descartado",#REF!,$C$2) -> #REF!
A24: Semana 11 | B24: =B23+$C$9 -> 46057 | C24: =IF(OR(C23="",C23=0),"",IF(ISBLANK(J23),IF(C23+K23+I23-$C$6<=0,IF(AND(C23>0,C23<>""),0,""),C23+K23+I23-$C$6),IF((C23-J23)+K23+I23<=0,IF(AND(C23>0,C23<>""),0,""),(C23-J23)+K23+I23))) -> #REF! | D24: =IF(OR(D23="",D23=0),"",IF(ISBLANK($J23),IF(D23+$K23+$I23-$C$7<=0,IF(AND(D23>0,D23<>""),0,""),D23+$K23+$I23-$C$7),IF((D23-$J23)+$K23+$I23<=0,IF(AND(D23>0,D23<>""),0,""),(D23-$J23)+$K23+$I23))) -> #REF! | E24: =IF(OR(E23="",E23=0),"",IF(ISBLANK($J23),IF(E23+$K23+$I23-$C$8<=0,IF(AND(E23>0,E23<>""),0,""),E23+$K23+$I23-$C$8),IF((E23-$J23)+$K23+$I23<=0,IF(AND(E23>0,E23<>""),0,""),(E23-$J23)+$K23+$I23))) -> #REF! | F24: =IF(J23="","",IF(G23+F23+H23+I23-J23<0,0,G23+F23+H23+I23-J23)) -> #REF! | G24: =COUNTIFS(#REF!, ">=" & INT(B24),#REF!, "<" & INT(B24)+6,#REF!, $C$2,#REF!, "<>BUG") -> #REF! | H24: =COUNTIFS(#REF!, ">=" &(INT(B24)+1),#REF!, "<" &(INT(B24)+6),#REF!, $C$2,#REF!, "<>BUG") -> #REF! | I24: =COUNTIFS(#REF!, $C$2,#REF!, "BUG",#REF!, ">=" & INT(B24),#REF!, "<" & INT(B24)+7) -> #REF! | J24: =COUNTIFS(#REF!, $C$2,#REF!, "<>" & "",#REF!, ">=" & INT(B24),#REF!, "<" & INT(B24)+7) -> #REF! | K24: =-COUNTIFS(#REF!, ">=" & INT(B24),#REF!, "<" & INT(B24)+7,#REF!, "Descartado",#REF!,$C$2) -> #REF!
A25: Semana 12 | B25: =B24+$C$9 -> 46064 | C25: =IF(OR(C24="",C24=0),"",IF(ISBLANK(J24),IF(C24+K24+I24-$C$6<=0,IF(AND(C24>0,C24<>""),0,""),C24+K24+I24-$C$6),IF((C24-J24)+K24+I24<=0,IF(AND(C24>0,C24<>""),0,""),(C24-J24)+K24+I24))) -> #REF! | D25: =IF(OR(D24="",D24=0),"",IF(ISBLANK($J24),IF(D24+$K24+$I24-$C$7<=0,IF(AND(D24>0,D24<>""),0,""),D24+$K24+$I24-$C$7),IF((D24-$J24)+$K24+$I24<=0,IF(AND(D24>0,D24<>""),0,""),(D24-$J24)+$K24+$I24))) -> #REF! | E25: =IF(OR(E24="",E24=0),"",IF(ISBLANK($J24),IF(E24+$K24+$I24-$C$8<=0,IF(AND(E24>0,E24<>""),0,""),E24+$K24+$I24-$C$8),IF((E24-$J24)+$K24+$I24<=0,IF(AND(E24>0,E24<>""),0,""),(E24-$J24)+$K24+$I24))) -> #REF! | F25: =IF(J24="","",IF(G24+F24+H24+I24-J24<0,0,G24+F24+H24+I24-J24)) -> #REF! | G25: =COUNTIFS(#REF!, ">=" & INT(B25),#REF!, "<" & INT(B25)+6,#REF!, $C$2,#REF!, "<>BUG") -> #REF! | H25: =COUNTIFS(#REF!, ">=" &(INT(B25)+1),#REF!, "<" &(INT(B25)+6),#REF!, $C$2,#REF!, "<>BUG") -> #REF! | I25: =COUNTIFS(#REF!, $C$2,#REF!, "BUG",#REF!, ">=" & INT(B25),#REF!, "<" & INT(B25)+7) -> #REF! | J25: =COUNTIFS(#REF!, $C$2,#REF!, "<>" & "",#REF!, ">=" & INT(B25),#REF!, "<" & INT(B25)+7) -> #REF! | K25: =-COUNTIFS(#REF!, ">=" & INT(B25),#REF!, "<" & INT(B25)+7,#REF!, "Descartado",#REF!,$C$2) -> #REF!
A26: Semana 13 | B26: =B25+$C$9 -> 46071 | C26: =IF(OR(C25="",C25=0),"",IF(ISBLANK(J25),IF(C25+K25+I25-$C$6<=0,IF(AND(C25>0,C25<>""),0,""),C25+K25+I25-$C$6),IF((C25-J25)+K25+I25<=0,IF(AND(C25>0,C25<>""),0,""),(C25-J25)+K25+I25))) -> #REF! | D26: =IF(OR(D25="",D25=0),"",IF(ISBLANK($J25),IF(D25+$K25+$I25-$C$7<=0,IF(AND(D25>0,D25<>""),0,""),D25+$K25+$I25-$C$7),IF((D25-$J25)+$K25+$I25<=0,IF(AND(D25>0,D25<>""),0,""),(D25-$J25)+$K25+$I25))) -> #REF! | E26: =IF(OR(E25="",E25=0),"",IF(ISBLANK($J25),IF(E25+$K25+$I25-$C$8<=0,IF(AND(E25>0,E25<>""),0,""),E25+$K25+$I25-$C$8),IF((E25-$J25)+$K25+$I25<=0,IF(AND(E25>0,E25<>""),0,""),(E25-$J25)+$K25+$I25))) -> #REF! | F26: =IF(J25="","",IF(G25+F25+H25+I25-J25<0,0,G25+F25+H25+I25-J25)) -> #REF! | H26: =COUNTIFS(#REF!, ">=" &(INT(B26)+1),#REF!, "<" &(INT(B26)+6),#REF!, $C$2,#REF!, "<>BUG") -> #REF!
A27: Semana 14 | B27: =B26+$C$9 -> 46078 | C27: =IF(OR(C26="",C26=0),"",IF(ISBLANK(J26),IF(C26+K26+I26-$C$6<=0,IF(AND(C26>0,C26<>""),0,""),C26+K26+I26-$C$6),IF((C26-J26)+K26+I26<=0,IF(AND(C26>0,C26<>""),0,""),(C26-J26)+K26+I26))) -> #REF! | D27: =IF(OR(D26="",D26=0),"",IF(ISBLANK($J26),IF(D26+$K26+$I26-$C$7<=0,IF(AND(D26>0,D26<>""),0,""),D26+$K26+$I26-$C$7),IF((D26-$J26)+$K26+$I26<=0,IF(AND(D26>0,D26<>""),0,""),(D26-$J26)+$K26+$I26))) -> #REF! | E27: =IF(OR(E26="",E26=0),"",IF(ISBLANK($J26),IF(E26+$K26+$I26-$C$8<=0,IF(AND(E26>0,E26<>""),0,""),E26+$K26+$I26-$C$8),IF((E26-$J26)+$K26+$I26<=0,IF(AND(E26>0,E26<>""),0,""),(E26-$J26)+$K26+$I26))) -> #REF! | F27: =IF(J26="","",IF(G26+F26+H26+I26-J26<0,0,G26+F26+H26+I26-J26)) | H27: =COUNTIFS(#REF!, ">=" &(INT(B27)+1),#REF!, "<" &(INT(B27)+6),#REF!, $C$2,#REF!, "<>BUG") -> #REF!
A28: Semana 15 | B28: =B27+$C$9 -> 46085 | C28: =IF(OR(C27="",C27=0),"",IF(ISBLANK(J27),IF(C27+K27+I27-$C$6<=0,IF(AND(C27>0,C27<>""),0,""),C27+K27+I27-$C$6),IF((C27-J27)+K27+I27<=0,IF(AND(C27>0,C27<>""),0,""),(C27-J27)+K27+I27))) -> #REF! | D28: =IF(OR(D27="",D27=0),"",IF(ISBLANK($J27),IF(D27+$K27+$I27-$C$7<=0,IF(AND(D27>0,D27<>""),0,""),D27+$K27+$I27-$C$7),IF((D27-$J27)+$K27+$I27<=0,IF(AND(D27>0,D27<>""),0,""),(D27-$J27)+$K27+$I27))) -> #REF! | E28: =IF(OR(E27="",E27=0),"",IF(ISBLANK($J27),IF(E27+$K27+$I27-$C$8<=0,IF(AND(E27>0,E27<>""),0,""),E27+$K27+$I27-$C$8),IF((E27-$J27)+$K27+$I27<=0,IF(AND(E27>0,E27<>""),0,""),(E27-$J27)+$K27+$I27))) -> #REF! | F28: =IF(J27="","",IF(G27+F27+H27+I27-J27<0,0,G27+F27+H27+I27-J27)) | H28: =COUNTIFS(#REF!, ">=" &(INT(B28)+1),#REF!, "<" &(INT(B28)+6),#REF!, $C$2,#REF!, "<>BUG") -> #REF!
A29: Semana 16 | B29: =B28+$C$9 -> 46092 | C29: =IF(OR(C28="",C28=0),"",IF(ISBLANK(J28),IF(C28+K28+I28-$C$6<=0,IF(AND(C28>0,C28<>""),0,""),C28+K28+I28-$C$6),IF((C28-J28)+K28+I28<=0,IF(AND(C28>0,C28<>""),0,""),(C28-J28)+K28+I28))) -> #REF! | D29: =IF(OR(D28="",D28=0),"",IF(ISBLANK($J28),IF(D28+$K28+$I28-$C$7<=0,IF(AND(D28>0,D28<>""),0,""),D28+$K28+$I28-$C$7),IF((D28-$J28)+$K28+$I28<=0,IF(AND(D28>0,D28<>""),0,""),(D28-$J28)+$K28+$I28))) -> #REF! | E29: =IF(OR(E28="",E28=0),"",IF(ISBLANK($J28),IF(E28+$K28+$I28-$C$8<=0,IF(AND(E28>0,E28<>""),0,""),E28+$K28+$I28-$C$8),IF((E28-$J28)+$K28+$I28<=0,IF(AND(E28>0,E28<>""),0,""),(E28-$J28)+$K28+$I28))) -> #REF! | F29: =IF(J28="","",IF(G28+F28+H28+I28-J28<0,0,G28+F28+H28+I28-J28)) | H29: =COUNTIFS(#REF!, ">=" &(INT(B29)+1),#REF!, "<" &(INT(B29)+6),#REF!, $C$2,#REF!, "<>BUG") -> #REF!
A30: Semana 17 | B30: =B29+$C$9 -> 46099 | C30: =IF(OR(C29="",C29=0),"",IF(ISBLANK(J29),IF(C29+K29+I29-$C$6<=0,IF(AND(C29>0,C29<>""),0,""),C29+K29+I29-$C$6),IF((C29-J29)+K29+I29<=0,IF(AND(C29>0,C29<>""),0,""),(C29-J29)+K29+I29))) -> #REF! | D30: =IF(OR(D29="",D29=0),"",IF(ISBLANK($J29),IF(D29+$K29+$I29-$C$7<=0,IF(AND(D29>0,D29<>""),0,""),D29+$K29+$I29-$C$7),IF((D29-$J29)+$K29+$I29<=0,IF(AND(D29>0,D29<>""),0,""),(D29-$J29)+$K29+$I29))) -> #REF! | E30: =IF(OR(E29="",E29=0),"",IF(ISBLANK($J29),IF(E29+$K29+$I29-$C$8<=0,IF(AND(E29>0,E29<>""),0,""),E29+$K29+$I29-$C$8),IF((E29-$J29)+$K29+$I29<=0,IF(AND(E29>0,E29<>""),0,""),(E29-$J29)+$K29+$I29))) -> #REF! | F30: =IF(J29="","",IF(G29+F29+H29+I29-J29<0,0,G29+F29+H29+I29-J29)) | H30: =COUNTIFS(#REF!, ">=" &(INT(B30)+1),#REF!, "<" &(INT(B30)+6),#REF!, $C$2,#REF!, "<>BUG") -> #REF!
A31: Semana 18 | B31: =B30+$C$9 -> 46106 | C31: =IF(OR(C30="",C30=0),"",IF(ISBLANK(J30),IF(C30+K30+I30-$C$6<=0,IF(AND(C30>0,C30<>""),0,""),C30+K30+I30-$C$6),IF((C30-J30)+K30+I30<=0,IF(AND(C30>0,C30<>""),0,""),(C30-J30)+K30+I30))) -> #REF! | D31: =IF(OR(D30="",D30=0),"",IF(ISBLANK($J30),IF(D30+$K30+$I30-$C$7<=0,IF(AND(D30>0,D30<>""),0,""),D30+$K30+$I30-$C$7),IF((D30-$J30)+$K30+$I30<=0,IF(AND(D30>0,D30<>""),0,""),(D30-$J30)+$K30+$I30))) -> #REF! | E31: =IF(OR(E30="",E30=0),"",IF(ISBLANK($J30),IF(E30+$K30+$I30-$C$8<=0,IF(AND(E30>0,E30<>""),0,""),E30+$K30+$I30-$C$8),IF((E30-$J30)+$K30+$I30<=0,IF(AND(E30>0,E30<>""),0,""),(E30-$J30)+$K30+$I30))) -> #REF! | F31: =IF(J30="","",IF(G30+F30+H30+I30-J30<0,0,G30+F30+H30+I30-J30)) | H31: =COUNTIFS(#REF!, ">=" &(INT(B31)+1),#REF!, "<" &(INT(B31)+6),#REF!, $C$2,#REF!, "<>BUG") -> #REF!
B32: =B31+$C$9 -> 46113 | C32: =IF(OR(C31="",C31=0),"",IF(ISBLANK(J31),IF(C31+K31+I31-$C$6<=0,IF(AND(C31>0,C31<>""),0,""),C31+K31+I31-$C$6),IF((C31-J31)+K31+I31<=0,IF(AND(C31>0,C31<>""),0,""),(C31-J31)+K31+I31))) -> #REF! | D32: =IF(OR(D31="",D31=0),"",IF(ISBLANK($J31),IF(D31+$K31+$I31-$C$7<=0,IF(AND(D31>0,D31<>""),0,""),D31+$K31+$I31-$C$7),IF((D31-$J31)+$K31+$I31<=0,IF(AND(D31>0,D31<>""),0,""),(D31-$J31)+$K31+$I31))) -> #REF! | E32: =IF(OR(E31="",E31=0),"",IF(ISBLANK($J31),IF(E31+$K31+$I31-$C$8<=0,IF(AND(E31>0,E31<>""),0,""),E31+$K31+$I31-$C$8),IF((E31-$J31)+$K31+$I31<=0,IF(AND(E31>0,E31<>""),0,""),(E31-$J31)+$K31+$I31))) -> #REF! | F32: =IF(J31="","",IF(G31+F31+H31+I31-J31<0,0,G31+F31+H31+I31-J31)) | H32: =COUNTIFS(#REF!, ">=" &(INT(B32)+1),#REF!, "<" &(INT(B32)+6),#REF!, $C$2,#REF!, "<>BUG") -> #REF!
B33: =B32+$C$9 -> 46120 | C33: =IF(OR(C32="",C32=0),"",IF(ISBLANK(J32),IF(C32+K32+I32-$C$6<=0,IF(AND(C32>0,C32<>""),0,""),C32+K32+I32-$C$6),IF((C32-J32)+K32+I32<=0,IF(AND(C32>0,C32<>""),0,""),(C32-J32)+K32+I32))) -> #REF! | D33: =IF(OR(D32="",D32=0),"",IF(ISBLANK($J32),IF(D32+$K32+$I32-$C$7<=0,IF(AND(D32>0,D32<>""),0,""),D32+$K32+$I32-$C$7),IF((D32-$J32)+$K32+$I32<=0,IF(AND(D32>0,D32<>""),0,""),(D32-$J32)+$K32+$I32))) -> #REF! | E33: =IF(OR(E32="",E32=0),"",IF(ISBLANK($J32),IF(E32+$K32+$I32-$C$8<=0,IF(AND(E32>0,E32<>""),0,""),E32+$K32+$I32-$C$8),IF((E32-$J32)+$K32+$I32<=0,IF(AND(E32>0,E32<>""),0,""),(E32-$J32)+$K32+$I32))) -> #REF! | F33: =IF(J32="","",IF(G32+F32+H32+I32-J32<0,0,G32+F32+H32+I32-J32))
B34: =B33+$C$9 -> 46127 | C34: =IF(OR(C33="",C33=0),"",IF(ISBLANK(J33),IF(C33+K33+I33-$C$6<=0,IF(AND(C33>0,C33<>""),0,""),C33+K33+I33-$C$6),IF((C33-J33)+K33+I33<=0,IF(AND(C33>0,C33<>""),0,""),(C33-J33)+K33+I33))) -> #REF! | D34: =IF(OR(D33="",D33=0),"",IF(ISBLANK($J33),IF(D33+$K33+$I33-$C$7<=0,IF(AND(D33>0,D33<>""),0,""),D33+$K33+$I33-$C$7),IF((D33-$J33)+$K33+$I33<=0,IF(AND(D33>0,D33<>""),0,""),(D33-$J33)+$K33+$I33))) -> #REF! | E34: =IF(OR(E33="",E33=0),"",IF(ISBLANK($J33),IF(E33+$K33+$I33-$C$8<=0,IF(AND(E33>0,E33<>""),0,""),E33+$K33+$I33-$C$8),IF((E33-$J33)+$K33+$I33<=0,IF(AND(E33>0,E33<>""),0,""),(E33-$J33)+$K33+$I33))) -> #REF! | F34: =IF(J33="","",IF(G33+F33+H33+I33-J33<0,0,G33+F33+H33+I33-J33))
B35: =B34+$C$9 -> 46134 | C35: =IF(OR(C34="",C34=0),"",IF(ISBLANK(J34),IF(C34+K34+I34-$C$6<=0,IF(AND(C34>0,C34<>""),0,""),C34+K34+I34-$C$6),IF((C34-J34)+K34+I34<=0,IF(AND(C34>0,C34<>""),0,""),(C34-J34)+K34+I34))) -> #REF! | D35: =IF(OR(D34="",D34=0),"",IF(ISBLANK($J34),IF(D34+$K34+$I34-$C$7<=0,IF(AND(D34>0,D34<>""),0,""),D34+$K34+$I34-$C$7),IF((D34-$J34)+$K34+$I34<=0,IF(AND(D34>0,D34<>""),0,""),(D34-$J34)+$K34+$I34))) -> #REF! | E35: =IF(OR(E34="",E34=0),"",IF(ISBLANK($J34),IF(E34+$K34+$I34-$C$8<=0,IF(AND(E34>0,E34<>""),0,""),E34+$K34+$I34-$C$8),IF((E34-$J34)+$K34+$I34<=0,IF(AND(E34>0,E34<>""),0,""),(E34-$J34)+$K34+$I34))) -> #REF! | F35: =IF(J34="","",IF(G34+F34+H34+I34-J34<0,0,G34+F34+H34+I34-J34))
B36: =B35+$C$9 -> 46141 | C36: =IF(OR(C35="",C35=0),"",IF(ISBLANK(J35),IF(C35+K35+I35-$C$6<=0,IF(AND(C35>0,C35<>""),0,""),C35+K35+I35-$C$6),IF((C35-J35)+K35+I35<=0,IF(AND(C35>0,C35<>""),0,""),(C35-J35)+K35+I35))) -> #REF! | D36: =IF(OR(D35="",D35=0),"",IF(ISBLANK($J35),IF(D35+$K35+$I35-$C$7<=0,IF(AND(D35>0,D35<>""),0,""),D35+$K35+$I35-$C$7),IF((D35-$J35)+$K35+$I35<=0,IF(AND(D35>0,D35<>""),0,""),(D35-$J35)+$K35+$I35))) -> #REF! | E36: =IF(OR(E35="",E35=0),"",IF(ISBLANK($J35),IF(E35+$K35+$I35-$C$8<=0,IF(AND(E35>0,E35<>""),0,""),E35+$K35+$I35-$C$8),IF((E35-$J35)+$K35+$I35<=0,IF(AND(E35>0,E35<>""),0,""),(E35-$J35)+$K35+$I35))) -> #REF! | F36: =IF(J35="","",IF(G35+F35+H35+I35-J35<0,0,G35+F35+H35+I35-J35))
B37: =B36+$C$9 -> 46148 | C37: =IF(OR(C36="",C36=0),"",IF(ISBLANK(J36),IF(C36+K36+I36-$C$6<=0,IF(AND(C36>0,C36<>""),0,""),C36+K36+I36-$C$6),IF((C36-J36)+K36+I36<=0,IF(AND(C36>0,C36<>""),0,""),(C36-J36)+K36+I36))) -> #REF! | D37: =IF(OR(D36="",D36=0),"",IF(ISBLANK($J36),IF(D36+$K36+$I36-$C$7<=0,IF(AND(D36>0,D36<>""),0,""),D36+$K36+$I36-$C$7),IF((D36-$J36)+$K36+$I36<=0,IF(AND(D36>0,D36<>""),0,""),(D36-$J36)+$K36+$I36))) -> #REF! | E37: =IF(OR(E36="",E36=0),"",IF(ISBLANK($J36),IF(E36+$K36+$I36-$C$8<=0,IF(AND(E36>0,E36<>""),0,""),E36+$K36+$I36-$C$8),IF((E36-$J36)+$K36+$I36<=0,IF(AND(E36>0,E36<>""),0,""),(E36-$J36)+$K36+$I36))) -> #REF! | F37: =IF(J36="","",IF(G36+F36+H36+I36-J36<0,0,G36+F36+H36+I36-J36))
B38: =B37+$C$9 -> 46155 | C38: =IF(OR(C37="",C37=0),"",IF(ISBLANK(J37),IF(C37+K37+I37-$C$6<=0,IF(AND(C37>0,C37<>""),0,""),C37+K37+I37-$C$6),IF((C37-J37)+K37+I37<=0,IF(AND(C37>0,C37<>""),0,""),(C37-J37)+K37+I37))) -> #REF! | D38: =IF(OR(D37="",D37=0),"",IF(ISBLANK($J37),IF(D37+$K37+$I37-$C$7<=0,IF(AND(D37>0,D37<>""),0,""),D37+$K37+$I37-$C$7),IF((D37-$J37)+$K37+$I37<=0,IF(AND(D37>0,D37<>""),0,""),(D37-$J37)+$K37+$I37))) -> #REF! | E38: =IF(OR(E37="",E37=0),"",IF(ISBLANK($J37),IF(E37+$K37+$I37-$C$8<=0,IF(AND(E37>0,E37<>""),0,""),E37+$K37+$I37-$C$8),IF((E37-$J37)+$K37+$I37<=0,IF(AND(E37>0,E37<>""),0,""),(E37-$J37)+$K37+$I37))) -> #REF! | F38: =IF(J37="","",IF(G37+F37+H37+I37-J37<0,0,G37+F37+H37+I37-J37))
